Workbook

Sheet ReadMe_Methodology
A1: Naukri Saaf — Ghost Job Listing Detector
A2: Real scraped data (LinkedIn + Indeed + Glassdoor via Apify) | Combined Master Workbook
A5: WHAT THIS WORKBOOK IS
A6: This workbook analyzes 3,000 REAL job postings scraped from three platforms to surface listings that
A7: look statistically like "ghost jobs" (postings that are live but not genuinely hiring).
A9: IMPORTANT — READ BEFORE TRUSTING ANY GHOST LABEL
A10: This dataset has NO verified ground truth. Nobody confirmed with these companies whether a given
A11: listing was real or fake. "ghost_label" is a TRANSPARENT PROXY built from 5 observable signals below —
A12: it is a heuristic risk score, not a fact. Treat "Likely Ghost" as "worth a second look," not "confirmed fake."
A14: v2 CORRECTION (why this version differs from the first draft)
A15: The first draft used GLOBAL (whole-dataset) thresholds for 3 of the 5 signals. That silently broke cross-
A16: platform fairness: Indeed jobs are scraped almost the same day they are posted (avg days_live ~0.8), so
... A80: salary figures as directional, not representative of the full market.

Sheet Executive_Dashboard
A1: Executive KPI Dashboard
A2: Naukri Saaf — Combined view across LinkedIn, Indeed & Glassdoor (3,000 real listings)
A4: Total Listings | C4: Likely Ghost | E4: Uncertain | G4: Likely Genuine | I4: Ghost Rate %
A5: =COUNTA(Combined_Data!$A$2:$A$3001) -> 3000 | C5: =COUNTIF(Combined_Data!$AG$2:$AG$3001,"Likely Ghost") -> 146 | E5: =COUNTIF(Combined_Data!$AG$2:$AG$3001,"Uncertain") -> 1543 | G5: =COUNTIF(Combined_Data!$AG$2:$AG$3001,"Likely Genuine") -> 1311 | I5: =COUNTIF(Combined_Data!$AG$2:$AG$3001,"Likely Ghost")/COUNTA(Combined_Data!$A$2:$A$3001)*100 -> 4.8666667
A9: Platform-wise Comparison
A10: Portal | B10: Total Listings | C10: Likely Ghost | D10: Uncertain | E10: Likely Genuine | F10: Ghost Rate % | G10: Avg Days Live | H10: Avg Ghost Score %
A11: LinkedIn | B11: =COUNTIF(Combined_Data!$B$2:$B$3001,"LinkedIn") -> 1000 | C11: =COUNTIFS(Combined_Data!$B$2:$B$3001,"LinkedIn",Combined_Data!$AG$2:$AG$3001,"Likely Ghost") -> 77 | D11: =COUNTIFS(Combined_Data!$B$2:$B$3001,"LinkedIn",Combined_Data!$AG$2:$AG$3001,"Uncertain") -> 669 | E11: =COUNTIFS(Combined_Data!$B$2:$B$3001,"LinkedIn",Combined_Data!$AG$2:$AG$3001,"Likely Genuine") -> 254 | F11: =C11/B11*100 -> 7.7 | G11: =AVERAGEIF(Combined_Data!$B$2:$B$3001,"LinkedIn",Combined_Data!$K$2:$K$3001) -> 40.734 | H11: =AVERAGEIF(Combined_Data!$B$2:$B$3001,"LinkedIn",Combined_Data!$AF$2:$AF$3001) -> 33.1397
A12: Indeed | B12: =COUNTIF(Combined_Data!$B$2:$B$3001,"Indeed") -> 1000 | C12: =COUNTIFS(Combined_Data!$B$2:$B$3001,"Indeed",Combined_Data!$AG$2:$AG$3001,"Likely Ghost") -> 44 | D12: =COUNTIFS(Combined_Data!$B$2:$B$3001,"Indeed",Combined_Data!$AG$2:$AG$3001,"Uncertain") -> 435 | E12: =COUNTIFS(Combined_Data!$B$2:$B$3001,"Indeed",Combined_Data!$AG$2:$AG$3001,"Likely Genuine") -> 521 | F12: =C12/B12*100 -> 4.4 | G12: =AVERAGEIF(Combined_Data!$B$2:$B$3001,"Indeed",Combined_Data!$K$2:$K$3001) -> 0.7631 | H12: =AVERAGEIF(Combined_Data!$B$2:$B$3001,"Indeed",Combined_Data!$AF$2:$AF$3001) -> 24.1054
A13: Glassdoor | B13: =COUNTIF(Combined_Data!$B$2:$B$3001,"Glassdoor") -> 1000 | C13: =COUNTIFS(Combined_Data!$B$2:$B$3001,"Glassdoor",Combined_Data!$AG$2:$AG$3001,"Likely Ghost") -> 25 | D13: =COUNTIFS(Combined_Data!$B$2:$B$3001,"Glassdoor",Combined_Data!$AG$2:$AG$3001,"Uncertain") -> 439 | E13: =COUNTIFS(Combined_Data!$B$2:$B$3001,"Glassdoor",Combined_Data!$AG$2:$AG$3001,"Likely Genuine") -> 536 | F13: =C13/B13*100 -> 2.5 | G13: =AVERAGEIF(Combined_Data!$B$2:$B$3001,"Glassdoor",Combined_Data!$K$2:$K$3001) -> 61.334 | H13: =AVERAGEIF(Combined_Data!$B$2:$B$3001,"Glassdoor",Combined_Data!$AF$2:$AF$3001) -> 21.805
A14: TOTAL | B14: =SUM(B11:B13) -> 3000 | C14: =SUM(C11:C13) -> 146 | D14: =SUM(D11:D13) -> 1543 | E14: =SUM(E11:E13) -> 1311 | F14: =C14/B14*100 -> 4.8666667 | G14: =AVERAGE(Combined_Data!$K$2:$K$3001) -> 34.277033 | H14: =AVERAGE(Combined_Data!$AF$2:$AF$3001) -> 26.350033
A16: Overall Ghost Label Split
A17: Likely Ghost | B17: =COUNTIF(Combined_Data!$AG$2:$AG$3001,"Likely Ghost") -> 146
A18: Uncertain | B18: =COUNTIF(Combined_Data!$AG$2:$AG$3001,"Uncertain") -> 1543
A19: Likely Genuine | B19: =COUNTIF(Combined_Data!$AG$2:$AG$3001,"Likely Genuine") -> 1311

Sheet Company_Explorer
A1: Interactive Company & Job Explorer
A2: Pick a Company / Platform / Role / Ghost Label below — every KPI, chart and row in this sheet updates instantly. No macros, no Excel 365 dynamic-array functions required.
A4: FILTERS (click cell → choose from dropdown)
A5: Company | B5: Infosys | F5: Tip: leave any filter on "All ..." to ignore it. Company list is sorted by posting volume (most-active employers first).
A6: Platform | B6: All Platforms
A7: Role Bucket | B7: All Roles
A8: Ghost Label | B8: All Ghost Labels
A9: KPI SUMMARY (for current filter selection)
A10: Matching Listings | C10: Likely Ghost | E10: Ghost Rate % | G10: Avg Days Live | I10: Avg Ghost Score % | K10: Avg Est. Annual Salary (disclosed)
A11: =SUM(Combined_Data!$AI$2:$AI$3001) -> 24 | C11: =SUMPRODUCT((Combined_Data!$AG$2:$AG$3001="Likely Ghost")*Combined_Data!$AI$2:$AI$3001) -> 0 | E11: =IFERROR(C11/A11*100,0) -> 0 | G11: =IFERROR(SUMPRODUCT(Combined_Data!$K$2:$K$3001*Combined_Data!$AI$2:$AI$3001)/A11,0) -> 3.4083333 | I11: =IFERROR(SUMPRODUCT(Combined_Data!$AF$2:$AF$3001*Combined_Data!$AI$2:$AI$3001)/A11,0) -> 29.195833 | K11: =IFERROR(SUMPRODUCT((Combined_Data!$T$2:$T$3001=TRUE())*Combined_Data!$AI$2:$AI$3001*Combined_Data!$S$2:$S$3001)/SUMPRODUCT((Combined_Data!$T$2:$T$3001=TRUE())*Combined_Data!$AI$2:$AI$3001),0) -> 0
A13: Platform Split (current filter) | F13: Ghost Label Split (current filter)
A14: Portal | B14: Count | F14: Ghost Label | G14: Count
A15: LinkedIn | B15: =SUMPRODUCT((Combined_Data!$B$2:$B$3001="LinkedIn")*Combined_Data!$AI$2:$AI$3001) -> 8 | F15: Likely Ghost | G15: =SUMPRODUCT((Combined_Data!$AG$2:$AG$3001="Likely Ghost")*Combined_Data!$AI$2:$AI$3001) -> 0
A16: Indeed | B16: =SUMPRODUCT((Combined_Data!$B$2:$B$3001="Indeed")*Combined_Data!$AI$2:$AI$3001) -> 16 | F16: Uncertain | G16: =SUMPRODUCT((Combined_Data!$AG$2:$AG$3001="Uncertain")*Combined_Data!$AI$2:$AI$3001) -> 18
A17: Glassdoor | B17: =SUMPRODUCT((Combined_Data!$B$2:$B$3001="Glassdoor")*Combined_Data!$AI$2:$AI$3001) -> 0 | F17: Likely Genuine | G17: =SUMPRODUCT((Combined_Data!$AG$2:$AG$3001="Likely Genuine")*Combined_Data!$AI$2:$AI$3001) -> 6
A33: DETAIL: MATCHING LISTINGS (showing up to first 400 matches — total match count is in the KPI above)
A34: Job Title | B34: Company Name | C34: Portal | D34: Role Bucket | E34: City | F34: Posted Date | G34: Days Live | H34: Experience Level | I34: Salary Disclosed? | J34: Est. Annual Salary | K34: Ghost Score % | L34: Ghost Label | M34: Source URL
A35: =IFERROR(INDEX(Combined_Data!$C:$C,$O35+1),"") -> Full stack Developer (Python with React) | B35: =IFERROR(INDEX(Combined_Data!$E:$E,$O35+1),"") -> Infosys | C35: =IFERROR(INDEX(Combined_Data!$B:$B,$O35+1),"") -> LinkedIn | D35: =IFERROR(INDEX(Combined_Data!$D:$D,$O35+1),"") -> Full Stack Engineer | E35: =IFERROR(INDEX(Combined_Data!$G:$G,$O35+1),"") -> Bengaluru East | F35: =IFERROR(INDEX(Combined_Data!$I:$I,$O35+1),"") -> 46205 | G35: =IFERROR(INDEX(Combined_Data!$K:$K,$O35+1),"") -> 5 | H35: =IFERROR(INDEX(Combined_Data!$M:$M,$O35+1),"") -> Not Applicable | I35: =IFERROR(INDEX(Combined_Data!$N:$N,$O35+1),"") -> FALSE | J35: =IFERROR(INDEX(Combined_Data!$S:$S,$O35+1),"") -> 0 | K35: =IFERROR(INDEX(Combined_Data!$AF:$AF,$O35+1),"") -> 14.3 | L35: =IFERROR(INDEX(Combined_Data!$AG:$AG,$O35+1),"") -> Likely Genuine | M35: =IFERROR(INDEX(Combined_Data!$AH:$AH,$O35+1),"") -> https://in.linkedin.com/jobs/view/full-stack-developer-python-with-react-at-infosys-4435263024?trk=public_jobs_topcard-title | O35: =IFERROR(_xlfn.AGGREGATE(15,6,(ROW(Combined_Data!$AI$2:$AI$3001)-1)/(Combined_Data!$AI$2:$AI$3001),1),"") -> 656
A36: =IFERROR(INDEX(Combined_Data!$C:$C,$O36+1),"") -> Java Developer | B36: =IFERROR(INDEX(Combined_Data!$E:$E,$O36+1),"") -> Infosys | C36: =IFERROR(INDEX(Combined_Data!$B:$B,$O36+1),"") -> LinkedIn | D36: =IFERROR(INDEX(Combined_Data!$D:$D,$O36+1),"") -> Software Engineer | E36: =IFERROR(INDEX(Combined_Data!$G:$G,$O36+1),"") -> Bengaluru East | F36: =IFERROR(INDEX(Combined_Data!$I:$I,$O36+1),"") -> 46203 | G36: =IFERROR(INDEX(Combined_Data!$K:$K,$O36+1),"") -> 7 | H36: =IFERROR(INDEX(Combined_Data!$M:$M,$O36+1),"") -> Not Applicable | I36: =IFERROR(INDEX(Combined_Data!$N:$N,$O36+1),"") -> FALSE | J36: =IFERROR(INDEX(Combined_Data!$S:$S,$O36+1),"") -> 0 | K36: =IFERROR(INDEX(Combined_Data!$AF:$AF,$O36+1),"") -> 28.6 | L36: =IFERROR(INDEX(Combined_Data!$AG:$AG,$O36+1),"") -> Uncertain | M36: =IFERROR(INDEX(Combined_Data!$AH:$AH,$O36+1),"") -> https://in.linkedin.com/jobs/view/java-developer-at-infosys-4434348807?trk=public_jobs_topcard-title | O36: =IFERROR(_xlfn.AGGREGATE(15,6,(ROW(Combined_Data!$AI$2:$AI$3001)-1)/(Combined_Data!$AI$2:$AI$3001),2),"") -> 661
A37: =IFERROR(INDEX(Combined_Data!$C:$C,$O37+1),"") -> Java Developer | B37: =IFERROR(INDEX(Combined_Data!$E:$E,$O37+1),"") -> Infosys | C37: =IFERROR(INDEX(Combined_Data!$B:$B,$O37+1),"") -> LinkedIn | D37: =IFERROR(INDEX(Combined_Data!$D:$D,$O37+1),"") -> Software Engineer | E37: =IFERROR(INDEX(Combined_Data!$G:$G,$O37+1),"") -> Bengaluru East | F37: =IFERROR(INDEX(Combined_Data!$I:$I,$O37+1),"") -> 46203 | G37: =IFERROR(INDEX(Combined_Data!$K:$K,$O37+1),"") -> 7 | H37: =IFERROR(INDEX(Combined_Data!$M:$M,$O37+1),"") -> Not Applicable | I37: =IFERROR(INDEX(Combined_Data!$N:$N,$O37+1),"") -> FALSE | J37: =IFERROR(INDEX(Combined_Data!$S:$S,$O37+1),"") -> 0 | K37: =IFERROR(INDEX(Combined_Data!$AF:$AF,$O37+1),"") -> 14.3 | L37: =IFERROR(INDEX(Combined_Data!$AG:$AG,$O37+1),"") -> Likely Genuine | M37: =IFERROR(INDEX(Combined_Data!$AH:$AH,$O37+1),"") -> https://in.linkedin.com/jobs/view/java-developer-at-infosys-4434302723?trk=public_jobs_topcard-title | O37: =IFERROR(_xlfn.AGGREGATE(15,6,(ROW(Combined_Data!$AI$2:$AI$3001)-1)/(Combined_Data!$AI$2:$AI$3001),3),"") -> 663
A38: =IFERROR(INDEX(Combined_Data!$C:$C,$O38+1),"") -> Java Springboot Developer | B38: =IFERROR(INDEX(Combined_Data!$E:$E,$O38+1),"") -> Infosys | C38: =IFERROR(INDEX(Combined_Data!$B:$B,$O38+1),"") -> LinkedIn | D38: =IFERROR(INDEX(Combined_Data!$D:$D,$O38+1),"") -> Software Engineer | E38: =IFERROR(INDEX(Combined_Data!$G:$G,$O38+1),"") -> Bengaluru East | F38: =IFERROR(INDEX(Combined_Data!$I:$I,$O38+1),"") -> 46200 | G38: =IFERROR(INDEX(Combined_Data!$K:$K,$O38+1),"") -> 10 | H38: =IFERROR(INDEX(Combined_Data!$M:$M,$O38+1),"") -> Not Applicable | I38: =IFERROR(INDEX(Combined_Data!$N:$N,$O38+1),"") -> FALSE | J38: =IFERROR(INDEX(Combined_Data!$S:$S,$O38+1),"") -> 0 | K38: =IFERROR(INDEX(Combined_Data!$AF:$AF,$O38+1),"") -> 14.3 | L38: =IFERROR(INDEX(Combined_Data!$AG:$AG,$O38+1),"") -> Likely Genuine | M38: =IFERROR(INDEX(Combined_Data!$AH:$AH,$O38+1),"") -> https://in.linkedin.com/jobs/view/java-springboot-developer-at-infosys-4433476671?trk=public_jobs_topcard-title | O38: =IFERROR(_xlfn.AGGREGATE(15,6,(ROW(Combined_Data!$AI$2:$AI$3001)-1)/(Combined_Data!$AI$2:$AI$3001),4),"") -> 687
A39: =IFERROR(INDEX(Combined_Data!$C:$C,$O39+1),"") -> Java Developer | B39: =IFERROR(INDEX(Combined_Data!$E:$E,$O39+1),"") -> Infosys | C39: =IFERROR(INDEX(Combined_Data!$B:$B,$O39+1),"") -> LinkedIn | D39: =IFERROR(INDEX(Combined_Data!$D:$D,$O39+1),"") -> Software Engineer | E39: =IFERROR(INDEX(Combined_Data!$G:$G,$O39+1),"") -> Bengaluru East | F39: =IFERROR(INDEX(Combined_Data!$I:$I,$O39+1),"") -> 46201 | G39: =IFERROR(INDEX(Combined_Data!$K:$K,$O39+1),"") -> 9 | H39: =IFERROR(INDEX(Combined_Data!$M:$M,$O39+1),"") -> Not Applicable | I39: =IFERROR(INDEX(Combined_Data!$N:$N,$O39+1),"") -> FALSE | J39: =IFERROR(INDEX(Combined_Data!$S:$S,$O39+1),"") -> 0 | K39: =IFERROR(INDEX(Combined_Data!$AF:$AF,$O39+1),"") -> 14.3 | L39: =IFERROR(INDEX(Combined_Data!$AG:$AG,$O39+1),"") -> Likely Genuine | M39: =IFERROR(INDEX(Combined_Data!$AH:$AH,$O39+1),"") -> https://in.linkedin.com/jobs/view/java-developer-at-infosys-4433627403?trk=public_jobs_topcard-title | O39: =IFERROR(_xlfn.AGGREGATE(15,6,(ROW(Combined_Data!$AI$2:$AI$3001)-1)/(Combined_Data!$AI$2:$AI$3001),5),"") -> 699
A40: =IFERROR(INDEX(Combined_Data!$C:$C,$O40+1),"") -> React.js Developer | B40: =IFERROR(INDEX(Combined_Data!$E:$E,$O40+1),"") -> Infosys | C40: =IFERROR(INDEX(Combined_Data!$B:$B,$O40+1),"") -> LinkedIn | D40: =IFERROR(INDEX(Combined_Data!$D:$D,$O40+1),"") -> Software Engineer | E40: =IFERROR(INDEX(Combined_Data!$G:$G,$O40+1),"") -> Hyderabad | F40: =IFERROR(INDEX(Combined_Data!$I:$I,$O40+1),"") -> 46200 | G40: =IFERROR(INDEX(Combined_Data!$K:$K,$O40+1),"") -> 10 | H40: =IFERROR(INDEX(Combined_Data!$M:$M,$O40+1),"") -> Not Applicable | I40: =IFERROR(INDEX(Combined_Data!$N:$N,$O40+1),"") -> FALSE | J40: =IFERROR(INDEX(Combined_Data!$S:$S,$O40+1),"") -> 0 | K40: =IFERROR(INDEX(Combined_Data!$AF:$AF,$O40+1),"") -> 14.3 | L40: =IFERROR(INDEX(Combined_Data!$AG:$AG,$O40+1),"") -> Likely Genuine | M40: =IFERROR(INDEX(Combined_Data!$AH:$AH,$O40+1),"") -> https://in.linkedin.com/jobs/view/react-js-developer-at-infosys-4433471833?trk=public_jobs_topcard-title | O40: =IFERROR(_xlfn.AGGREGATE(15,6,(ROW(Combined_Data!$AI$2:$AI$3001)-1)/(Combined_Data!$AI$2:$AI$3001),6),"") -> 714
A41: =IFERROR(INDEX(Combined_Data!$C:$C,$O41+1),"") -> Node JS, Graph QL, AWS/Azure Developer | B41: =IFERROR(INDEX(Combined_Data!$E:$E,$O41+1),"") -> Infosys | C41: =IFERROR(INDEX(Combined_Data!$B:$B,$O41+1),"") -> LinkedIn | D41: =IFERROR(INDEX(Combined_Data!$D:$D,$O41+1),"") -> Software Engineer | E41: =IFERROR(INDEX(Combined_Data!$G:$G,$O41+1),"") -> Pune Division | F41: =IFERROR(INDEX(Combined_Data!$I:$I,$O41+1),"") -> 46203 | G41: =IFERROR(INDEX(Combined_Data!$K:$K,$O41+1),"") -> 7 | H41: =IFERROR(INDEX(Combined_Data!$M:$M,$O41+1),"") -> Not Applicable | I41: =IFERROR(INDEX(Combined_Data!$N:$N,$O41+1),"") -> FALSE | J41: =IFERROR(INDEX(Combined_Data!$S:$S,$O41+1),"") -> 0 | K41: =IFERROR(INDEX(Combined_Data!$AF:$AF,$O41+1),"") -> 14.3 | L41: =IFERROR(INDEX(Combined_Data!$AG:$AG,$O41+1),"") -> Likely Genuine | M41: =IFERROR(INDEX(Combined_Data!$AH:$AH,$O41+1),"") -> https://in.linkedin.com/jobs/view/node-js-graph-ql-aws-azure-developer-at-infosys-4434341886?trk=public_jobs_topcard-title | O41: =IFERROR(_xlfn.AGGREGATE(15,6,(ROW(Combined_Data!$AI$2:$AI$3001)-1)/(Combined_Data!$AI$2:$AI$3001),7),"") -> 750
A42: =IFERROR(INDEX(Combined_Data!$C:$C,$O42+1),"") -> Java full stack, React Developer | B42: =IFERROR(INDEX(Combined_Data!$E:$E,$O42+1),"") -> Infosys | C42: =IFERROR(INDEX(Combined_Data!$B:$B,$O42+1),"") -> LinkedIn | D42: =IFERROR(INDEX(Combined_Data!$D:$D,$O42+1),"") -> Full Stack Engineer | E42: =IFERROR(INDEX(Combined_Data!$G:$G,$O42+1),"") -> Bengaluru East | F42: =IFERROR(INDEX(Combined_Data!$I:$I,$O42+1),"") -> 46203 | G42: =IFERROR(INDEX(Combined_Data!$K:$K,$O42+1),"") -> 7 | H42: =IFERROR(INDEX(Combined_Data!$M:$M,$O42+1),"") -> Not Applicable | I42: =IFERROR(INDEX(Combined_Data!$N:$N,$O42+1),"") -> FALSE | J42: =IFERROR(INDEX(Combined_Data!$S:$S,$O42+1),"") -> 0 | K42: =IFERROR(INDEX(Combined_Data!$AF:$AF,$O42+1),"") -> 28.6 | L42: =IFERROR(INDEX(Combined_Data!$AG:$AG,$O42+1),"") -> Uncertain | M42: =IFERROR(INDEX(Combined_Data!$AH:$AH,$O42+1),"") -> https://in.linkedin.com/jobs/view/java-full-stack-react-developer-at-infosys-4434904987?trk=public_jobs_topcard-title | O42: =IFERROR(_xlfn.AGGREGATE(15,6,(ROW(Combined_Data!$AI$2:$AI$3001)-1)/(Combined_Data!$AI$2:$AI$3001),8),"") -> 839
A43: =IFERROR(INDEX(Combined_Data!$C:$C,$O43+1),"") -> Healthcare Business Analyst | B43: =IFERROR(INDEX(Combined_Data!$E:$E,$O43+1),"") -> Infosys | C43: =IFERROR(INDEX(Combined_Data!$B:$B,$O43+1),"") -> Indeed | D43: =IFERROR(INDEX(Combined_Data!$D:$D,$O43+1),"") -> Data Analyst | E43: =IFERROR(INDEX(Combined_Data!$G:$G,$O43+1),"") -> Not Specified | F43: =IFERROR(INDEX(Combined_Data!$I:$I,$O43+1),"") -> 46210.222 | G43: =IFERROR(INDEX(Combined_Data!$K:$K,$O43+1),"") -> 0.1 | H43: =IFERROR(INDEX(Combined_Data!$M:$M,$O43+1),"") -> Not Captured by Scraper | I43: =IFERROR(INDEX(Combined_Data!$N:$N,$O43+1),"") -> FALSE | J43: =IFERROR(INDEX(Combined_Data!$S:$S,$O43+1),"") -> 0 | K43: =IFERROR(INDEX(Combined_Data!$AF:$AF,$O43+1),"") -> 28.6 | L43: =IFERROR(INDEX(Combined_Data!$AG:$AG,$O43+1),"") -> Uncertain | M43: =IFERROR(INDEX(Combined_Data!$AH:$AH,$O43+1),"") -> https://indeed.com/viewjob?jk=45af8ba21046d880 | O43: =IFERROR(_xlfn.AGGREGATE(15,6,(ROW(Combined_Data!$AI$2:$AI$3001)-1)/(Combined_Data!$AI$2:$AI$3001),9),"") -> 1035
A44: =IFERROR(INDEX(Combined_Data!$C:$C,$O44+1),"") -> Python & InManta Automation | B44: =IFERROR(INDEX(Combined_Data!$E:$E,$O44+1),"") -> Infosys | C44: =IFERROR(INDEX(Combined_Data!$B:$B,$O44+1),"") -> Indeed | D44: =IFERROR(INDEX(Combined_Data!$D:$D,$O44+1),"") -> Other | E44: =IFERROR(INDEX(Combined_Data!$G:$G,$O44+1),"") -> Not Specified | F44: =IFERROR(INDEX(Combined_Data!$I:$I,$O44+1),"") -> 46210.223 | G44: =IFERROR(INDEX(Combined_Data!$K:$K,$O44+1),"") -> 0.1 | H44: =IFERROR(INDEX(Combined_Data!$M:$M,$O44+1),"") -> Not Captured by Scraper | I44: =IFERROR(INDEX(Combined_Data!$N:$N,$O44+1),"") -> FALSE | J44: =IFERROR(INDEX(Combined_Data!$S:$S,$O44+1),"") -> 0 | K44: =IFERROR(INDEX(Combined_Data!$AF:$AF,$O44+1),"") -> 28.6 | L44: =IFERROR(INDEX(Combined_Data!$AG:$AG,$O44+1),"") -> Uncertain | M44: =IFERROR(INDEX(Combined_Data!$AH:$AH,$O44+1),"") -> https://indeed.com/viewjob?jk=13396b5c08f1e021 | O44: =IFERROR(_xlfn.AGGREGATE(15,6,(ROW(Combined_Data!$AI$2:$AI$3001)-1)/(Combined_Data!$AI$2:$AI$3001),10),"") -> 1153
A45: =IFERROR(INDEX(Combined_Data!$C:$C,$O45+1),"") -> Agentic AI Engineer | B45: =IFERROR(INDEX(Combined_Data!$E:$E,$O45+1),"") -> Infosys | C45: =IFERROR(INDEX(Combined_Data!$B:$B,$O45+1),"") -> Indeed | D45: =IFERROR(INDEX(Combined_Data!$D:$D,$O45+1),"") -> ML Engineer | E45: =IFERROR(INDEX(Combined_Data!$G:$G,$O45+1),"") -> Not Specified | F45: =IFERROR(INDEX(Combined_Data!$I:$I,$O45+1),"") -> 46210.223 | G45: =IFERROR(INDEX(Combined_Data!$K:$K,$O45+1),"") -> 0.1 | H45: =IFERROR(INDEX(Combined_Data!$M:$M,$O45+1),"") -> Not Captured by Scraper | I45: =IFERROR(INDEX(Combined_Data!$N:$N,$O45+1),"") -> FALSE | J45: =IFERROR(INDEX(Combined_Data!$S:$S,$O45+1),"") -> 0 | K45: =IFERROR(INDEX(Combined_Data!$AF:$AF,$O45+1),"") -> 28.6 | L45: =IFERROR(INDEX(Combined_Data!$AG:$AG,$O45+1),"") -> Uncertain | M45: =IFERROR(INDEX(Combined_Data!$AH:$AH,$O45+1),"") -> https://indeed.com/viewjob?jk=63743131dcf8d453 | O45: =IFERROR(_xlfn.AGGREGATE(15,6,(ROW(Combined_Data!$AI$2:$AI$3001)-1)/(Combined_Data!$AI$2:$AI$3001),11),"") -> 1154
A46: =IFERROR(INDEX(Combined_Data!$C:$C,$O46+1),"") -> Agentic AI Engineer | B46: =IFERROR(INDEX(Combined_Data!$E:$E,$O46+1),"") -> Infosys | C46: =IFERROR(INDEX(Combined_Data!$B:$B,$O46+1),"") -> Indeed | D46: =IFERROR(INDEX(Combined_Data!$D:$D,$O46+1),"") -> ML Engineer | E46: =IFERROR(INDEX(Combined_Data!$G:$G,$O46+1),"") -> Not Specified | F46: =IFERROR(INDEX(Combined_Data!$I:$I,$O46+1),"") -> 46210.223 | G46: =IFERROR(INDEX(Combined_Data!$K:$K,$O46+1),"") -> 0.1 | H46: =IFERROR(INDEX(Combined_Data!$M:$M,$O46+1),"") -> Not Captured by Scraper | I46: =IFERROR(INDEX(Combined_Data!$N:$N,$O46+1),"") -> FALSE | J46: =IFERROR(INDEX(Combined_Data!$S:$S,$O46+1),"") -> 0 | K46: =IFERROR(INDEX(Combined_Data!$AF:$AF,$O46+1),"") -> 28.6 | L46: =IFERROR(INDEX(Combined_Data!$AG:$AG,$O46+1),"") -> Uncertain | M46: =IFERROR(INDEX(Combined_Data!$AH:$AH,$O46+1),"") -> https://indeed.com/viewjob?jk=8490dafc143b3dc8 | O46: =IFERROR(_xlfn.AGGREGATE(15,6,(ROW(Combined_Data!$AI$2:$AI$3001)-1)/(Combined_Data!$AI$2:$AI$3001),12),"") -> 1246
A47: =IFERROR(INDEX(Combined_Data!$C:$C,$O47+1),"") -> Senior Snowflake Data Engineer – DBT & Power BI | B47: =IFERROR(INDEX(Combined_Data!$E:$E,$O47+1),"") -> Infosys | C47: =IFERROR(INDEX(Combined_Data!$B:$B,$O47+1),"") -> Indeed | D47: =IFERROR(INDEX(Combined_Data!$D:$D,$O47+1),"") -> Data Engineer | E47: =IFERROR(INDEX(Combined_Data!$G:$G,$O47+1),"") -> Not Specified | F47: =IFERROR(INDEX(Combined_Data!$I:$I,$O47+1),"") -> 46206.723 | G47: =IFERROR(INDEX(Combined_Data!$K:$K,$O47+1),"") -> 3.6 | H47: =IFERROR(INDEX(Combined_Data!$M:$M,$O47+1),"") -> Not Captured by Scraper | I47: =IFERROR(INDEX(Combined_Data!$N:$N,$O47+1),"") -> FALSE | J47: =IFERROR(INDEX(Combined_Data!$S:$S,$O47+1),"") -> 0 | K47: =IFERROR(INDEX(Combined_Data!$AF:$AF,$O47+1),"") -> 42.9 | L47: =IFERROR(INDEX(Combined_Data!$AG:$AG,$O47+1),"") -> Uncertain | M47: =IFERROR(INDEX(Combined_Data!$AH:$AH,$O47+1),"") -> https://indeed.com/viewjob?jk=fbd25b69e715c7e5 | O47: =IFERROR(_xlfn.AGGREGATE(15,6,(ROW(Combined_Data!$AI$2:$AI$3001)-1)/(Combined_Data!$AI$2:$AI$3001),13),"") -> 1839
A48: =IFERROR(INDEX(Combined_Data!$C:$C,$O48+1),"") -> Business analyst - Regulatory reporting | B48: =IFERROR(INDEX(Combined_Data!$E:$E,$O48+1),"") -> Infosys | C48: =IFERROR(INDEX(Combined_Data!$B:$B,$O48+1),"") -> Indeed | D48: =IFERROR(INDEX(Combined_Data!$D:$D,$O48+1),"") -> Data Analyst | E48: =IFERROR(INDEX(Combined_Data!$G:$G,$O48+1),"") -> Not Specified | F48: =IFERROR(INDEX(Combined_Data!$I:$I,$O48+1),"") -> 46205.973 | G48: =IFERROR(INDEX(Combined_Data!$K:$K,$O48+1),"") -> 4.3 | H48: =IFERROR(INDEX(Combined_Data!$M:$M,$O48+1),"") -> Not Captured by Scraper | I48: =IFERROR(INDEX(Combined_Data!$N:$N,$O48+1),"") -> FALSE | J48: =IFERROR(INDEX(Combined_Data!$S:$S,$O48+1),"") -> 0 | K48: =IFERROR(INDEX(Combined_Data!$AF:$AF,$O48+1),"") -> 42.9 | L48: =IFERROR(INDEX(Combined_Data!$AG:$AG,$O48+1),"") -> Uncertain | M48: =IFERROR(INDEX(Combined_Data!$AH:$AH,$O48+1),"") -> https://indeed.com/viewjob?jk=8291b9483fde94dc | O48: =IFERROR(_xlfn.AGGREGATE(15,6,(ROW(Combined_Data!$AI$2:$AI$3001)-1)/(Combined_Data!$AI$2:$AI$3001),14),"") -> 1930
A49: =IFERROR(INDEX(Combined_Data!$C:$C,$O49+1),"") -> Power Bi Admin | B49: =IFERROR(INDEX(Combined_Data!$E:$E,$O49+1),"") -> Infosys | C49: =IFERROR(INDEX(Combined_Data!$B:$B,$O49+1),"") -> Indeed | D49: =IFERROR(INDEX(Combined_Data!$D:$D,$O49+1),"") -> Other | E49: =IFERROR(INDEX(Combined_Data!$G:$G,$O49+1),"") -> Not Specified | F49: =IFERROR(INDEX(Combined_Data!$I:$I,$O49+1),"") -> 46205.973 | G49: =IFERROR(INDEX(Combined_Data!$K:$K,$O49+1),"") -> 4.3 | H49: =IFERROR(INDEX(Combined_Data!$M:$M,$O49+1),"") -> Not Captured by Scraper | I49: =IFERROR(INDEX(Combined_Data!$N:$N,$O49+1),"") -> FALSE | J49: =IFERROR(INDEX(Combined_Data!$S:$S,$O49+1),"") -> 0 | K49: =IFERROR(INDEX(Combined_Data!$AF:$AF,$O49+1),"") -> 28.6 | L49: =IFERROR(INDEX(Combined_Data!$AG:$AG,$O49+1),"") -> Uncertain | M49: =IFERROR(INDEX(Combined_Data!$AH:$AH,$O49+1),"") -> https://indeed.com/viewjob?jk=11262d6203dd79e8 | O49: =IFERROR(_xlfn.AGGREGATE(15,6,(ROW(Combined_Data!$AI$2:$AI$3001)-1)/(Combined_Data!$AI$2:$AI$3001),15),"") -> 1932
A50: =IFERROR(INDEX(Combined_Data!$C:$C,$O50+1),"") -> .Net Full Stack | B50: =IFERROR(INDEX(Combined_Data!$E:$E,$O50+1),"") -> Infosys | C50: =IFERROR(INDEX(Combined_Data!$B:$B,$O50+1),"") -> Indeed | D50: =IFERROR(INDEX(Combined_Data!$D:$D,$O50+1),"") -> Full Stack Engineer | E50: =IFERROR(INDEX(Combined_Data!$G:$G,$O50+1),"") -> Not Specified | F50: =IFERROR(INDEX(Combined_Data!$I:$I,$O50+1),"") -> 46209.473 | G50: =IFERROR(INDEX(Combined_Data!$K:$K,$O50+1),"") -> 0.8 | H50: =IFERROR(INDEX(Combined_Data!$M:$M,$O50+1),"") -> Not Captured by Scraper | I50: =IFERROR(INDEX(Combined_Data!$N:$N,$O50+1),"") -> FALSE | J50: =IFERROR(INDEX(Combined_Data!$S:$S,$O50+1),"") -> 0 | K50: =IFERROR(INDEX(Combined_Data!$AF:$AF,$O50+1),"") -> 42.9 | L50: =IFERROR(INDEX(Combined_Data!$AG:$AG,$O50+1),"") -> Uncertain | M50: =IFERROR(INDEX(Combined_Data!$AH:$AH,$O50+1),"") -> https://indeed.com/viewjob?jk=82530a1f7f3227d3 | O50: =IFERROR(_xlfn.AGGREGATE(15,6,(ROW(Combined_Data!$AI$2:$AI$3001)-1)/(Combined_Data!$AI$2:$AI$3001),16),"") -> 1957
A51: =IFERROR(INDEX(Combined_Data!$C:$C,$O51+1),"") -> Java Full Stack | B51: =IFERROR(INDEX(Combined_Data!$E:$E,$O51+1),"") -> Infosys | C51: =IFERROR(INDEX(Combined_Data!$B:$B,$O51+1),"") -> Indeed | D51: =IFERROR(INDEX(Combined_Data!$D:$D,$O51+1),"") -> Full Stack Engineer | E51: =IFERROR(INDEX(Combined_Data!$G:$G,$O51+1),"") -> Not Specified | F51: =IFERROR(INDEX(Combined_Data!$I:$I,$O51+1),"") -> 46209.473 | G51: =IFERROR(INDEX(Combined_Data!$K:$K,$O51+1),"") -> 0.8 | H51: =IFERROR(INDEX(Combined_Data!$M:$M,$O51+1),"") -> Not Captured by Scraper | I51: =IFERROR(INDEX(Combined_Data!$N:$N,$O51+1),"") -> FALSE | J51: =IFERROR(INDEX(Combined_Data!$S:$S,$O51+1),"") -> 0 | K51: =IFERROR(INDEX(Combined_Data!$AF:$AF,$O51+1),"") -> 42.9 | L51: =IFERROR(INDEX(Combined_Data!$AG:$AG,$O51+1),"") -> Uncertain | M51: =IFERROR(INDEX(Combined_Data!$AH:$AH,$O51+1),"") -> https://indeed.com/viewjob?jk=f40e3fa4d1983453 | O51: =IFERROR(_xlfn.AGGREGATE(15,6,(ROW(Combined_Data!$AI$2:$AI$3001)-1)/(Combined_Data!$AI$2:$AI$3001),17),"") -> 1962
A52: =IFERROR(INDEX(Combined_Data!$C:$C,$O52+1),"") -> Production Support - Java | B52: =IFERROR(INDEX(Combined_Data!$E:$E,$O52+1),"") -> Infosys | C52: =IFERROR(INDEX(Combined_Data!$B:$B,$O52+1),"") -> Indeed | D52: =IFERROR(INDEX(Combined_Data!$D:$D,$O52+1),"") -> Other | E52: =IFERROR(INDEX(Combined_Data!$G:$G,$O52+1),"") -> Not Specified | F52: =IFERROR(INDEX(Combined_Data!$I:$I,$O52+1),"") -> 46209.473 | G52: =IFERROR(INDEX(Combined_Data!$K:$K,$O52+1),"") -> 0.8 | H52: =IFERROR(INDEX(Combined_Data!$M:$M,$O52+1),"") -> Not Captured by Scraper | I52: =IFERROR(INDEX(Combined_Data!$N:$N,$O52+1),"") -> FALSE | J52: =IFERROR(INDEX(Combined_Data!$S:$S,$O52+1),"") -> 0 | K52: =IFERROR(INDEX(Combined_Data!$AF:$AF,$O52+1),"") -> 42.9 | L52: =IFERROR(INDEX(Combined_Data!$AG:$AG,$O52+1),"") -> Uncertain | M52: =IFERROR(INDEX(Combined_Data!$AH:$AH,$O52+1),"") -> https://indeed.com/viewjob?jk=da3afae1e4e530bd | O52: =IFERROR(_xlfn.AGGREGATE(15,6,(ROW(Combined_Data!$AI$2:$AI$3001)-1)/(Combined_Data!$AI$2:$AI$3001),18),"") -> 1966
A53: =IFERROR(INDEX(Combined_Data!$C:$C,$O53+1),"") -> IT Consulting | B53: =IFERROR(INDEX(Combined_Data!$E:$E,$O53+1),"") -> Infosys | C53: =IFERROR(INDEX(Combined_Data!$B:$B,$O53+1),"") -> Indeed | D53: =IFERROR(INDEX(Combined_Data!$D:$D,$O53+1),"") -> Other | E53: =IFERROR(INDEX(Combined_Data!$G:$G,$O53+1),"") -> Not Specified | F53: =IFERROR(INDEX(Combined_Data!$I:$I,$O53+1),"") -> 46209.473 | G53: =IFERROR(INDEX(Combined_Data!$K:$K,$O53+1),"") -> 0.8 | H53: =IFERROR(INDEX(Combined_Data!$M:$M,$O53+1),"") -> Not Captured by Scraper | I53: =IFERROR(INDEX(Combined_Data!$N:$N,$O53+1),"") -> FALSE | J53: =IFERROR(INDEX(Combined_Data!$S:$S,$O53+1),"") -> 0 | K53: =IFERROR(INDEX(Combined_Data!$AF:$AF,$O53+1),"") -> 42.9 | L53: =IFERROR(INDEX(Combined_Data!$AG:$AG,$O53+1),"") -> Uncertain | M53: =IFERROR(INDEX(Combined_Data!$AH:$AH,$O53+1),"") -> https://indeed.com/viewjob?jk=0f484b58a9d28673 | O53: =IFERROR(_xlfn.AGGREGATE(15,6,(ROW(Combined_Data!$AI$2:$AI$3001)-1)/(Combined_Data!$AI$2:$AI$3001),19),"") -> 1967
A54: =IFERROR(INDEX(Combined_Data!$C:$C,$O54+1),"") -> SAP ABAP Developer | B54: =IFERROR(INDEX(Combined_Data!$E:$E,$O54+1),"") -> Infosys | C54: =IFERROR(INDEX(Combined_Data!$B:$B,$O54+1),"") -> Indeed | D54: =IFERROR(INDEX(Combined_Data!$D:$D,$O54+1),"") -> Software Engineer | E54: =IFERROR(INDEX(Combined_Data!$G:$G,$O54+1),"") -> Not Specified | F54: =IFERROR(INDEX(Combined_Data!$I:$I,$O54+1),"") -> 46209.473 | G54: =IFERROR(INDEX(Combined_Data!$K:$K,$O54+1),"") -> 0.8 | H54: =IFERROR(INDEX(Combined_Data!$M:$M,$O54+1),"") -> Not Captured by Scraper | I54: =IFERROR(INDEX(Combined_Data!$N:$N,$O54+1),"") -> FALSE | J54: =IFERROR(INDEX(Combined_Data!$S:$S,$O54+1),"") -> 0 | K54: =IFERROR(INDEX(Combined_Data!$AF:$AF,$O54+1),"") -> 28.6 | L54: =IFERROR(INDEX(Combined_Data!$AG:$AG,$O54+1),"") -> Uncertain | M54: =IFERROR(INDEX(Combined_Data!$AH:$AH,$O54+1),"") -> https://indeed.com/viewjob?jk=46adcd1840e7e2eb | O54: =IFERROR(_xlfn.AGGREGATE(15,6,(ROW(Combined_Data!$AI$2:$AI$3001)-1)/(Combined_Data!$AI$2:$AI$3001),20),"") -> 1969
A55: =IFERROR(INDEX(Combined_Data!$C:$C,$O55+1),"") -> Production Support - .Net II | B55: =IFERROR(INDEX(Combined_Data!$E:$E,$O55+1),"") -> Infosys | C55: =IFERROR(INDEX(Combined_Data!$B:$B,$O55+1),"") -> Indeed | D55: =IFERROR(INDEX(Combined_Data!$D:$D,$O55+1),"") -> Other | E55: =IFERROR(INDEX(Combined_Data!$G:$G,$O55+1),"") -> Not Specified | F55: =IFERROR(INDEX(Combined_Data!$I:$I,$O55+1),"") -> 46209.473 | G55: =IFERROR(INDEX(Combined_Data!$K:$K,$O55+1),"") -> 0.8 | H55: =IFERROR(INDEX(Combined_Data!$M:$M,$O55+1),"") -> Not Captured by Scraper | I55: =IFERROR(INDEX(Combined_Data!$N:$N,$O55+1),"") -> FALSE | J55: =IFERROR(INDEX(Combined_Data!$S:$S,$O55+1),"") -> 0 | K55: =IFERROR(INDEX(Combined_Data!$AF:$AF,$O55+1),"") -> 28.6 | L55: =IFERROR(INDEX(Combined_Data!$AG:$AG,$O55+1),"") -> Uncertain | M55: =IFERROR(INDEX(Combined_Data!$AH:$AH,$O55+1),"") -> https://indeed.com/viewjob?jk=b8e1e5faf4c6aeb6 | O55: =IFERROR(_xlfn.AGGREGATE(15,6,(ROW(Combined_Data!$AI$2:$AI$3001)-1)/(Combined_Data!$AI$2:$AI$3001),21),"") -> 1973
A56: =IFERROR(INDEX(Combined_Data!$C:$C,$O56+1),"") -> Senior Systems Engineer | B56: =IFERROR(INDEX(Combined_Data!$E:$E,$O56+1),"") -> Infosys | C56: =IFERROR(INDEX(Combined_Data!$B:$B,$O56+1),"") -> Indeed | D56: =IFERROR(INDEX(Combined_Data!$D:$D,$O56+1),"") -> Other | E56: =IFERROR(INDEX(Combined_Data!$G:$G,$O56+1),"") -> Not Specified | F56: =IFERROR(INDEX(Combined_Data!$I:$I,$O56+1),"") -> 46209.473 | G56: =IFERROR(INDEX(Combined_Data!$K:$K,$O56+1),"") -> 0.8 | H56: =IFERROR(INDEX(Combined_Data!$M:$M,$O56+1),"") -> Not Captured by Scraper | I56: =IFERROR(INDEX(Combined_Data!$N:$N,$O56+1),"") -> FALSE | J56: =IFERROR(INDEX(Combined_Data!$S:$S,$O56+1),"") -> 0 | K56: =IFERROR(INDEX(Combined_Data!$AF:$AF,$O56+1),"") -> 42.9 | L56: =IFERROR(INDEX(Combined_Data!$AG:$AG,$O56+1),"") -> Uncertain | M56: =IFERROR(INDEX(Combined_Data!$AH:$AH,$O56+1),"") -> https://indeed.com/viewjob?jk=4f4f5f2faee25402 | O56: =IFERROR(_xlfn.AGGREGATE(15,6,(ROW(Combined_Data!$AI$2:$AI$3001)-1)/(Combined_Data!$AI$2:$AI$3001),22),"") -> 1977
A57: =IFERROR(INDEX(Combined_Data!$C:$C,$O57+1),"") -> Production Support - .Net | B57: =IFERROR(INDEX(Combined_Data!$E:$E,$O57+1),"") -> Infosys | C57: =IFERROR(INDEX(Combined_Data!$B:$B,$O57+1),"") -> Indeed | D57: =IFERROR(INDEX(Combined_Data!$D:$D,$O57+1),"") -> Other | E57: =IFERROR(INDEX(Combined_Data!$G:$G,$O57+1),"") -> Not Specified | F57: =IFERROR(INDEX(Combined_Data!$I:$I,$O57+1),"") -> 46209.473 | G57: =IFERROR(INDEX(Combined_Data!$K:$K,$O57+1),"") -> 0.8 | H57: =IFERROR(INDEX(Combined_Data!$M:$M,$O57+1),"") -> Not Captured by Scraper | I57: =IFERROR(INDEX(Combined_Data!$N:$N,$O57+1),"") -> FALSE | J57: =IFERROR(INDEX(Combined_Data!$S:$S,$O57+1),"") -> 0 | K57: =IFERROR(INDEX(Combined_Data!$AF:$AF,$O57+1),"") -> 28.6 | L57: =IFERROR(INDEX(Combined_Data!$AG:$AG,$O57+1),"") -> Uncertain | M57: =IFERROR(INDEX(Combined_Data!$AH:$AH,$O57+1),"") -> https://indeed.com/viewjob?jk=c16097404185408c | O57: =IFERROR(_xlfn.AGGREGATE(15,6,(ROW(Combined_Data!$AI$2:$AI$3001)-1)/(Combined_Data!$AI$2:$AI$3001),23),"") -> 1978
A58: =IFERROR(INDEX(Combined_Data!$C:$C,$O58+1),"") -> SAP ABAP Developer | B58: =IFERROR(INDEX(Combined_Data!$E:$E,$O58+1),"") -> Infosys | C58: =IFERROR(INDEX(Combined_Data!$B:$B,$O58+1),"") -> Indeed | D58: =IFERROR(INDEX(Combined_Data!$D:$D,$O58+1),"") -> Software Engineer | E58: =IFERROR(INDEX(Combined_Data!$G:$G,$O58+1),"") -> Not Specified | F58: =IFERROR(INDEX(Combined_Data!$I:$I,$O58+1),"") -> 46209.473 | G58: =IFERROR(INDEX(Combined_Data!$K:$K,$O58+1),"") -> 0.8 | H58: =IFERROR(INDEX(Combined_Data!$M:$M,$O58+1),"") -> Not Captured by Scraper | I58: =IFERROR(INDEX(Combined_Data!$N:$N,$O58+1),"") -> FALSE | J58: =IFERROR(INDEX(Combined_Data!$S:$S,$O58+1),"") -> 0 | K58: =IFERROR(INDEX(Combined_Data!$AF:$AF,$O58+1),"") -> 28.6 | L58: =IFERROR(INDEX(Combined_Data!$AG:$AG,$O58+1),"") -> Uncertain | M58: =IFERROR(INDEX(Combined_Data!$AH:$AH,$O58+1),"") -> https://indeed.com/viewjob?jk=6936b5cfafd6e186 | O58: =IFERROR(_xlfn.AGGREGATE(15,6,(ROW(Combined_Data!$AI$2:$AI$3001)-1)/(Combined_Data!$AI$2:$AI$3001),24),"") -> 1979
A59: =IFERROR(INDEX(Combined_Data!$C:$C,$O59+1),"") | B59: =IFERROR(INDEX(Combined_Data!$E:$E,$O59+1),"") | C59: =IFERROR(INDEX(Combined_Data!$B:$B,$O59+1),"") | D59: =IFERROR(INDEX(Combined_Data!$D:$D,$O59+1),"") | E59: =IFERROR(INDEX(Combined_Data!$G:$G,$O59+1),"") | F59: =IFERROR(INDEX(Combined_Data!$I:$I,$O59+1),"") | G59: =IFERROR(INDEX(Combined_Data!$K:$K,$O59+1),"") | H59: =IFERROR(INDEX(Combined_Data!$M:$M,$O59+1),"") | I59: =IFERROR(INDEX(Combined_Data!$N:$N,$O59+1),"") | J59: =IFERROR(INDEX(Combined_Data!$S:$S,$O59+1),"") | K59: =IFERROR(INDEX(Combined_Data!$AF:$AF,$O59+1),"") | L59: =IFERROR(INDEX(Combined_Data!$AG:$AG,$O59+1),"") | M59: =IFERROR(INDEX(Combined_Data!$AH:$AH,$O59+1),"") | O59: =IFERROR(_xlfn.AGGREGATE(15,6,(ROW(Combined_Data!$AI$2:$AI$3001)-1)/(Combined_Data!$AI$2:$AI$3001),25),"")
A60: =IFERROR(INDEX(Combined_Data!$C:$C,$O60+1),"") | B60: =IFERROR(INDEX(Combined_Data!$E:$E,$O60+1),"") | C60: =IFERROR(INDEX(Combined_Data!$B:$B,$O60+1),"") | D60: =IFERROR(INDEX(Combined_Data!$D:$D,$O60+1),"") | E60: =IFERROR(INDEX(Combined_Data!$G:$G,$O60+1),"") | F60: =IFERROR(INDEX(Combined_Data!$I:$I,$O60+1),"") | G60: =IFERROR(INDEX(Combined_Data!$K:$K,$O60+1),"") | H60: =IFERROR(INDEX(Combined_Data!$M:$M,$O60+1),"") | I60: =IFERROR(INDEX(Combined_Data!$N:$N,$O60+1),"") | J60: =IFERROR(INDEX(Combined_Data!$S:$S,$O60+1),"") | K60: =IFERROR(INDEX(Combined_Data!$AF:$AF,$O60+1),"") | L60: =IFERROR(INDEX(Combined_Data!$AG:$AG,$O60+1),"") | M60: =IFERROR(INDEX(Combined_Data!$AH:$AH,$O60+1),"") | O60: =IFERROR(_xlfn.AGGREGATE(15,6,(ROW(Combined_Data!$AI$2:$AI$3001)-1)/(Combined_Data!$AI$2:$AI$3001),26),"")
A61: =IFERROR(INDEX(Combined_Data!$C:$C,$O61+1),"") | B61: =IFERROR(INDEX(Combined_Data!$E:$E,$O61+1),"") | C61: =IFERROR(INDEX(Combined_Data!$B:$B,$O61+1),"") | D61: =IFERROR(INDEX(Combined_Data!$D:$D,$O61+1),"") | E61: =IFERROR(INDEX(Combined_Data!$G:$G,$O61+1),"") | F61: =IFERROR(INDEX(Combined_Data!$I:$I,$O61+1),"") | G61: =IFERROR(INDEX(Combined_Data!$K:$K,$O61+1),"") | H61: =IFERROR(INDEX(Combined_Data!$M:$M,$O61+1),"") | I61: =IFERROR(INDEX(Combined_Data!$N:$N,$O61+1),"") | J61: =IFERROR(INDEX(Combined_Data!$S:$S,$O61+1),"") | K61: =IFERROR(INDEX(Combined_Data!$AF:$AF,$O61+1),"") | L61: =IFERROR(INDEX(Combined_Data!$AG:$AG,$O61+1),"") | M61: =IFERROR(INDEX(Combined_Data!$AH:$AH,$O61+1),"") | O61: =IFERROR(_xlfn.AGGREGATE(15,6,(ROW(Combined_Data!$AI$2:$AI$3001)-1)/(Combined_Data!$AI$2:$AI$3001),27),"")
A62: =IFERROR(INDEX(Combined_Data!$C:$C,$O62+1),"") | B62: =IFERROR(INDEX(Combined_Data!$E:$E,$O62+1),"") | C62: =IFERROR(INDEX(Combined_Data!$B:$B,$O62+1),"") | D62: =IFERROR(INDEX(Combined_Data!$D:$D,$O62+1),"") | E62: =IFERROR(INDEX(Combined_Data!$G:$G,$O62+1),"") | F62: =IFERROR(INDEX(Combined_Data!$I:$I,$O62+1),"") | G62: =IFERROR(INDEX(Combined_Data!$K:$K,$O62+1),"") | H62: =IFERROR(INDEX(Combined_Data!$M:$M,$O62+1),"") | I62: =IFERROR(INDEX(Combined_Data!$N:$N,$O62+1),"") | J62: =IFERROR(INDEX(Combined_Data!$S:$S,$O62+1),"") | K62: =IFERROR(INDEX(Combined_Data!$AF:$AF,$O62+1),"") | L62: =IFERROR(INDEX(Combined_Data!$AG:$AG,$O62+1),"") | M62: =IFERROR(INDEX(Combined_Data!$AH:$AH,$O62+1),"") | O62: =IFERROR(_xlfn.AGGREGATE(15,6,(ROW(Combined_Data!$AI$2:$AI$3001)-1)/(Combined_Data!$AI$2:$AI$3001),28),"")
A63: =IFERROR(INDEX(Combined_Data!$C:$C,$O63+1),"") | B63: =IFERROR(INDEX(Combined_Data!$E:$E,$O63+1),"") | C63: =IFERROR(INDEX(Combined_Data!$B:$B,$O63+1),"") | D63: =IFERROR(INDEX(Combined_Data!$D:$D,$O63+1),"") | E63: =IFERROR(INDEX(Combined_Data!$G:$G,$O63+1),"") | F63: =IFERROR(INDEX(Combined_Data!$I:$I,$O63+1),"") | G63: =IFERROR(INDEX(Combined_Data!$K:$K,$O63+1),"") | H63: =IFERROR(INDEX(Combined_Data!$M:$M,$O63+1),"") | I63: =IFERROR(INDEX(Combined_Data!$N:$N,$O63+1),"") | J63: =IFERROR(INDEX(Combined_Data!$S:$S,$O63+1),"") | K63: =IFERROR(INDEX(Combined_Data!$AF:$AF,$O63+1),"") | L63: =IFERROR(INDEX(Combined_Data!$AG:$AG,$O63+1),"") | M63: =IFERROR(INDEX(Combined_Data!$AH:$AH,$O63+1),"") | O63: =IFERROR(_xlfn.AGGREGATE(15,6,(ROW(Combined_Data!$AI$2:$AI$3001)-1)/(Combined_Data!$AI$2:$AI$3001),29),"")
A64: =IFERROR(INDEX(Combined_Data!$C:$C,$O64+1),"") | B64: =IFERROR(INDEX(Combined_Data!$E:$E,$O64+1),"") | C64: =IFERROR(INDEX(Combined_Data!$B:$B,$O64+1),"") | D64: =IFERROR(INDEX(Combined_Data!$D:$D,$O64+1),"") | E64: =IFERROR(INDEX(Combined_Data!$G:$G,$O64+1),"") | F64: =IFERROR(INDEX(Combined_Data!$I:$I,$O64+1),"") | G64: =IFERROR(INDEX(Combined_Data!$K:$K,$O64+1),"") | H64: =IFERROR(INDEX(Combined_Data!$M:$M,$O64+1),"") | I64: =IFERROR(INDEX(Combined_Data!$N:$N,$O64+1),"") | J64: =IFERROR(INDEX(Combined_Data!$S:$S,$O64+1),"") | K64: =IFERROR(INDEX(Combined_Data!$AF:$AF,$O64+1),"") | L64: =IFERROR(INDEX(Combined_Data!$AG:$AG,$O64+1),"") | M64: =IFERROR(INDEX(Combined_Data!$AH:$AH,$O64+1),"") | O64: =IFERROR(_xlfn.AGGREGATE(15,6,(ROW(Combined_Data!$AI$2:$AI$3001)-1)/(Combined_Data!$AI$2:$AI$3001),30),"")
A65: =IFERROR(INDEX(Combined_Data!$C:$C,$O65+1),"") | B65: =IFERROR(INDEX(Combined_Data!$E:$E,$O65+1),"") | C65: =IFERROR(INDEX(Combined_Data!$B:$B,$O65+1),"") | D65: =IFERROR(INDEX(Combined_Data!$D:$D,$O65+1),"") | E65: =IFERROR(INDEX(Combined_Data!$G:$G,$O65+1),"") | F65: =IFERROR(INDEX(Combined_Data!$I:$I,$O65+1),"") | G65: =IFERROR(INDEX(Combined_Data!$K:$K,$O65+1),"") | H65: =IFERROR(INDEX(Combined_Data!$M:$M,$O65+1),"") | I65: =IFERROR(INDEX(Combined_Data!$N:$N,$O65+1),"") | J65: =IFERROR(INDEX(Combined_Data!$S:$S,$O65+1),"") | K65: =IFERROR(INDEX(Combined_Data!$AF:$AF,$O65+1),"") | L65: =IFERROR(INDEX(Combined_Data!$AG:$AG,$O65+1),"") | M65: =IFERROR(INDEX(Combined_Data!$AH:$AH,$O65+1),"") | O65: =IFERROR(_xlfn.AGGREGATE(15,6,(ROW(Combined_Data!$AI$2:$AI$3001)-1)/(Combined_Data!$AI$2:$AI$3001),31),"")
A66: =IFERROR(INDEX(Combined_Data!$C:$C,$O66+1),"") | B66: =IFERROR(INDEX(Combined_Data!$E:$E,$O66+1),"") | C66: =IFERROR(INDEX(Combined_Data!$B:$B,$O66+1),"") | D66: =IFERROR(INDEX(Combined_Data!$D:$D,$O66+1),"") | E66: =IFERROR(INDEX(Combined_Data!$G:$G,$O66+1),"") | F66: =IFERROR(INDEX(Combined_Data!$I:$I,$O66+1),"") | G66: =IFERROR(INDEX(Combined_Data!$K:$K,$O66+1),"") | H66: =IFERROR(INDEX(Combined_Data!$M:$M,$O66+1),"") | I66: =IFERROR(INDEX(Combined_Data!$N:$N,$O66+1),"") | J66: =IFERROR(INDEX(Combined_Data!$S:$S,$O66+1),"") | K66: =IFERROR(INDEX(Combined_Data!$AF:$AF,$O66+1),"") | L66: =IFERROR(INDEX(Combined_Data!$AG:$AG,$O66+1),"") | M66: =IFERROR(INDEX(Combined_Data!$AH:$AH,$O66+1),"") | O66: =IFERROR(_xlfn.AGGREGATE(15,6,(ROW(Combined_Data!$AI$2:$AI$3001)-1)/(Combined_Data!$AI$2:$AI$3001),32),"")
A67: =IFERROR(INDEX(Combined_Data!$C:$C,$O67+1),"") | B67: =IFERROR(INDEX(Combined_Data!$E:$E,$O67+1),"") | C67: =IFERROR(INDEX(Combined_Data!$B:$B,$O67+1),"") | D67: =IFERROR(INDEX(Combined_Data!$D:$D,$O67+1),"") | E67: =IFERROR(INDEX(Combined_Data!$G:$G,$O67+1),"") | F67: =IFERROR(INDEX(Combined_Data!$I:$I,$O67+1),"") | G67: =IFERROR(INDEX(Combined_Data!$K:$K,$O67+1),"") | H67: =IFERROR(INDEX(Combined_Data!$M:$M,$O67+1),"") | I67: =IFERROR(INDEX(Combined_Data!$N:$N,$O67+1),"") | J67: =IFERROR(INDEX(Combined_Data!$S:$S,$O67+1),"") | K67: =IFERROR(INDEX(Combined_Data!$AF:$AF,$O67+1),"") | L67: =IFERROR(INDEX(Combined_Data!$AG:$AG,$O67+1),"") | M67: =IFERROR(INDEX(Combined_Data!$AH:$AH,$O67+1),"") | O67: =IFERROR(_xlfn.AGGREGATE(15,6,(ROW(Combined_Data!$AI$2:$AI$3001)-1)/(Combined_Data!$AI$2:$AI$3001),33),"")
A68: =IFERROR(INDEX(Combined_Data!$C:$C,$O68+1),"") | B68: =IFERROR(INDEX(Combined_Data!$E:$E,$O68+1),"") | C68: =IFERROR(INDEX(Combined_Data!$B:$B,$O68+1),"") | D68: =IFERROR(INDEX(Combined_Data!$D:$D,$O68+1),"") | E68: =IFERROR(INDEX(Combined_Data!$G:$G,$O68+1),"") | F68: =IFERROR(INDEX(Combined_Data!$I:$I,$O68+1),"") | G68: =IFERROR(INDEX(Combined_Data!$K:$K,$O68+1),"") | H68: =IFERROR(INDEX(Combined_Data!$M:$M,$O68+1),"") | I68: =IFERROR(INDEX(Combined_Data!$N:$N,$O68+1),"") | J68: =IFERROR(INDEX(Combined_Data!$S:$S,$O68+1),"") | K68: =IFERROR(INDEX(Combined_Data!$AF:$AF,$O68+1),"") | L68: =IFERROR(INDEX(Combined_Data!$AG:$AG,$O68+1),"") | M68: =IFERROR(INDEX(Combined_Data!$AH:$AH,$O68+1),"") | O68: =IFERROR(_xlfn.AGGREGATE(15,6,(ROW(Combined_Data!$AI$2:$AI$3001)-1)/(Combined_Data!$AI$2:$AI$3001),34),"")
A69: =IFERROR(INDEX(Combined_Data!$C:$C,$O69+1),"") | B69: =IFERROR(INDEX(Combined_Data!$E:$E,$O69+1),"") | C69: =IFERROR(INDEX(Combined_Data!$B:$B,$O69+1),"") | D69: =IFERROR(INDEX(Combined_Data!$D:$D,$O69+1),"") | E69: =IFERROR(INDEX(Combined_Data!$G:$G,$O69+1),"") | F69: =IFERROR(INDEX(Combined_Data!$I:$I,$O69+1),"") | G69: =IFERROR(INDEX(Combined_Data!$K:$K,$O69+1),"") | H69: =IFERROR(INDEX(Combined_Data!$M:$M,$O69+1),"") | I69: =IFERROR(INDEX(Combined_Data!$N:$N,$O69+1),"") | J69: =IFERROR(INDEX(Combined_Data!$S:$S,$O69+1),"") | K69: =IFERROR(INDEX(Combined_Data!$AF:$AF,$O69+1),"") | L69: =IFERROR(INDEX(Combined_Data!$AG:$AG,$O69+1),"") | M69: =IFERROR(INDEX(Combined_Data!$AH:$AH,$O69+1),"") | O69: =IFERROR(_xlfn.AGGREGATE(15,6,(ROW(Combined_Data!$AI$2:$AI$3001)-1)/(Combined_Data!$AI$2:$AI$3001),35),"")
A70: =IFERROR(INDEX(Combined_Data!$C:$C,$O70+1),"") | B70: =IFERROR(INDEX(Combined_Data!$E:$E,$O70+1),"") | C70: =IFERROR(INDEX(Combined_Data!$B:$B,$O70+1),"") | D70: =IFERROR(INDEX(Combined_Data!$D:$D,$O70+1),"") | E70: =IFERROR(INDEX(Combined_Data!$G:$G,$O70+1),"") | F70: =IFERROR(INDEX(Combined_Data!$I:$I,$O70+1),"") | G70: =IFERROR(INDEX(Combined_Data!$K:$K,$O70+1),"") | H70: =IFERROR(INDEX(Combined_Data!$M:$M,$O70+1),"") | I70: =IFERROR(INDEX(Combined_Data!$N:$N,$O70+1),"") | J70: =IFERROR(INDEX(Combined_Data!$S:$S,$O70+1),"") | K70: =IFERROR(INDEX(Combined_Data!$AF:$AF,$O70+1),"") | L70: =IFERROR(INDEX(Combined_Data!$AG:$AG,$O70+1),"") | M70: =IFERROR(INDEX(Combined_Data!$AH:$AH,$O70+1),"") | O70: =IFERROR(_xlfn.AGGREGATE(15,6,(ROW(Combined_Data!$AI$2:$AI$3001)-1)/(Combined_Data!$AI$2:$AI$3001),36),"")
A71: =IFERROR(INDEX(Combined_Data!$C:$C,$O71+1),"") | B71: =IFERROR(INDEX(Combined_Data!$E:$E,$O71+1),"") | C71: =IFERROR(INDEX(Combined_Data!$B:$B,$O71+1),"") | D71: =IFERROR(INDEX(Combined_Data!$D:$D,$O71+1),"") | E71: =IFERROR(INDEX(Combined_Data!$G:$G,$O71+1),"") | F71: =IFERROR(INDEX(Combined_Data!$I:$I,$O71+1),"") | G71: =IFERROR(INDEX(Combined_Data!$K:$K,$O71+1),"") | H71: =IFERROR(INDEX(Combined_Data!$M:$M,$O71+1),"") | I71: =IFERROR(INDEX(Combined_Data!$N:$N,$O71+1),"") | J71: =IFERROR(INDEX(Combined_Data!$S:$S,$O71+1),"") | K71: =IFERROR(INDEX(Combined_Data!$AF:$AF,$O71+1),"") | L71: =IFERROR(INDEX(Combined_Data!$AG:$AG,$O71+1),"") | M71: =IFERROR(INDEX(Combined_Data!$AH:$AH,$O71+1),"") | O71: =IFERROR(_xlfn.AGGREGATE(15,6,(ROW(Combined_Data!$AI$2:$AI$3001)-1)/(Combined_Data!$AI$2:$AI$3001),37),"")
A72: =IFERROR(INDEX(Combined_Data!$C:$C,$O72+1),"") | B72: =IFERROR(INDEX(Combined_Data!$E:$E,$O72+1),"") | C72: =IFERROR(INDEX(Combined_Data!$B:$B,$O72+1),"") | D72: =IFERROR(INDEX(Combined_Data!$D:$D,$O72+1),"") | E72: =IFERROR(INDEX(Combined_Data!$G:$G,$O72+1),"") | F72: =IFERROR(INDEX(Combined_Data!$I:$I,$O72+1),"") | G72: =IFERROR(INDEX(Combined_Data!$K:$K,$O72+1),"") | H72: =IFERROR(INDEX(Combined_Data!$M:$M,$O72+1),"") | I72: =IFERROR(INDEX(Combined_Data!$N:$N,$O72+1),"") | J72: =IFERROR(INDEX(Combined_Data!$S:$S,$O72+1),"") | K72: =IFERROR(INDEX(Combined_Data!$AF:$AF,$O72+1),"") | L72: =IFERROR(INDEX(Combined_Data!$AG:$AG,$O72+1),"") | M72: =IFERROR(INDEX(Combined_Data!$AH:$AH,$O72+1),"") | O72: =IFERROR(_xlfn.AGGREGATE(15,6,(ROW(Combined_Data!$AI$2:$AI$3001)-1)/(Combined_Data!$AI$2:$AI$3001),38),"")
A73: =IFERROR(INDEX(Combined_Data!$C:$C,$O73+1),"") | B73: =IFERROR(INDEX(Combined_Data!$E:$E,$O73+1),"") | C73: =IFERROR(INDEX(Combined_Data!$B:$B,$O73+1),"") | D73: =IFERROR(INDEX(Combined_Data!$D:$D,$O73+1),"") | E73: =IFERROR(INDEX(Combined_Data!$G:$G,$O73+1),"") | F73: =IFERROR(INDEX(Combined_Data!$I:$I,$O73+1),"") | G73: =IFERROR(INDEX(Combined_Data!$K:$K,$O73+1),"") | H73: =IFERROR(INDEX(Combined_Data!$M:$M,$O73+1),"") | I73: =IFERROR(INDEX(Combined_Data!$N:$N,$O73+1),"") | J73: =IFERROR(INDEX(Combined_Data!$S:$S,$O73+1),"") | K73: =IFERROR(INDEX(Combined_Data!$AF:$AF,$O73+1),"") | L73: =IFERROR(INDEX(Combined_Data!$AG:$AG,$O73+1),"") | M73: =IFERROR(INDEX(Combined_Data!$AH:$AH,$O73+1),"") | O73: =IFERROR(_xlfn.AGGREGATE(15,6,(ROW(Combined_Data!$AI$2:$AI$3001)-1)/(Combined_Data!$AI$2:$AI$3001),39),"")
A74: =IFERROR(INDEX(Combined_Data!$C:$C,$O74+1),"") | B74: =IFERROR(INDEX(Combined_Data!$E:$E,$O74+1),"") | C74: =IFERROR(INDEX(Combined_Data!$B:$B,$O74+1),"") | D74: =IFERROR(INDEX(Combined_Data!$D:$D,$O74+1),"") | E74: =IFERROR(INDEX(Combined_Data!$G:$G,$O74+1),"") | F74: =IFERROR(INDEX(Combined_Data!$I:$I,$O74+1),"") | G74: =IFERROR(INDEX(Combined_Data!$K:$K,$O74+1),"") | H74: =IFERROR(INDEX(Combined_Data!$M:$M,$O74+1),"") | I74: =IFERROR(INDEX(Combined_Data!$N:$N,$O74+1),"") | J74: =IFERROR(INDEX(Combined_Data!$S:$S,$O74+1),"") | K74: =IFERROR(INDEX(Combined_Data!$AF:$AF,$O74+1),"") | L74: =IFERROR(INDEX(Combined_Data!$AG:$AG,$O74+1),"") | M74: =IFERROR(INDEX(Combined_Data!$AH:$AH,$O74+1),"") | O74: =IFERROR(_xlfn.AGGREGATE(15,6,(ROW(Combined_Data!$AI$2:$AI$3001)-1)/(Combined_Data!$AI$2:$AI$3001),40),"")
A75: =IFERROR(INDEX(Combined_Data!$C:$C,$O75+1),"") | B75: =IFERROR(INDEX(Combined_Data!$E:$E,$O75+1),"") | C75: =IFERROR(INDEX(Combined_Data!$B:$B,$O75+1),"") | D75: =IFERROR(INDEX(Combined_Data!$D:$D,$O75+1),"") | E75: =IFERROR(INDEX(Combined_Data!$G:$G,$O75+1),"") | F75: =IFERROR(INDEX(Combined_Data!$I:$I,$O75+1),"") | G75: =IFERROR(INDEX(Combined_Data!$K:$K,$O75+1),"") | H75: =IFERROR(INDEX(Combined_Data!$M:$M,$O75+1),"") | I75: =IFERROR(INDEX(Combined_Data!$N:$N,$O75+1),"") | J75: =IFERROR(INDEX(Combined_Data!$S:$S,$O75+1),"") | K75: =IFERROR(INDEX(Combined_Data!$AF:$AF,$O75+1),"") | L75: =IFERROR(INDEX(Combined_Data!$AG:$AG,$O75+1),"") | M75: =IFERROR(INDEX(Combined_Data!$AH:$AH,$O75+1),"") | O75: =IFERROR(_xlfn.AGGREGATE(15,6,(ROW(Combined_Data!$AI$2:$AI$3001)-1)/(Combined_Data!$AI$2:$AI$3001),41),"")
A76: =IFERROR(INDEX(Combined_Data!$C:$C,$O76+1),"") | B76: =IFERROR(INDEX(Combined_Data!$E:$E,$O76+1),"") | C76: =IFERROR(INDEX(Combined_Data!$B:$B,$O76+1),"") | D76: =IFERROR(INDEX(Combined_Data!$D:$D,$O76+1),"") | E76: =IFERROR(INDEX(Combined_Data!$G:$G,$O76+1),"") | F76: =IFERROR(INDEX(Combined_Data!$I:$I,$O76+1),"") | G76: =IFERROR(INDEX(Combined_Data!$K:$K,$O76+1),"") | H76: =IFERROR(INDEX(Combined_Data!$M:$M,$O76+1),"") | I76: =IFERROR(INDEX(Combined_Data!$N:$N,$O76+1),"") | J76: =IFERROR(INDEX(Combined_Data!$S:$S,$O76+1),"") | K76: =IFERROR(INDEX(Combined_Data!$AF:$AF,$O76+1),"") | L76: =IFERROR(INDEX(Combined_Data!$AG:$AG,$O76+1),"") | M76: =IFERROR(INDEX(Combined_Data!$AH:$AH,$O76+1),"") | O76: =IFERROR(_xlfn.AGGREGATE(15,6,(ROW(Combined_Data!$AI$2:$AI$3001)-1)/(Combined_Data!$AI$2:$AI$3001),42),"")
A77: =IFERROR(INDEX(Combined_Data!$C:$C,$O77+1),"") | B77: =IFERROR(INDEX(Combined_Data!$E:$E,$O77+1),"") | C77: =IFERROR(INDEX(Combined_Data!$B:$B,$O77+1),"") | D77: =IFERROR(INDEX(Combined_Data!$D:$D,$O77+1),"") | E77: =IFERROR(INDEX(Combined_Data!$G:$G,$O77+1),"") | F77: =IFERROR(INDEX(Combined_Data!$I:$I,$O77+1),"") | G77: =IFERROR(INDEX(Combined_Data!$K:$K,$O77+1),"") | H77: =IFERROR(INDEX(Combined_Data!$M:$M,$O77+1),"") | I77: =IFERROR(INDEX(Combined_Data!$N:$N,$O77+1),"") | J77: =IFERROR(INDEX(Combined_Data!$S:$S,$O77+1),"") | K77: =IFERROR(INDEX(Combined_Data!$AF:$AF,$O77+1),"") | L77: =IFERROR(INDEX(Combined_Data!$AG:$AG,$O77+1),"") | M77: =IFERROR(INDEX(Combined_Data!$AH:$AH,$O77+1),"") | O77: =IFERROR(_xlfn.AGGREGATE(15,6,(ROW(Combined_Data!$AI$2:$AI$3001)-1)/(Combined_Data!$AI$2:$AI$3001),43),"")
A78: =IFERROR(INDEX(Combined_Data!$C:$C,$O78+1),"") | B78: =IFERROR(INDEX(Combined_Data!$E:$E,$O78+1),"") | C78: =IFERROR(INDEX(Combined_Data!$B:$B,$O78+1),"") | D78: =IFERROR(INDEX(Combined_Data!$D:$D,$O78+1),"") | E78: =IFERROR(INDEX(Combined_Data!$G:$G,$O78+1),"") | F78: =IFERROR(INDEX(Combined_Data!$I:$I,$O78+1),"") | G78: =IFERROR(INDEX(Combined_Data!$K:$K,$O78+1),"") | H78: =IFERROR(INDEX(Combined_Data!$M:$M,$O78+1),"") | I78: =IFERROR(INDEX(Combined_Data!$N:$N,$O78+1),"") | J78: =IFERROR(INDEX(Combined_Data!$S:$S,$O78+1),"") | K78: =IFERROR(INDEX(Combined_Data!$AF:$AF,$O78+1),"") | L78: =IFERROR(INDEX(Combined_Data!$AG:$AG,$O78+1),"") | M78: =IFERROR(INDEX(Combined_Data!$AH:$AH,$O78+1),"") | O78: =IFERROR(_xlfn.AGGREGATE(15,6,(ROW(Combined_Data!$AI$2:$AI$3001)-1)/(Combined_Data!$AI$2:$AI$3001),44),"")
A79: =IFERROR(INDEX(Combined_Data!$C:$C,$O79+1),"") | B79: =IFERROR(INDEX(Combined_Data!$E:$E,$O79+1),"") | C79: =IFERROR(INDEX(Combined_Data!$B:$B,$O79+1),"") | D79: =IFERROR(INDEX(Combined_Data!$D:$D,$O79+1),"") | E79: =IFERROR(INDEX(Combined_Data!$G:$G,$O79+1),"") | F79: =IFERROR(INDEX(Combined_Data!$I:$I,$O79+1),"") | G79: =IFERROR(INDEX(Combined_Data!$K:$K,$O79+1),"") | H79: =IFERROR(INDEX(Combined_Data!$M:$M,$O79+1),"") | I79: =IFERROR(INDEX(Combined_Data!$N:$N,$O79+1),"") | J79: =IFERROR(INDEX(Combined_Data!$S:$S,$O79+1),"") | K79: =IFERROR(INDEX(Combined_Data!$AF:$AF,$O79+1),"") | L79: =IFERROR(INDEX(Combined_Data!$AG:$AG,$O79+1),"") | M79: =IFERROR(INDEX(Combined_Data!$AH:$AH,$O79+1),"") | O79: =IFERROR(_xlfn.AGGREGATE(15,6,(ROW(Combined_Data!$AI$2:$AI$3001)-1)/(Combined_Data!$AI$2:$AI$3001),45),"")
A80: =IFERROR(INDEX(Combined_Data!$C:$C,$O80+1),"") | B80: =IFERROR(INDEX(Combined_Data!$E:$E,$O80+1),"") | C80: =IFERROR(INDEX(Combined_Data!$B:$B,$O80+1),"") | D80: =IFERROR(INDEX(Combined_Data!$D:$D,$O80+1),"") | E80: =IFERROR(INDEX(Combined_Data!$G:$G,$O80+1),"") | F80: =IFERROR(INDEX(Combined_Data!$I:$I,$O80+1),"") | G80: =IFERROR(INDEX(Combined_Data!$K:$K,$O80+1),"") | H80: =IFERROR(INDEX(Combined_Data!$M:$M,$O80+1),"") | I80: =IFERROR(INDEX(Combined_Data!$N:$N,$O80+1),"") | J80: =IFERROR(INDEX(Combined_Data!$S:$S,$O80+1),"") | K80: =IFERROR(INDEX(Combined_Data!$AF:$AF,$O80+1),"") | L80: =IFERROR(INDEX(Combined_Data!$AG:$AG,$O80+1),"") | M80: =IFERROR(INDEX(Combined_Data!$AH:$AH,$O80+1),"") | O80: =IFERROR(_xlfn.AGGREGATE(15,6,(ROW(Combined_Data!$AI$2:$AI$3001)-1)/(Combined_Data!$AI$2:$AI$3001),46),"")
A81: =IFERROR(INDEX(Combined_Data!$C:$C,$O81+1),"") | B81: =IFERROR(INDEX(Combined_Data!$E:$E,$O81+1),"") | C81: =IFERROR(INDEX(Combined_Data!$B:$B,$O81+1),"") | D81: =IFERROR(INDEX(Combined_Data!$D:$D,$O81+1),"") | E81: =IFERROR(INDEX(Combined_Data!$G:$G,$O81+1),"") | F81: =IFERROR(INDEX(Combined_Data!$I:$I,$O81+1),"") | G81: =IFERROR(INDEX(Combined_Data!$K:$K,$O81+1),"") | H81: =IFERROR(INDEX(Combined_Data!$M:$M,$O81+1),"") | I81: =IFERROR(INDEX(Combined_Data!$N:$N,$O81+1),"") | J81: =IFERROR(INDEX(Combined_Data!$S:$S,$O81+1),"") | K81: =IFERROR(INDEX(Combined_Data!$AF:$AF,$O81+1),"") | L81: =IFERROR(INDEX(Combined_Data!$AG:$AG,$O81+1),"") | M81: =IFERROR(INDEX(Combined_Data!$AH:$AH,$O81+1),"") | O81: =IFERROR(_xlfn.AGGREGATE(15,6,(ROW(Combined_Data!$AI$2:$AI$3001)-1)/(Combined_Data!$AI$2:$AI$3001),47),"")
A82: =IFERROR(INDEX(Combined_Data!$C:$C,$O82+1),"") | B82: =IFERROR(INDEX(Combined_Data!$E:$E,$O82+1),"") | C82: =IFERROR(INDEX(Combined_Data!$B:$B,$O82+1),"") | D82: =IFERROR(INDEX(Combined_Data!$D:$D,$O82+1),"") | E82: =IFERROR(INDEX(Combined_Data!$G:$G,$O82+1),"") | F82: =IFERROR(INDEX(Combined_Data!$I:$I,$O82+1),"") | G82: =IFERROR(INDEX(Combined_Data!$K:$K,$O82+1),"") | H82: =IFERROR(INDEX(Combined_Data!$M:$M,$O82+1),"") | I82: =IFERROR(INDEX(Combined_Data!$N:$N,$O82+1),"") | J82: =IFERROR(INDEX(Combined_Data!$S:$S,$O82+1),"") | K82: =IFERROR(INDEX(Combined_Data!$AF:$AF,$O82+1),"") | L82: =IFERROR(INDEX(Combined_Data!$AG:$AG,$O82+1),"") | M82: =IFERROR(INDEX(Combined_Data!$AH:$AH,$O82+1),"") | O82: =IFERROR(_xlfn.AGGREGATE(15,6,(ROW(Combined_Data!$AI$2:$AI$3001)-1)/(Combined_Data!$AI$2:$AI$3001),48),"")
A83: =IFERROR(INDEX(Combined_Data!$C:$C,$O83+1),"") | B83: =IFERROR(INDEX(Combined_Data!$E:$E,$O83+1),"") | C83: =IFERROR(INDEX(Combined_Data!$B:$B,$O83+1),"") | D83: =IFERROR(INDEX(Combined_Data!$D:$D,$O83+1),"") | E83: =IFERROR(INDEX(Combined_Data!$G:$G,$O83+1),"") | F83: =IFERROR(INDEX(Combined_Data!$I:$I,$O83+1),"") | G83: =IFERROR(INDEX(Combined_Data!$K:$K,$O83+1),"") | H83: =IFERROR(INDEX(Combined_Data!$M:$M,$O83+1),"") | I83: =IFERROR(INDEX(Combined_Data!$N:$N,$O83+1),"") | J83: =IFERROR(INDEX(Combined_Data!$S:$S,$O83+1),"") | K83: =IFERROR(INDEX(Combined_Data!$AF:$AF,$O83+1),"") | L83: =IFERROR(INDEX(Combined_Data!$AG:$AG,$O83+1),"") | M83: =IFERROR(INDEX(Combined_Data!$AH:$AH,$O83+1),"") | O83: =IFERROR(_xlfn.AGGREGATE(15,6,(ROW(Combined_Data!$AI$2:$AI$3001)-1)/(Combined_Data!$AI$2:$AI$3001),49),"")
A84: =IFERROR(INDEX(Combined_Data!$C:$C,$O84+1),"") | B84: =IFERROR(INDEX(Combined_Data!$E:$E,$O84+1),"") | C84: =IFERROR(INDEX(Combined_Data!$B:$B,$O84+1),"") | D84: =IFERROR(INDEX(Combined_Data!$D:$D,$O84+1),"") | E84: =IFERROR(INDEX(Combined_Data!$G:$G,$O84+1),"") | F84: =IFERROR(INDEX(Combined_Data!$I:$I,$O84+1),"") | G84: =IFERROR(INDEX(Combined_Data!$K:$K,$O84+1),"") | H84: =IFERROR(INDEX(Combined_Data!$M:$M,$O84+1),"") | I84: =IFERROR(INDEX(Combined_Data!$N:$N,$O84+1),"") | J84: =IFERROR(INDEX(Combined_Data!$S:$S,$O84+1),"") | K84: =IFERROR(INDEX(Combined_Data!$AF:$AF,$O84+1),"") | L84: =IFERROR(INDEX(Combined_Data!$AG:$AG,$O84+1),"") | M84: =IFERROR(INDEX(Combined_Data!$AH:$AH,$O84+1),"") | O84: =IFERROR(_xlfn.AGGREGATE(15,6,(ROW(Combined_Data!$AI$2:$AI$3001)-1)/(Combined_Data!$AI$2:$AI$3001),50),"")
A85: =IFERROR(INDEX(Combined_Data!$C:$C,$O85+1),"") | B85: =IFERROR(INDEX(Combined_Data!$E:$E,$O85+1),"") | C85: =IFERROR(INDEX(Combined_Data!$B:$B,$O85+1),"") | D85: =IFERROR(INDEX(Combined_Data!$D:$D,$O85+1),"") | E85: =IFERROR(INDEX(Combined_Data!$G:$G,$O85+1),"") | F85: =IFERROR(INDEX(Combined_Data!$I:$I,$O85+1),"") | G85: =IFERROR(INDEX(Combined_Data!$K:$K,$O85+1),"") | H85: =IFERROR(INDEX(Combined_Data!$M:$M,$O85+1),"") | I85: =IFERROR(INDEX(Combined_Data!$N:$N,$O85+1),"") | J85: =IFERROR(INDEX(Combined_Data!$S:$S,$O85+1),"") | K85: =IFERROR(INDEX(Combined_Data!$AF:$AF,$O85+1),"") | L85: =IFERROR(INDEX(Combined_Data!$AG:$AG,$O85+1),"") | M85: =IFERROR(INDEX(Combined_Data!$AH:$AH,$O85+1),"") | O85: =IFERROR(_xlfn.AGGREGATE(15,6,(ROW(Combined_Data!$AI$2:$AI$3001)-1)/(Combined_Data!$AI$2:$AI$3001),51),"")
A86: =IFERROR(INDEX(Combined_Data!$C:$C,$O86+1),"") | B86: =IFERROR(INDEX(Combined_Data!$E:$E,$O86+1),"") | C86: =IFERROR(INDEX(Combined_Data!$B:$B,$O86+1),"") | D86: =IFERROR(INDEX(Combined_Data!$D:$D,$O86+1),"") | E86: =IFERROR(INDEX(Combined_Data!$G:$G,$O86+1),"") | F86: =IFERROR(INDEX(Combined_Data!$I:$I,$O86+1),"") | G86: =IFERROR(INDEX(Combined_Data!$K:$K,$O86+1),"") | H86: =IFERROR(INDEX(Combined_Data!$M:$M,$O86+1),"") | I86: =IFERROR(INDEX(Combined_Data!$N:$N,$O86+1),"") | J86: =IFERROR(INDEX(Combined_Data!$S:$S,$O86+1),"") | K86: =IFERROR(INDEX(Combined_Data!$AF:$AF,$O86+1),"") | L86: =IFERROR(INDEX(Combined_Data!$AG:$AG,$O86+1),"") | M86: =IFERROR(INDEX(Combined_Data!$AH:$AH,$O86+1),"") | O86: =IFERROR(_xlfn.AGGREGATE(15,6,(ROW(Combined_Data!$AI$2:$AI$3001)-1)/(Combined_Data!$AI$2:$AI$3001),52),"")
A87: =IFERROR(INDEX(Combined_Data!$C:$C,$O87+1),"") | B87: =IFERROR(INDEX(Combined_Data!$E:$E,$O87+1),"") | C87: =IFERROR(INDEX(Combined_Data!$B:$B,$O87+1),"") | D87: =IFERROR(INDEX(Combined_Data!$D:$D,$O87+1),"") | E87: =IFERROR(INDEX(Combined_Data!$G:$G,$O87+1),"") | F87: =IFERROR(INDEX(Combined_Data!$I:$I,$O87+1),"") | G87: =IFERROR(INDEX(Combined_Data!$K:$K,$O87+1),"") | H87: =IFERROR(INDEX(Combined_Data!$M:$M,$O87+1),"") | I87: =IFERROR(INDEX(Combined_Data!$N:$N,$O87+1),"") | J87: =IFERROR(INDEX(Combined_Data!$S:$S,$O87+1),"") | K87: =IFERROR(INDEX(Combined_Data!$AF:$AF,$O87+1),"") | L87: =IFERROR(INDEX(Combined_Data!$AG:$AG,$O87+1),"") | M87: =IFERROR(INDEX(Combined_Data!$AH:$AH,$O87+1),"") | O87: =IFERROR(_xlfn.AGGREGATE(15,6,(ROW(Combined_Data!$AI$2:$AI$3001)-1)/(Combined_Data!$AI$2:$AI$3001),53),"")
A88: =IFERROR(INDEX(Combined_Data!$C:$C,$O88+1),"") | B88: =IFERROR(INDEX(Combined_Data!$E:$E,$O88+1),"") | C88: =IFERROR(INDEX(Combined_Data!$B:$B,$O88+1),"") | D88: =IFERROR(INDEX(Combined_Data!$D:$D,$O88+1),"") | E88: =IFERROR(INDEX(Combined_Data!$G:$G,$O88+1),"") | F88: =IFERROR(INDEX(Combined_Data!$I:$I,$O88+1),"") | G88: =IFERROR(INDEX(Combined_Data!$K:$K,$O88+1),"") | H88: =IFERROR(INDEX(Combined_Data!$M:$M,$O88+1),"") | I88: =IFERROR(INDEX(Combined_Data!$N:$N,$O88+1),"") | J88: =IFERROR(INDEX(Combined_Data!$S:$S,$O88+1),"") | K88: =IFERROR(INDEX(Combined_Data!$AF:$AF,$O88+1),"") | L88: =IFERROR(INDEX(Combined_Data!$AG:$AG,$O88+1),"") | M88: =IFERROR(INDEX(Combined_Data!$AH:$AH,$O88+1),"") | O88: =IFERROR(_xlfn.AGGREGATE(15,6,(ROW(Combined_Data!$AI$2:$AI$3001)-1)/(Combined_Data!$AI$2:$AI$3001),54),"")
A89: =IFERROR(INDEX(Combined_Data!$C:$C,$O89+1),"") | B89: =IFERROR(INDEX(Combined_Data!$E:$E,$O89+1),"") | C89: =IFERROR(INDEX(Combined_Data!$B:$B,$O89+1),"") | D89: =IFERROR(INDEX(Combined_Data!$D:$D,$O89+1),"") | E89: =IFERROR(INDEX(Combined_Data!$G:$G,$O89+1),"") | F89: =IFERROR(INDEX(Combined_Data!$I:$I,$O89+1),"") | G89: =IFERROR(INDEX(Combined_Data!$K:$K,$O89+1),"") | H89: =IFERROR(INDEX(Combined_Data!$M:$M,$O89+1),"") | I89: =IFERROR(INDEX(Combined_Data!$N:$N,$O89+1),"") | J89: =IFERROR(INDEX(Combined_Data!$S:$S,$O89+1),"") | K89: =IFERROR(INDEX(Combined_Data!$AF:$AF,$O89+1),"") | L89: =IFERROR(INDEX(Combined_Data!$AG:$AG,$O89+1),"") | M89: =IFERROR(INDEX(Combined_Data!$AH:$AH,$O89+1),"") | O89: =IFERROR(_xlfn.AGGREGATE(15,6,(ROW(Combined_Data!$AI$2:$AI$3001)-1)/(Combined_Data!$AI$2:$AI$3001),55),"")
A90: =IFERROR(INDEX(Combined_Data!$C:$C,$O90+1),"") | B90: =IFERROR(INDEX(Combined_Data!$E:$E,$O90+1),"") | C90: =IFERROR(INDEX(Combined_Data!$B:$B,$O90+1),"") | D90: =IFERROR(INDEX(Combined_Data!$D:$D,$O90+1),"") | E90: =IFERROR(INDEX(Combined_Data!$G:$G,$O90+1),"") | F90: =IFERROR(INDEX(Combined_Data!$I:$I,$O90+1),"") | G90: =IFERROR(INDEX(Combined_Data!$K:$K,$O90+1),"") | H90: =IFERROR(INDEX(Combined_Data!$M:$M,$O90+1),"") | I90: =IFERROR(INDEX(Combined_Data!$N:$N,$O90+1),"") | J90: =IFERROR(INDEX(Combined_Data!$S:$S,$O90+1),"") | K90: =IFERROR(INDEX(Combined_Data!$AF:$AF,$O90+1),"") | L90: =IFERROR(INDEX(Combined_Data!$AG:$AG,$O90+1),"") | M90: =IFERROR(INDEX(Combined_Data!$AH:$AH,$O90+1),"") | O90: =IFERROR(_xlfn.AGGREGATE(15,6,(ROW(Combined_Data!$AI$2:$AI$3001)-1)/(Combined_Data!$AI$2:$AI$3001),56),"")
A91: =IFERROR(INDEX(Combined_Data!$C:$C,$O91+1),"") | B91: =IFERROR(INDEX(Combined_Data!$E:$E,$O91+1),"") | C91: =IFERROR(INDEX(Combined_Data!$B:$B,$O91+1),"") | D91: =IFERROR(INDEX(Combined_Data!$D:$D,$O91+1),"") | E91: =IFERROR(INDEX(Combined_Data!$G:$G,$O91+1),"") | F91: =IFERROR(INDEX(Combined_Data!$I:$I,$O91+1),"") | G91: =IFERROR(INDEX(Combined_Data!$K:$K,$O91+1),"") | H91: =IFERROR(INDEX(Combined_Data!$M:$M,$O91+1),"") | I91: =IFERROR(INDEX(Combined_Data!$N:$N,$O91+1),"") | J91: =IFERROR(INDEX(Combined_Data!$S:$S,$O91+1),"") | K91: =IFERROR(INDEX(Combined_Data!$AF:$AF,$O91+1),"") | L91: =IFERROR(INDEX(Combined_Data!$AG:$AG,$O91+1),"") | M91: =IFERROR(INDEX(Combined_Data!$AH:$AH,$O91+1),"") | O91: =IFERROR(_xlfn.AGGREGATE(15,6,(ROW(Combined_Data!$AI$2:$AI$3001)-1)/(Combined_Data!$AI$2:$AI$3001),57),"")
A92: =IFERROR(INDEX(Combined_Data!$C:$C,$O92+1),"") | B92: =IFERROR(INDEX(Combined_Data!$E:$E,$O92+1),"") | C92: =IFERROR(INDEX(Combined_Data!$B:$B,$O92+1),"") | D92: =IFERROR(INDEX(Combined_Data!$D:$D,$O92+1),"") | E92: =IFERROR(INDEX(Combined_Data!$G:$G,$O92+1),"") | F92: =IFERROR(INDEX(Combined_Data!$I:$I,$O92+1),"") | G92: =IFERROR(INDEX(Combined_Data!$K:$K,$O92+1),"") | H92: =IFERROR(INDEX(Combined_Data!$M:$M,$O92+1),"") | I92: =IFERROR(INDEX(Combined_Data!$N:$N,$O92+1),"") | J92: =IFERROR(INDEX(Combined_Data!$S:$S,$O92+1),"") | K92: =IFERROR(INDEX(Combined_Data!$AF:$AF,$O92+1),"") | L92: =IFERROR(INDEX(Combined_Data!$AG:$AG,$O92+1),"") | M92: =IFERROR(INDEX(Combined_Data!$AH:$AH,$O92+1),"") | O92: =IFERROR(_xlfn.AGGREGATE(15,6,(ROW(Combined_Data!$AI$2:$AI$3001)-1)/(Combined_Data!$AI$2:$AI$3001),58),"")
A93: =IFERROR(INDEX(Combined_Data!$C:$C,$O93+1),"") | B93: =IFERROR(INDEX(Combined_Data!$E:$E,$O93+1),"") | C93: =IFERROR(INDEX(Combined_Data!$B:$B,$O93+1),"") | D93: =IFERROR(INDEX(Combined_Data!$D:$D,$O93+1),"") | E93: =IFERROR(INDEX(Combined_Data!$G:$G,$O93+1),"") | F93: =IFERROR(INDEX(Combined_Data!$I:$I,$O93+1),"") | G93: =IFERROR(INDEX(Combined_Data!$K:$K,$O93+1),"") | H93: =IFERROR(INDEX(Combined_Data!$M:$M,$O93+1),"") | I93: =IFERROR(INDEX(Combined_Data!$N:$N,$O93+1),"") | J93: =IFERROR(INDEX(Combined_Data!$S:$S,$O93+1),"") | K93: =IFERROR(INDEX(Combined_Data!$AF:$AF,$O93+1),"") | L93: =IFERROR(INDEX(Combined_Data!$AG:$AG,$O93+1),"") | M93: =IFERROR(INDEX(Combined_Data!$AH:$AH,$O93+1),"") | O93: =IFERROR(_xlfn.AGGREGATE(15,6,(ROW(Combined_Data!$AI$2:$AI$3001)-1)/(Combined_Data!$AI$2:$AI$3001),59),"")
A94: =IFERROR(INDEX(Combined_Data!$C:$C,$O94+1),"") | B94: =IFERROR(INDEX(Combined_Data!$E:$E,$O94+1),"") | C94: =IFERROR(INDEX(Combined_Data!$B:$B,$O94+1),"") | D94: =IFERROR(INDEX(Combined_Data!$D:$D,$O94+1),"") | E94: =IFERROR(INDEX(Combined_Data!$G:$G,$O94+1),"") | F94: =IFERROR(INDEX(Combined_Data!$I:$I,$O94+1),"") | G94: =IFERROR(INDEX(Combined_Data!$K:$K,$O94+1),"") | H94: =IFERROR(INDEX(Combined_Data!$M:$M,$O94+1),"") | I94: =IFERROR(INDEX(Combined_Data!$N:$N,$O94+1),"") | J94: =IFERROR(INDEX(Combined_Data!$S:$S,$O94+1),"") | K94: =IFERROR(INDEX(Combined_Data!$AF:$AF,$O94+1),"") | L94: =IFERROR(INDEX(Combined_Data!$AG:$AG,$O94+1),"") | M94: =IFERROR(INDEX(Combined_Data!$AH:$AH,$O94+1),"") | O94: =IFERROR(_xlfn.AGGREGATE(15,6,(ROW(Combined_Data!$AI$2:$AI$3001)-1)/(Combined_Data!$AI$2:$AI$3001),60),"")
A95: =IFERROR(INDEX(Combined_Data!$C:$C,$O95+1),"") | B95: =IFERROR(INDEX(Combined_Data!$E:$E,$O95+1),"") | C95: =IFERROR(INDEX(Combined_Data!$B:$B,$O95+1),"") | D95: =IFERROR(INDEX(Combined_Data!$D:$D,$O95+1),"") | E95: =IFERROR(INDEX(Combined_Data!$G:$G,$O95+1),"") | F95: =IFERROR(INDEX(Combined_Data!$I:$I,$O95+1),"") | G95: =IFERROR(INDEX(Combined_Data!$K:$K,$O95+1),"") | H95: =IFERROR(INDEX(Combined_Data!$M:$M,$O95+1),"") | I95: =IFERROR(INDEX(Combined_Data!$N:$N,$O95+1),"") | J95: =IFERROR(INDEX(Combined_Data!$S:$S,$O95+1),"") | K95: =IFERROR(INDEX(Combined_Data!$AF:$AF,$O95+1),"") | L95: =IFERROR(INDEX(Combined_Data!$AG:$AG,$O95+1),"") | M95: =IFERROR(INDEX(Combined_Data!$AH:$AH,$O95+1),"") | O95: =IFERROR(_xlfn.AGGREGATE(15,6,(ROW(Combined_Data!$AI$2:$AI$3001)-1)/(Combined_Data!$AI$2:$AI$3001),61),"")
A96: =IFERROR(INDEX(Combined_Data!$C:$C,$O96+1),"") | B96: =IFERROR(INDEX(Combined_Data!$E:$E,$O96+1),"") | C96: =IFERROR(INDEX(Combined_Data!$B:$B,$O96+1),"") | D96: =IFERROR(INDEX(Combined_Data!$D:$D,$O96+1),"") | E96: =IFERROR(INDEX(Combined_Data!$G:$G,$O96+1),"") | F96: =IFERROR(INDEX(Combined_Data!$I:$I,$O96+1),"") | G96: =IFERROR(INDEX(Combined_Data!$K:$K,$O96+1),"") | H96: =IFERROR(INDEX(Combined_Data!$M:$M,$O96+1),"") | I96: =IFERROR(INDEX(Combined_Data!$N:$N,$O96+1),"") | J96: =IFERROR(INDEX(Combined_Data!$S:$S,$O96+1),"") | K96: =IFERROR(INDEX(Combined_Data!$AF:$AF,$O96+1),"") | L96: =IFERROR(INDEX(Combined_Data!$AG:$AG,$O96+1),"") | M96: =IFERROR(INDEX(Combined_Data!$AH:$AH,$O96+1),"") | O96: =IFERROR(_xlfn.AGGREGATE(15,6,(ROW(Combined_Data!$AI$2:$AI$3001)-1)/(Combined_Data!$AI$2:$AI$3001),62),"")
A97: =IFERROR(INDEX(Combined_Data!$C:$C,$O97+1),"") | B97: =IFERROR(INDEX(Combined_Data!$E:$E,$O97+1),"") | C97: =IFERROR(INDEX(Combined_Data!$B:$B,$O97+1),"") | D97: =IFERROR(INDEX(Combined_Data!$D:$D,$O97+1),"") | E97: =IFERROR(INDEX(Combined_Data!$G:$G,$O97+1),"") | F97: =IFERROR(INDEX(Combined_Data!$I:$I,$O97+1),"") | G97: =IFERROR(INDEX(Combined_Data!$K:$K,$O97+1),"") | H97: =IFERROR(INDEX(Combined_Data!$M:$M,$O97+1),"") | I97: =IFERROR(INDEX(Combined_Data!$N:$N,$O97+1),"") | J97: =IFERROR(INDEX(Combined_Data!$S:$S,$O97+1),"") | K97: =IFERROR(INDEX(Combined_Data!$AF:$AF,$O97+1),"") | L97: =IFERROR(INDEX(Combined_Data!$AG:$AG,$O97+1),"") | M97: =IFERROR(INDEX(Combined_Data!$AH:$AH,$O97+1),"") | O97: =IFERROR(_xlfn.AGGREGATE(15,6,(ROW(Combined_Data!$AI$2:$AI$3001)-1)/(Combined_Data!$AI$2:$AI$3001),63),"")
A98: =IFERROR(INDEX(Combined_Data!$C:$C,$O98+1),"") | B98: =IFERROR(INDEX(Combined_Data!$E:$E,$O98+1),"") | C98: =IFERROR(INDEX(Combined_Data!$B:$B,$O98+1),"") | D98: =IFERROR(INDEX(Combined_Data!$D:$D,$O98+1),"") | E98: =IFERROR(INDEX(Combined_Data!$G:$G,$O98+1),"") | F98: =IFERROR(INDEX(Combined_Data!$I:$I,$O98+1),"") | G98: =IFERROR(INDEX(Combined_Data!$K:$K,$O98+1),"") | H98: =IFERROR(INDEX(Combined_Data!$M:$M,$O98+1),"") | I98: =IFERROR(INDEX(Combined_Data!$N:$N,$O98+1),"") | J98: =IFERROR(INDEX(Combined_Data!$S:$S,$O98+1),"") | K98: =IFERROR(INDEX(Combined_Data!$AF:$AF,$O98+1),"") | L98: =IFERROR(INDEX(Combined_Data!$AG:$AG,$O98+1),"") | M98: =IFERROR(INDEX(Combined_Data!$AH:$AH,$O98+1),"") | O98: =IFERROR(_xlfn.AGGREGATE(15,6,(ROW(Combined_Data!$AI$2:$AI$3001)-1)/(Combined_Data!$AI$2:$AI$3001),64),"")
A99: =IFERROR(INDEX(Combined_Data!$C:$C,$O99+1),"") | B99: =IFERROR(INDEX(Combined_Data!$E:$E,$O99+1),"") | C99: =IFERROR(INDEX(Combined_Data!$B:$B,$O99+1),"") | D99: =IFERROR(INDEX(Combined_Data!$D:$D,$O99+1),"") | E99: =IFERROR(INDEX(Combined_Data!$G:$G,$O99+1),"") | F99: =IFERROR(INDEX(Combined_Data!$I:$I,$O99+1),"") | G99: =IFERROR(INDEX(Combined_Data!$K:$K,$O99+1),"") | H99: =IFERROR(INDEX(Combined_Data!$M:$M,$O99+1),"") | I99: =IFERROR(INDEX(Combined_Data!$N:$N,$O99+1),"") | J99: =IFERROR(INDEX(Combined_Data!$S:$S,$O99+1),"") | K99: =IFERROR(INDEX(Combined_Data!$AF:$AF,$O99+1),"") | L99: =IFERROR(INDEX(Combined_Data!$AG:$AG,$O99+1),"") | M99: =IFERROR(INDEX(Combined_Data!$AH:$AH,$O99+1),"") | O99: =IFERROR(_xlfn.AGGREGATE(15,6,(ROW(Combined_Data!$AI$2:$AI$3001)-1)/(Combined_Data!$AI$2:$AI$3001),65),"")
A100: =IFERROR(INDEX(Combined_Data!$C:$C,$O100+1),"") | B100: =IFERROR(INDEX(Combined_Data!$E:$E,$O100+1),"") | C100: =IFERROR(INDEX(Combined_Data!$B:$B,$O100+1),"") | D100: =IFERROR(INDEX(Combined_Data!$D:$D,$O100+1),"") | E100: =IFERROR(INDEX(Combined_Data!$G:$G,$O100+1),"") | F100: =IFERROR(INDEX(Combined_Data!$I:$I,$O100+1),"") | G100: =IFERROR(INDEX(Combined_Data!$K:$K,$O100+1),"") | H100: =IFERROR(INDEX(Combined_Data!$M:$M,$O100+1),"") | I100: =IFERROR(INDEX(Combined_Data!$N:$N,$O100+1),"") | J100: =IFERROR(INDEX(Combined_Data!$S:$S,$O100+1),"") | K100: =IFERROR(INDEX(Combined_Data!$AF:$AF,$O100+1),"") | L100: =IFERROR(INDEX(Combined_Data!$AG:$AG,$O100+1),"") | M100: =IFERROR(INDEX(Combined_Data!$AH:$AH,$O100+1),"") | O100: =IFERROR(_xlfn.AGGREGATE(15,6,(ROW(Combined_Data!$AI$2:$AI$3001)-1)/(Combined_Data!$AI$2:$AI$3001),66),"")
A101: =IFERROR(INDEX(Combined_Data!$C:$C,$O101+1),"") | B101: =IFERROR(INDEX(Combined_Data!$E:$E,$O101+1),"") | C101: =IFERROR(INDEX(Combined_Data!$B:$B,$O101+1),"") | D101: =IFERROR(INDEX(Combined_Data!$D:$D,$O101+1),"") | E101: =IFERROR(INDEX(Combined_Data!$G:$G,$O101+1),"") | F101: =IFERROR(INDEX(Combined_Data!$I:$I,$O101+1),"") | G101: =IFERROR(INDEX(Combined_Data!$K:$K,$O101+1),"") | H101: =IFERROR(INDEX(Combined_Data!$M:$M,$O101+1),"") | I101: =IFERROR(INDEX(Combined_Data!$N:$N,$O101+1),"") | J101: =IFERROR(INDEX(Combined_Data!$S:$S,$O101+1),"") | K101: =IFERROR(INDEX(Combined_Data!$AF:$AF,$O101+1),"") | L101: =IFERROR(INDEX(Combined_Data!$AG:$AG,$O101+1),"") | M101: =IFERROR(INDEX(Combined_Data!$AH:$AH,$O101+1),"") | O101: =IFERROR(_xlfn.AGGREGATE(15,6,(ROW(Combined_Data!$AI$2:$AI$3001)-1)/(Combined_Data!$AI$2:$AI$3001),67),"")
A102: =IFERROR(INDEX(Combined_Data!$C:$C,$O102+1),"") | B102: =IFERROR(INDEX(Combined_Data!$E:$E,$O102+1),"") | C102: =IFERROR(INDEX(Combined_Data!$B:$B,$O102+1),"") | D102: =IFERROR(INDEX(Combined_Data!$D:$D,$O102+1),"") | E102: =IFERROR(INDEX(Combined_Data!$G:$G,$O102+1),"") | F102: =IFERROR(INDEX(Combined_Data!$I:$I,$O102+1),"") | G102: =IFERROR(INDEX(Combined_Data!$K:$K,$O102+1),"") | H102: =IFERROR(INDEX(Combined_Data!$M:$M,$O102+1),"") | I102: =IFERROR(INDEX(Combined_Data!$N:$N,$O102+1),"") | J102: =IFERROR(INDEX(Combined_Data!$S:$S,$O102+1),"") | K102: =IFERROR(INDEX(Combined_Data!$AF:$AF,$O102+1),"") | L102: =IFERROR(INDEX(Combined_Data!$AG:$AG,$O102+1),"") | M102: =IFERROR(INDEX(Combined_Data!$AH:$AH,$O102+1),"") | O102: =IFERROR(_xlfn.AGGREGATE(15,6,(ROW(Combined_Data!$AI$2:$AI$3001)-1)/(Combined_Data!$AI$2:$AI$3001),68),"")
A103: =IFERROR(INDEX(Combined_Data!$C:$C,$O103+1),"") | B103: =IFERROR(INDEX(Combined_Data!$E:$E,$O103+1),"") | C103: =IFERROR(INDEX(Combined_Data!$B:$B,$O103+1),"") | D103: =IFERROR(INDEX(Combined_Data!$D:$D,$O103+1),"") | E103: =IFERROR(INDEX(Combined_Data!$G:$G,$O103+1),"") | F103: =IFERROR(INDEX(Combined_Data!$I:$I,$O103+1),"") | G103: =IFERROR(INDEX(Combined_Data!$K:$K,$O103+1),"") | H103: =IFERROR(INDEX(Combined_Data!$M:$M,$O103+1),"") | I103: =IFERROR(INDEX(Combined_Data!$N:$N,$O103+1),"") | J103: =IFERROR(INDEX(Combined_Data!$S:$S,$O103+1),"") | K103: =IFERROR(INDEX(Combined_Data!$AF:$AF,$O103+1),"") | L103: =IFERROR(INDEX(Combined_Data!$AG:$AG,$O103+1),"") | M103: =IFERROR(INDEX(Combined_Data!$AH:$AH,$O103+1),"") | O103: =IFERROR(_xlfn.AGGREGATE(15,6,(ROW(Combined_Data!$AI$2:$AI$3001)-1)/(Combined_Data!$AI$2:$AI$3001),69),"")
A104: =IFERROR(INDEX(Combined_Data!$C:$C,$O104+1),"") | B104: =IFERROR(INDEX(Combined_Data!$E:$E,$O104+1),"") | C104: =IFERROR(INDEX(Combined_Data!$B:$B,$O104+1),"") | D104: =IFERROR(INDEX(Combined_Data!$D:$D,$O104+1),"") | E104: =IFERROR(INDEX(Combined_Data!$G:$G,$O104+1),"") | F104: =IFERROR(INDEX(Combined_Data!$I:$I,$O104+1),"") | G104: =IFERROR(INDEX(Combined_Data!$K:$K,$O104+1),"") | H104: =IFERROR(INDEX(Combined_Data!$M:$M,$O104+1),"") | I104: =IFERROR(INDEX(Combined_Data!$N:$N,$O104+1),"") | J104: =IFERROR(INDEX(Combined_Data!$S:$S,$O104+1),"") | K104: =IFERROR(INDEX(Combined_Data!$AF:$AF,$O104+1),"") | L104: =IFERROR(INDEX(Combined_Data!$AG:$AG,$O104+1),"") | M104: =IFERROR(INDEX(Combined_Data!$AH:$AH,$O104+1),"") | O104: =IFERROR(_xlfn.AGGREGATE(15,6,(ROW(Combined_Data!$AI$2:$AI$3001)-1)/(Combined_Data!$AI$2:$AI$3001),70),"")
A105: =IFERROR(INDEX(Combined_Data!$C:$C,$O105+1),"") | B105: =IFERROR(INDEX(Combined_Data!$E:$E,$O105+1),"") | C105: =IFERROR(INDEX(Combined_Data!$B:$B,$O105+1),"") | D105: =IFERROR(INDEX(Combined_Data!$D:$D,$O105+1),"") | E105: =IFERROR(INDEX(Combined_Data!$G:$G,$O105+1),"") | F105: =IFERROR(INDEX(Combined_Data!$I:$I,$O105+1),"") | G105: =IFERROR(INDEX(Combined_Data!$K:$K,$O105+1),"") | H105: =IFERROR(INDEX(Combined_Data!$M:$M,$O105+1),"") | I105: =IFERROR(INDEX(Combined_Data!$N:$N,$O105+1),"") | J105: =IFERROR(INDEX(Combined_Data!$S:$S,$O105+1),"") | K105: =IFERROR(INDEX(Combined_Data!$AF:$AF,$O105+1),"") | L105: =IFERROR(INDEX(Combined_Data!$AG:$AG,$O105+1),"") | M105: =IFERROR(INDEX(Combined_Data!$AH:$AH,$O105+1),"") | O105: =IFERROR(_xlfn.AGGREGATE(15,6,(ROW(Combined_Data!$AI$2:$AI$3001)-1)/(Combined_Data!$AI$2:$AI$3001),71),"")
A106: =IFERROR(INDEX(Combined_Data!$C:$C,$O106+1),"") | B106: =IFERROR(INDEX(Combined_Data!$E:$E,$O106+1),"") | C106: =IFERROR(INDEX(Combined_Data!$B:$B,$O106+1),"") | D106: =IFERROR(INDEX(Combined_Data!$D:$D,$O106+1),"") | E106: =IFERROR(INDEX(Combined_Data!$G:$G,$O106+1),"") | F106: =IFERROR(INDEX(Combined_Data!$I:$I,$O106+1),"") | G106: =IFERROR(INDEX(Combined_Data!$K:$K,$O106+1),"") | H106: =IFERROR(INDEX(Combined_Data!$M:$M,$O106+1),"") | I106: =IFERROR(INDEX(Combined_Data!$N:$N,$O106+1),"") | J106: =IFERROR(INDEX(Combined_Data!$S:$S,$O106+1),"") | K106: =IFERROR(INDEX(Combined_Data!$AF:$AF,$O106+1),"") | L106: =IFERROR(INDEX(Combined_Data!$AG:$AG,$O106+1),"") | M106: =IFERROR(INDEX(Combined_Data!$AH:$AH,$O106+1),"") | O106: =IFERROR(_xlfn.AGGREGATE(15,6,(ROW(Combined_Data!$AI$2:$AI$3001)-1)/(Combined_Data!$AI$2:$AI$3001),72),"")
A107: =IFERROR(INDEX(Combined_Data!$C:$C,$O107+1),"") | B107: =IFERROR(INDEX(Combined_Data!$E:$E,$O107+1),"") | C107: =IFERROR(INDEX(Combined_Data!$B:$B,$O107+1),"") | D107: =IFERROR(INDEX(Combined_Data!$D:$D,$O107+1),"") | E107: =IFERROR(INDEX(Combined_Data!$G:$G,$O107+1),"") | F107: =IFERROR(INDEX(Combined_Data!$I:$I,$O107+1),"") | G107: =IFERROR(INDEX(Combined_Data!$K:$K,$O107+1),"") | H107: =IFERROR(INDEX(Combined_Data!$M:$M,$O107+1),"") | I107: =IFERROR(INDEX(Combined_Data!$N:$N,$O107+1),"") | J107: =IFERROR(INDEX(Combined_Data!$S:$S,$O107+1),"") | K107: =IFERROR(INDEX(Combined_Data!$AF:$AF,$O107+1),"") | L107: =IFERROR(INDEX(Combined_Data!$AG:$AG,$O107+1),"") | M107: =IFERROR(INDEX(Combined_Data!$AH:$AH,$O107+1),"") | O107: =IFERROR(_xlfn.AGGREGATE(15,6,(ROW(Combined_Data!$AI$2:$AI$3001)-1)/(Combined_Data!$AI$2:$AI$3001),73),"")
A108: =IFERROR(INDEX(Combined_Data!$C:$C,$O108+1),"") | B108: =IFERROR(INDEX(Combined_Data!$E:$E,$O108+1),"") | C108: =IFERROR(INDEX(Combined_Data!$B:$B,$O108+1),"") | D108: =IFERROR(INDEX(Combined_Data!$D:$D,$O108+1),"") | E108: =IFERROR(INDEX(Combined_Data!$G:$G,$O108+1),"") | F108: =IFERROR(INDEX(Combined_Data!$I:$I,$O108+1),"") | G108: =IFERROR(INDEX(Combined_Data!$K:$K,$O108+1),"") | H108: =IFERROR(INDEX(Combined_Data!$M:$M,$O108+1),"") | I108: =IFERROR(INDEX(Combined_Data!$N:$N,$O108+1),"") | J108: =IFERROR(INDEX(Combined_Data!$S:$S,$O108+1),"") | K108: =IFERROR(INDEX(Combined_Data!$AF:$AF,$O108+1),"") | L108: =IFERROR(INDEX(Combined_Data!$AG:$AG,$O108+1),"") | M108: =IFERROR(INDEX(Combined_Data!$AH:$AH,$O108+1),"") | O108: =IFERROR(_xlfn.AGGREGATE(15,6,(ROW(Combined_Data!$AI$2:$AI$3001)-1)/(Combined_Data!$AI$2:$AI$3001),74),"")
A109: =IFERROR(INDEX(Combined_Data!$C:$C,$O109+1),"") | B109: =IFERROR(INDEX(Combined_Data!$E:$E,$O109+1),"") | C109: =IFERROR(INDEX(Combined_Data!$B:$B,$O109+1),"") | D109: =IFERROR(INDEX(Combined_Data!$D:$D,$O109+1),"") | E109: =IFERROR(INDEX(Combined_Data!$G:$G,$O109+1),"") | F109: =IFERROR(INDEX(Combined_Data!$I:$I,$O109+1),"") | G109: =IFERROR(INDEX(Combined_Data!$K:$K,$O109+1),"") | H109: =IFERROR(INDEX(Combined_Data!$M:$M,$O109+1),"") | I109: =IFERROR(INDEX(Combined_Data!$N:$N,$O109+1),"") | J109: =IFERROR(INDEX(Combined_Data!$S:$S,$O109+1),"") | K109: =IFERROR(INDEX(Combined_Data!$AF:$AF,$O109+1),"") | L109: =IFERROR(INDEX(Combined_Data!$AG:$AG,$O109+1),"") | M109: =IFERROR(INDEX(Combined_Data!$AH:$AH,$O109+1),"") | O109: =IFERROR(_xlfn.AGGREGATE(15,6,(ROW(Combined_Data!$AI$2:$AI$3001)-1)/(Combined_Data!$AI$2:$AI$3001),75),"")
A110: =IFERROR(INDEX(Combined_Data!$C:$C,$O110+1),"") | B110: =IFERROR(INDEX(Combined_Data!$E:$E,$O110+1),"") | C110: =IFERROR(INDEX(Combined_Data!$B:$B,$O110+1),"") | D110: =IFERROR(INDEX(Combined_Data!$D:$D,$O110+1),"") | E110: =IFERROR(INDEX(Combined_Data!$G:$G,$O110+1),"") | F110: =IFERROR(INDEX(Combined_Data!$I:$I,$O110+1),"") | G110: =IFERROR(INDEX(Combined_Data!$K:$K,$O110+1),"") | H110: =IFERROR(INDEX(Combined_Data!$M:$M,$O110+1),"") | I110: =IFERROR(INDEX(Combined_Data!$N:$N,$O110+1),"") | J110: =IFERROR(INDEX(Combined_Data!$S:$S,$O110+1),"") | K110: =IFERROR(INDEX(Combined_Data!$AF:$AF,$O110+1),"") | L110: =IFERROR(INDEX(Combined_Data!$AG:$AG,$O110+1),"") | M110: =IFERROR(INDEX(Combined_Data!$AH:$AH,$O110+1),"") | O110: =IFERROR(_xlfn.AGGREGATE(15,6,(ROW(Combined_Data!$AI$2:$AI$3001)-1)/(Combined_Data!$AI$2:$AI$3001),76),"")
A111: =IFERROR(INDEX(Combined_Data!$C:$C,$O111+1),"") | B111: =IFERROR(INDEX(Combined_Data!$E:$E,$O111+1),"") | C111: =IFERROR(INDEX(Combined_Data!$B:$B,$O111+1),"") | D111: =IFERROR(INDEX(Combined_Data!$D:$D,$O111+1),"") | E111: =IFERROR(INDEX(Combined_Data!$G:$G,$O111+1),"") | F111: =IFERROR(INDEX(Combined_Data!$I:$I,$O111+1),"") | G111: =IFERROR(INDEX(Combined_Data!$K:$K,$O111+1),"") | H111: =IFERROR(INDEX(Combined_Data!$M:$M,$O111+1),"") | I111: =IFERROR(INDEX(Combined_Data!$N:$N,$O111+1),"") | J111: =IFERROR(INDEX(Combined_Data!$S:$S,$O111+1),"") | K111: =IFERROR(INDEX(Combined_Data!$AF:$AF,$O111+1),"") | L111: =IFERROR(INDEX(Combined_Data!$AG:$AG,$O111+1),"") | M111: =IFERROR(INDEX(Combined_Data!$AH:$AH,$O111+1),"") | O111: =IFERROR(_xlfn.AGGREGATE(15,6,(ROW(Combined_Data!$AI$2:$AI$3001)-1)/(Combined_Data!$AI$2:$AI$3001),77),"")
A112: =IFERROR(INDEX(Combined_Data!$C:$C,$O112+1),"") | B112: =IFERROR(INDEX(Combined_Data!$E:$E,$O112+1),"") | C112: =IFERROR(INDEX(Combined_Data!$B:$B,$O112+1),"") | D112: =IFERROR(INDEX(Combined_Data!$D:$D,$O112+1),"") | E112: =IFERROR(INDEX(Combined_Data!$G:$G,$O112+1),"") | F112: =IFERROR(INDEX(Combined_Data!$I:$I,$O112+1),"") | G112: =IFERROR(INDEX(Combined_Data!$K:$K,$O112+1),"") | H112: =IFERROR(INDEX(Combined_Data!$M:$M,$O112+1),"") | I112: =IFERROR(INDEX(Combined_Data!$N:$N,$O112+1),"") | J112: =IFERROR(INDEX(Combined_Data!$S:$S,$O112+1),"") | K112: =IFERROR(INDEX(Combined_Data!$AF:$AF,$O112+1),"") | L112: =IFERROR(INDEX(Combined_Data!$AG:$AG,$O112+1),"") | M112: =IFERROR(INDEX(Combined_Data!$AH:$AH,$O112+1),"") | O112: =IFERROR(_xlfn.AGGREGATE(15,6,(ROW(Combined_Data!$AI$2:$AI$3001)-1)/(Combined_Data!$AI$2:$AI$3001),78),"")
A113: =IFERROR(INDEX(Combined_Data!$C:$C,$O113+1),"") | B113: =IFERROR(INDEX(Combined_Data!$E:$E,$O113+1),"") | C113: =IFERROR(INDEX(Combined_Data!$B:$B,$O113+1),"") | D113: =IFERROR(INDEX(Combined_Data!$D:$D,$O113+1),"") | E113: =IFERROR(INDEX(Combined_Data!$G:$G,$O113+1),"") | F113: =IFERROR(INDEX(Combined_Data!$I:$I,$O113+1),"") | G113: =IFERROR(INDEX(Combined_Data!$K:$K,$O113+1),"") | H113: =IFERROR(INDEX(Combined_Data!$M:$M,$O113+1),"") | I113: =IFERROR(INDEX(Combined_Data!$N:$N,$O113+1),"") | J113: =IFERROR(INDEX(Combined_Data!$S:$S,$O113+1),"") | K113: =IFERROR(INDEX(Combined_Data!$AF:$AF,$O113+1),"") | L113: =IFERROR(INDEX(Combined_Data!$AG:$AG,$O113+1),"") | M113: =IFERROR(INDEX(Combined_Data!$AH:$AH,$O113+1),"") | O113: =IFERROR(_xlfn.AGGREGATE(15,6,(ROW(Combined_Data!$AI$2:$AI$3001)-1)/(Combined_Data!$AI$2:$AI$3001),79),"")
A114: =IFERROR(INDEX(Combined_Data!$C:$C,$O114+1),"") | B114: =IFERROR(INDEX(Combined_Data!$E:$E,$O114+1),"") | C114: =IFERROR(INDEX(Combined_Data!$B:$B,$O114+1),"") | D114: =IFERROR(INDEX(Combined_Data!$D:$D,$O114+1),"") | E114: =IFERROR(INDEX(Combined_Data!$G:$G,$O114+1),"") | F114: =IFERROR(INDEX(Combined_Data!$I:$I,$O114+1),"") | G114: =IFERROR(INDEX(Combined_Data!$K:$K,$O114+1),"") | H114: =IFERROR(INDEX(Combined_Data!$M:$M,$O114+1),"") | I114: =IFERROR(INDEX(Combined_Data!$N:$N,$O114+1),"") | J114: =IFERROR(INDEX(Combined_Data!$S:$S,$O114+1),"") | K114: =IFERROR(INDEX(Combined_Data!$AF:$AF,$O114+1),"") | L114: =IFERROR(INDEX(Combined_Data!$AG:$AG,$O114+1),"") | M114: =IFERROR(INDEX(Combined_Data!$AH:$AH,$O114+1),"") | O114: =IFERROR(_xlfn.AGGREGATE(15,6,(ROW(Combined_Data!$AI$2:$AI$3001)-1)/(Combined_Data!$AI$2:$AI$3001),80),"")
A115: =IFERROR(INDEX(Combined_Data!$C:$C,$O115+1),"") | B115: =IFERROR(INDEX(Combined_Data!$E:$E,$O115+1),"") | C115: =IFERROR(INDEX(Combined_Data!$B:$B,$O115+1),"") | D115: =IFERROR(INDEX(Combined_Data!$D:$D,$O115+1),"") | E115: =IFERROR(INDEX(Combined_Data!$G:$G,$O115+1),"") | F115: =IFERROR(INDEX(Combined_Data!$I:$I,$O115+1),"") | G115: =IFERROR(INDEX(Combined_Data!$K:$K,$O115+1),"") | H115: =IFERROR(INDEX(Combined_Data!$M:$M,$O115+1),"") | I115: =IFERROR(INDEX(Combined_Data!$N:$N,$O115+1),"") | J115: =IFERROR(INDEX(Combined_Data!$S:$S,$O115+1),"") | K115: =IFERROR(INDEX(Combined_Data!$AF:$AF,$O115+1),"") | L115: =IFERROR(INDEX(Combined_Data!$AG:$AG,$O115+1),"") | M115: =IFERROR(INDEX(Combined_Data!$AH:$AH,$O115+1),"") | O115: =IFERROR(_xlfn.AGGREGATE(15,6,(ROW(Combined_Data!$AI$2:$AI$3001)-1)/(Combined_Data!$AI$2:$AI$3001),81),"")
A116: =IFERROR(INDEX(Combined_Data!$C:$C,$O116+1),"") | B116: =IFERROR(INDEX(Combined_Data!$E:$E,$O116+1),"") | C116: =IFERROR(INDEX(Combined_Data!$B:$B,$O116+1),"") | D116: =IFERROR(INDEX(Combined_Data!$D:$D,$O116+1),"") | E116: =IFERROR(INDEX(Combined_Data!$G:$G,$O116+1),"") | F116: =IFERROR(INDEX(Combined_Data!$I:$I,$O116+1),"") | G116: =IFERROR(INDEX(Combined_Data!$K:$K,$O116+1),"") | H116: =IFERROR(INDEX(Combined_Data!$M:$M,$O116+1),"") | I116: =IFERROR(INDEX(Combined_Data!$N:$N,$O116+1),"") | J116: =IFERROR(INDEX(Combined_Data!$S:$S,$O116+1),"") | K116: =IFERROR(INDEX(Combined_Data!$AF:$AF,$O116+1),"") | L116: =IFERROR(INDEX(Combined_Data!$AG:$AG,$O116+1),"") | M116: =IFERROR(INDEX(Combined_Data!$AH:$AH,$O116+1),"") | O116: =IFERROR(_xlfn.AGGREGATE(15,6,(ROW(Combined_Data!$AI$2:$AI$3001)-1)/(Combined_Data!$AI$2:$AI$3001),82),"")
A117: =IFERROR(INDEX(Combined_Data!$C:$C,$O117+1),"") | B117: =IFERROR(INDEX(Combined_Data!$E:$E,$O117+1),"") | C117: =IFERROR(INDEX(Combined_Data!$B:$B,$O117+1),"") | D117: =IFERROR(INDEX(Combined_Data!$D:$D,$O117+1),"") | E117: =IFERROR(INDEX(Combined_Data!$G:$G,$O117+1),"") | F117: =IFERROR(INDEX(Combined_Data!$I:$I,$O117+1),"") | G117: =IFERROR(INDEX(Combined_Data!$K:$K,$O117+1),"") | H117: =IFERROR(INDEX(Combined_Data!$M:$M,$O117+1),"") | I117: =IFERROR(INDEX(Combined_Data!$N:$N,$O117+1),"") | J117: =IFERROR(INDEX(Combined_Data!$S:$S,$O117+1),"") | K117: =IFERROR(INDEX(Combined_Data!$AF:$AF,$O117+1),"") | L117: =IFERROR(INDEX(Combined_Data!$AG:$AG,$O117+1),"") | M117: =IFERROR(INDEX(Combined_Data!$AH:$AH,$O117+1),"") | O117: =IFERROR(_xlfn.AGGREGATE(15,6,(ROW(Combined_Data!$AI$2:$AI$3001)-1)/(Combined_Data!$AI$2:$AI$3001),83),"")
...

Sheet Platform_Breakdown
A1: Platform-wise Breakdown
A2: Role mix, salary levels & ghost rate — LinkedIn vs Indeed vs Glassdoor
A4: Role Distribution by Platform (listing count) | G4: Salary & Ghost Rate by Platform
A5: Role Bucket | B5: LinkedIn | C5: Indeed | D5: Glassdoor | G5: Portal | H5: Avg Annual Salary (INR est.) | I5: # Salary-Comparable | J5: Ghost Rate %
A6: Software Engineer | B6: =COUNTIFS(Combined_Data!$D$2:$D$3001,"Software Engineer",Combined_Data!$B$2:$B$3001,"LinkedIn") -> 701 | C6: =COUNTIFS(Combined_Data!$D$2:$D$3001,"Software Engineer",Combined_Data!$B$2:$B$3001,"Indeed") -> 288 | D6: =COUNTIFS(Combined_Data!$D$2:$D$3001,"Software Engineer",Combined_Data!$B$2:$B$3001,"Glassdoor") -> 209 | G6: LinkedIn | H6: =IFERROR(AVERAGEIFS(Combined_Data!$S$2:$S$3001,Combined_Data!$B$2:$B$3001,"LinkedIn",Combined_Data!$T$2:$T$3001,TRUE()),0) -> 0 | I6: =COUNTIFS(Combined_Data!$B$2:$B$3001,"LinkedIn",Combined_Data!$T$2:$T$3001,TRUE()) -> 0 | J6: =COUNTIFS(Combined_Data!$B$2:$B$3001,"LinkedIn",Combined_Data!$AG$2:$AG$3001,"Likely Ghost")/COUNTIF(Combined_Data!$B$2:$B$3001,"LinkedIn")*100 -> 7.7
A7: Other | B7: =COUNTIFS(Combined_Data!$D$2:$D$3001,"Other",Combined_Data!$B$2:$B$3001,"LinkedIn") -> 63 | C7: =COUNTIFS(Combined_Data!$D$2:$D$3001,"Other",Combined_Data!$B$2:$B$3001,"Indeed") -> 466 | D7: =COUNTIFS(Combined_Data!$D$2:$D$3001,"Other",Combined_Data!$B$2:$B$3001,"Glassdoor") -> 227 | G7: Indeed | H7: =IFERROR(AVERAGEIFS(Combined_Data!$S$2:$S$3001,Combined_Data!$B$2:$B$3001,"Indeed",Combined_Data!$T$2:$T$3001,TRUE()),0) -> 712321.28 | I7: =COUNTIFS(Combined_Data!$B$2:$B$3001,"Indeed",Combined_Data!$T$2:$T$3001,TRUE()) -> 148 | J7: =COUNTIFS(Combined_Data!$B$2:$B$3001,"Indeed",Combined_Data!$AG$2:$AG$3001,"Likely Ghost")/COUNTIF(Combined_Data!$B$2:$B$3001,"Indeed")*100 -> 4.4
A8: Data Analyst | B8: =COUNTIFS(Combined_Data!$D$2:$D$3001,"Data Analyst",Combined_Data!$B$2:$B$3001,"LinkedIn") -> 0 | C8: =COUNTIFS(Combined_Data!$D$2:$D$3001,"Data Analyst",Combined_Data!$B$2:$B$3001,"Indeed") -> 93 | D8: =COUNTIFS(Combined_Data!$D$2:$D$3001,"Data Analyst",Combined_Data!$B$2:$B$3001,"Glassdoor") -> 178 | G8: Glassdoor | H8: =IFERROR(AVERAGEIFS(Combined_Data!$S$2:$S$3001,Combined_Data!$B$2:$B$3001,"Glassdoor",Combined_Data!$T$2:$T$3001,TRUE()),0) -> 608706.69 | I8: =COUNTIFS(Combined_Data!$B$2:$B$3001,"Glassdoor",Combined_Data!$T$2:$T$3001,TRUE()) -> 451 | J8: =COUNTIFS(Combined_Data!$B$2:$B$3001,"Glassdoor",Combined_Data!$AG$2:$AG$3001,"Likely Ghost")/COUNTIF(Combined_Data!$B$2:$B$3001,"Glassdoor")*100 -> 2.5
A9: ML Engineer | B9: =COUNTIFS(Combined_Data!$D$2:$D$3001,"ML Engineer",Combined_Data!$B$2:$B$3001,"LinkedIn") -> 1 | C9: =COUNTIFS(Combined_Data!$D$2:$D$3001,"ML Engineer",Combined_Data!$B$2:$B$3001,"Indeed") -> 14 | D9: =COUNTIFS(Combined_Data!$D$2:$D$3001,"ML Engineer",Combined_Data!$B$2:$B$3001,"Glassdoor") -> 189
A10: Frontend Engineer | B10: =COUNTIFS(Combined_Data!$D$2:$D$3001,"Frontend Engineer",Combined_Data!$B$2:$B$3001,"LinkedIn") -> 30 | C10: =COUNTIFS(Combined_Data!$D$2:$D$3001,"Frontend Engineer",Combined_Data!$B$2:$B$3001,"Indeed") -> 5 | D10: =COUNTIFS(Combined_Data!$D$2:$D$3001,"Frontend Engineer",Combined_Data!$B$2:$B$3001,"Glassdoor") -> 119
A11: Full Stack Engineer | B11: =COUNTIFS(Combined_Data!$D$2:$D$3001,"Full Stack Engineer",Combined_Data!$B$2:$B$3001,"LinkedIn") -> 79 | C11: =COUNTIFS(Combined_Data!$D$2:$D$3001,"Full Stack Engineer",Combined_Data!$B$2:$B$3001,"Indeed") -> 56 | D11: =COUNTIFS(Combined_Data!$D$2:$D$3001,"Full Stack Engineer",Combined_Data!$B$2:$B$3001,"Glassdoor") -> 14
A12: Backend Engineer | B12: =COUNTIFS(Combined_Data!$D$2:$D$3001,"Backend Engineer",Combined_Data!$B$2:$B$3001,"LinkedIn") -> 121 | C12: =COUNTIFS(Combined_Data!$D$2:$D$3001,"Backend Engineer",Combined_Data!$B$2:$B$3001,"Indeed") -> 16 | D12: =COUNTIFS(Combined_Data!$D$2:$D$3001,"Backend Engineer",Combined_Data!$B$2:$B$3001,"Glassdoor") -> 6
A13: Data Scientist | B13: =COUNTIFS(Combined_Data!$D$2:$D$3001,"Data Scientist",Combined_Data!$B$2:$B$3001,"LinkedIn") -> 0 | C13: =COUNTIFS(Combined_Data!$D$2:$D$3001,"Data Scientist",Combined_Data!$B$2:$B$3001,"Indeed") -> 9 | D13: =COUNTIFS(Combined_Data!$D$2:$D$3001,"Data Scientist",Combined_Data!$B$2:$B$3001,"Glassdoor") -> 36
A14: Data Engineer | B14: =COUNTIFS(Combined_Data!$D$2:$D$3001,"Data Engineer",Combined_Data!$B$2:$B$3001,"LinkedIn") -> 0 | C14: =COUNTIFS(Combined_Data!$D$2:$D$3001,"Data Engineer",Combined_Data!$B$2:$B$3001,"Indeed") -> 14 | D14: =COUNTIFS(Combined_Data!$D$2:$D$3001,"Data Engineer",Combined_Data!$B$2:$B$3001,"Glassdoor") -> 22
A15: DevOps Engineer | B15: =COUNTIFS(Combined_Data!$D$2:$D$3001,"DevOps Engineer",Combined_Data!$B$2:$B$3001,"LinkedIn") -> 0 | C15: =COUNTIFS(Combined_Data!$D$2:$D$3001,"DevOps Engineer",Combined_Data!$B$2:$B$3001,"Indeed") -> 24 | D15: =COUNTIFS(Combined_Data!$D$2:$D$3001,"DevOps Engineer",Combined_Data!$B$2:$B$3001,"Glassdoor") -> 0
A16: QA/Test Engineer | B16: =COUNTIFS(Combined_Data!$D$2:$D$3001,"QA/Test Engineer",Combined_Data!$B$2:$B$3001,"LinkedIn") -> 5 | C16: =COUNTIFS(Combined_Data!$D$2:$D$3001,"QA/Test Engineer",Combined_Data!$B$2:$B$3001,"Indeed") -> 9 | D16: =COUNTIFS(Combined_Data!$D$2:$D$3001,"QA/Test Engineer",Combined_Data!$B$2:$B$3001,"Glassdoor") -> 0
A17: Product Manager | B17: =COUNTIFS(Combined_Data!$D$2:$D$3001,"Product Manager",Combined_Data!$B$2:$B$3001,"LinkedIn") -> 0 | C17: =COUNTIFS(Combined_Data!$D$2:$D$3001,"Product Manager",Combined_Data!$B$2:$B$3001,"Indeed") -> 6 | D17: =COUNTIFS(Combined_Data!$D$2:$D$3001,"Product Manager",Combined_Data!$B$2:$B$3001,"Glassdoor") -> 0

Sheet Top_Companies
A1: Top Companies & Employer Trust Score
A2: Top 20 employers by posting volume (across all 3 platforms, names as scraped — see ReadMe on entity resolution)
A4: Company Name | B4: Total Postings | C4: Likely Ghost | D4: Ghost Rate % | E4: Avg Ghost Score % | F4: Employer Trust Score
A5: Accenture in India | B5: =COUNTIF(Combined_Data!$E$2:$E$3001,"Accenture in India") -> 429 | C5: =COUNTIFS(Combined_Data!$E$2:$E$3001,"Accenture in India",Combined_Data!$AG$2:$AG$3001,"Likely Ghost") -> 77 | D5: =C5/B5*100 -> 17.948718 | E5: =AVERAGEIF(Combined_Data!$E$2:$E$3001,"Accenture in India",Combined_Data!$AF$2:$AF$3001) -> 45.448718 | F5: =100-E5 -> 54.551282
A6: Wipro | B6: =COUNTIF(Combined_Data!$E$2:$E$3001,"Wipro") -> 81 | C6: =COUNTIFS(Combined_Data!$E$2:$E$3001,"Wipro",Combined_Data!$AG$2:$AG$3001,"Likely Ghost") -> 9 | D6: =C6/B6*100 -> 11.111111 | E6: =AVERAGEIF(Combined_Data!$E$2:$E$3001,"Wipro",Combined_Data!$AF$2:$AF$3001) -> 44.477778 | F6: =100-E6 -> 55.522222
A7: Accenture | B7: =COUNTIF(Combined_Data!$E$2:$E$3001,"Accenture") -> 64 | C7: =COUNTIFS(Combined_Data!$E$2:$E$3001,"Accenture",Combined_Data!$AG$2:$AG$3001,"Likely Ghost") -> 23 | D7: =C7/B7*100 -> 35.9375 | E7: =AVERAGEIF(Combined_Data!$E$2:$E$3001,"Accenture",Combined_Data!$AF$2:$AF$3001) -> 48.003125 | F7: =100-E7 -> 51.996875
A8: Capgemini | B8: =COUNTIF(Combined_Data!$E$2:$E$3001,"Capgemini") -> 50 | C8: =COUNTIFS(Combined_Data!$E$2:$E$3001,"Capgemini",Combined_Data!$AG$2:$AG$3001,"Likely Ghost") -> 0 | D8: =C8/B8*100 -> 0 | E8: =AVERAGEIF(Combined_Data!$E$2:$E$3001,"Capgemini",Combined_Data!$AF$2:$AF$3001) -> 28.028 | F8: =100-E8 -> 71.972
A9: Calpion | B9: =COUNTIF(Combined_Data!$E$2:$E$3001,"Calpion") -> 42 | C9: =COUNTIFS(Combined_Data!$E$2:$E$3001,"Calpion",Combined_Data!$AG$2:$AG$3001,"Likely Ghost") -> 0 | D9: =C9/B9*100 -> 0 | E9: =AVERAGEIF(Combined_Data!$E$2:$E$3001,"Calpion",Combined_Data!$AF$2:$AF$3001) -> 14.3 | F9: =100-E9 -> 85.7
A10: Amazon.com | B10: =COUNTIF(Combined_Data!$E$2:$E$3001,"Amazon.com") -> 33 | C10: =COUNTIFS(Combined_Data!$E$2:$E$3001,"Amazon.com",Combined_Data!$AG$2:$AG$3001,"Likely Ghost") -> 0 | D10: =C10/B10*100 -> 0 | E10: =AVERAGEIF(Combined_Data!$E$2:$E$3001,"Amazon.com",Combined_Data!$AF$2:$AF$3001) -> 16.9 | F10: =100-E10 -> 83.1
A11: Infosys | B11: =COUNTIF(Combined_Data!$E$2:$E$3001,"Infosys") -> 24 | C11: =COUNTIFS(Combined_Data!$E$2:$E$3001,"Infosys",Combined_Data!$AG$2:$AG$3001,"Likely Ghost") -> 0 | D11: =C11/B11*100 -> 0 | E11: =AVERAGEIF(Combined_Data!$E$2:$E$3001,"Infosys",Combined_Data!$AF$2:$AF$3001) -> 29.195833 | F11: =100-E11 -> 70.804167
A12: U.S. Bank | B12: =COUNTIF(Combined_Data!$E$2:$E$3001,"U.S. Bank") -> 18 | C12: =COUNTIFS(Combined_Data!$E$2:$E$3001,"U.S. Bank",Combined_Data!$AG$2:$AG$3001,"Likely Ghost") -> 0 | D12: =C12/B12*100 -> 0 | E12: =AVERAGEIF(Combined_Data!$E$2:$E$3001,"U.S. Bank",Combined_Data!$AF$2:$AF$3001) -> 14.3 | F12: =100-E12 -> 85.7
A13: Citi | B13: =COUNTIF(Combined_Data!$E$2:$E$3001,"Citi") -> 18 | C13: =COUNTIFS(Combined_Data!$E$2:$E$3001,"Citi",Combined_Data!$AG$2:$AG$3001,"Likely Ghost") -> 0 | D13: =C13/B13*100 -> 0 | E13: =AVERAGEIF(Combined_Data!$E$2:$E$3001,"Citi",Combined_Data!$AF$2:$AF$3001) -> 19.066667 | F13: =100-E13 -> 80.933333
A14: Citigroup Inc. | B14: =COUNTIF(Combined_Data!$E$2:$E$3001,"Citigroup Inc.") -> 18 | C14: =COUNTIFS(Combined_Data!$E$2:$E$3001,"Citigroup Inc.",Combined_Data!$AG$2:$AG$3001,"Likely Ghost") -> 1 | D14: =C14/B14*100 -> 5.5555556 | E14: =AVERAGEIF(Combined_Data!$E$2:$E$3001,"Citigroup Inc.",Combined_Data!$AF$2:$AF$3001) -> 37.333333 | F14: =100-E14 -> 62.666667
A15: Amazon.com, Inc. | B15: =COUNTIF(Combined_Data!$E$2:$E$3001,"Amazon.com, Inc.") -> 17 | C15: =COUNTIFS(Combined_Data!$E$2:$E$3001,"Amazon.com, Inc.",Combined_Data!$AG$2:$AG$3001,"Likely Ghost") -> 0 | D15: =C15/B15*100 -> 0 | E15: =AVERAGEIF(Combined_Data!$E$2:$E$3001,"Amazon.com, Inc.",Combined_Data!$AF$2:$AF$3001) -> 37.011765 | F15: =100-E15 -> 62.988235
A16: Accenture Ltd | B16: =COUNTIF(Combined_Data!$E$2:$E$3001,"Accenture Ltd") -> 17 | C16: =COUNTIFS(Combined_Data!$E$2:$E$3001,"Accenture Ltd",Combined_Data!$AG$2:$AG$3001,"Likely Ghost") -> 4 | D16: =C16/B16*100 -> 23.529412 | E16: =AVERAGEIF(Combined_Data!$E$2:$E$3001,"Accenture Ltd",Combined_Data!$AF$2:$AF$3001) -> 43.717647 | F16: =100-E16 -> 56.282353
A17: Deloitte | B17: =COUNTIF(Combined_Data!$E$2:$E$3001,"Deloitte") -> 16 | C17: =COUNTIFS(Combined_Data!$E$2:$E$3001,"Deloitte",Combined_Data!$AG$2:$AG$3001,"Likely Ghost") -> 0 | D17: =C17/B17*100 -> 0 | E17: =AVERAGEIF(Combined_Data!$E$2:$E$3001,"Deloitte",Combined_Data!$AF$2:$AF$3001) -> 25.91875 | F17: =100-E17 -> 74.08125
A18: Optum, Inc. | B18: =COUNTIF(Combined_Data!$E$2:$E$3001,"Optum, Inc.") -> 16 | C18: =COUNTIFS(Combined_Data!$E$2:$E$3001,"Optum, Inc.",Combined_Data!$AG$2:$AG$3001,"Likely Ghost") -> 0 | D18: =C18/B18*100 -> 0 | E18: =AVERAGEIF(Combined_Data!$E$2:$E$3001,"Optum, Inc.",Combined_Data!$AF$2:$AF$3001) -> 39.325 | F18: =100-E18 -> 60.675
A19: Amazon | B19: =COUNTIF(Combined_Data!$E$2:$E$3001,"Amazon") -> 16 | C19: =COUNTIFS(Combined_Data!$E$2:$E$3001,"Amazon",Combined_Data!$AG$2:$AG$3001,"Likely Ghost") -> 0 | D19: =C19/B19*100 -> 0 | E19: =AVERAGEIF(Combined_Data!$E$2:$E$3001,"Amazon",Combined_Data!$AF$2:$AF$3001) -> 16.0875 | F19: =100-E19 -> 83.9125
A20: JPMorganChase | B20: =COUNTIF(Combined_Data!$E$2:$E$3001,"JPMorganChase") -> 15 | C20: =COUNTIFS(Combined_Data!$E$2:$E$3001,"JPMorganChase",Combined_Data!$AG$2:$AG$3001,"Likely Ghost") -> 0 | D20: =C20/B20*100 -> 0 | E20: =AVERAGEIF(Combined_Data!$E$2:$E$3001,"JPMorganChase",Combined_Data!$AF$2:$AF$3001) -> 20.973333 | F20: =100-E20 -> 79.026667
A21: ExlService Holdings, Inc. | B21: =COUNTIF(Combined_Data!$E$2:$E$3001,"ExlService Holdings, Inc.") -> 15 | C21: =COUNTIFS(Combined_Data!$E$2:$E$3001,"ExlService Holdings, Inc.",Combined_Data!$AG$2:$AG$3001,"Likely Ghost") -> 1 | D21: =C21/B21*100 -> 6.6666667 | E21: =AVERAGEIF(Combined_Data!$E$2:$E$3001,"ExlService Holdings, Inc.",Combined_Data!$AF$2:$AF$3001) -> 40.033333 | F21: =100-E21 -> 59.966667
A22: Persistent Systems | B22: =COUNTIF(Combined_Data!$E$2:$E$3001,"Persistent Systems") -> 15 | C22: =COUNTIFS(Combined_Data!$E$2:$E$3001,"Persistent Systems",Combined_Data!$AG$2:$AG$3001,"Likely Ghost") -> 0 | D22: =C22/B22*100 -> 0 | E22: =AVERAGEIF(Combined_Data!$E$2:$E$3001,"Persistent Systems",Combined_Data!$AF$2:$AF$3001) -> 19.066667 | F22: =100-E22 -> 80.933333
A23: Cisco | B23: =COUNTIF(Combined_Data!$E$2:$E$3001,"Cisco") -> 14 | C23: =COUNTIFS(Combined_Data!$E$2:$E$3001,"Cisco",Combined_Data!$AG$2:$AG$3001,"Likely Ghost") -> 0 | D23: =C23/B23*100 -> 0 | E23: =AVERAGEIF(Combined_Data!$E$2:$E$3001,"Cisco",Combined_Data!$AF$2:$AF$3001) -> 15.321429 | F23: =100-E23 -> 84.678571
A24: Husky Injection Molding | B24: =COUNTIF(Combined_Data!$E$2:$E$3001,"Husky Injection Molding") -> 14 | C24: =COUNTIFS(Combined_Data!$E$2:$E$3001,"Husky Injection Molding",Combined_Data!$AG$2:$AG$3001,"Likely Ghost") -> 0 | D24: =C24/B24*100 -> 0 | E24: =AVERAGEIF(Combined_Data!$E$2:$E$3001,"Husky Injection Molding",Combined_Data!$AF$2:$AF$3001) -> 14.3 | F24: =100-E24 -> 85.7

Sheet Role_Analysis
A1: Role-wise Analysis
A2: Data Analyst vs Software Engineer vs ML Engineer, etc. — ghost rate & salary by role
A4: Role Bucket | B4: Total Postings | C4: Likely Ghost | D4: Ghost Rate % | E4: Avg Days Live | F4: Avg Annual Salary (INR est.)
A5: Software Engineer | B5: =COUNTIF(Combined_Data!$D$2:$D$3001,"Software Engineer") -> 1198 | C5: =COUNTIFS(Combined_Data!$D$2:$D$3001,"Software Engineer",Combined_Data!$AG$2:$AG$3001,"Likely Ghost") -> 93 | D5: =C5/B5*100 -> 7.7629382 | E5: =AVERAGEIF(Combined_Data!$D$2:$D$3001,"Software Engineer",Combined_Data!$K$2:$K$3001) -> 32.650501 | F5: =IFERROR(AVERAGEIFS(Combined_Data!$S$2:$S$3001,Combined_Data!$D$2:$D$3001,"Software Engineer",Combined_Data!$T$2:$T$3001,TRUE()),0) -> 582718.11
A6: Other | B6: =COUNTIF(Combined_Data!$D$2:$D$3001,"Other") -> 756 | C6: =COUNTIFS(Combined_Data!$D$2:$D$3001,"Other",Combined_Data!$AG$2:$AG$3001,"Likely Ghost") -> 26 | D6: =C6/B6*100 -> 3.4391534 | E6: =AVERAGEIF(Combined_Data!$D$2:$D$3001,"Other",Combined_Data!$K$2:$K$3001) -> 16.557937 | F6: =IFERROR(AVERAGEIFS(Combined_Data!$S$2:$S$3001,Combined_Data!$D$2:$D$3001,"Other",Combined_Data!$T$2:$T$3001,TRUE()),0) -> 613551.15
A7: Data Analyst | B7: =COUNTIF(Combined_Data!$D$2:$D$3001,"Data Analyst") -> 271 | C7: =COUNTIFS(Combined_Data!$D$2:$D$3001,"Data Analyst",Combined_Data!$AG$2:$AG$3001,"Likely Ghost") -> 10 | D7: =C7/B7*100 -> 3.6900369 | E7: =AVERAGEIF(Combined_Data!$D$2:$D$3001,"Data Analyst",Combined_Data!$K$2:$K$3001) -> 29.852399 | F7: =IFERROR(AVERAGEIFS(Combined_Data!$S$2:$S$3001,Combined_Data!$D$2:$D$3001,"Data Analyst",Combined_Data!$T$2:$T$3001,TRUE()),0) -> 563160.42
A8: ML Engineer | B8: =COUNTIF(Combined_Data!$D$2:$D$3001,"ML Engineer") -> 204 | C8: =COUNTIFS(Combined_Data!$D$2:$D$3001,"ML Engineer",Combined_Data!$AG$2:$AG$3001,"Likely Ghost") -> 12 | D8: =C8/B8*100 -> 5.8823529 | E8: =AVERAGEIF(Combined_Data!$D$2:$D$3001,"ML Engineer",Combined_Data!$K$2:$K$3001) -> 53.192647 | F8: =IFERROR(AVERAGEIFS(Combined_Data!$S$2:$S$3001,Combined_Data!$D$2:$D$3001,"ML Engineer",Combined_Data!$T$2:$T$3001,TRUE()),0) -> 638042.2
A9: Frontend Engineer | B9: =COUNTIF(Combined_Data!$D$2:$D$3001,"Frontend Engineer") -> 154 | C9: =COUNTIFS(Combined_Data!$D$2:$D$3001,"Frontend Engineer",Combined_Data!$AG$2:$AG$3001,"Likely Ghost") -> 3 | D9: =C9/B9*100 -> 1.9480519 | E9: =AVERAGEIF(Combined_Data!$D$2:$D$3001,"Frontend Engineer",Combined_Data!$K$2:$K$3001) -> 92.096753 | F9: =IFERROR(AVERAGEIFS(Combined_Data!$S$2:$S$3001,Combined_Data!$D$2:$D$3001,"Frontend Engineer",Combined_Data!$T$2:$T$3001,TRUE()),0) -> 633805.33
A10: Full Stack Engineer | B10: =COUNTIF(Combined_Data!$D$2:$D$3001,"Full Stack Engineer") -> 149 | C10: =COUNTIFS(Combined_Data!$D$2:$D$3001,"Full Stack Engineer",Combined_Data!$AG$2:$AG$3001,"Likely Ghost") -> 1 | D10: =C10/B10*100 -> 0.67114094 | E10: =AVERAGEIF(Combined_Data!$D$2:$D$3001,"Full Stack Engineer",Combined_Data!$K$2:$K$3001) -> 28.612081 | F10: =IFERROR(AVERAGEIFS(Combined_Data!$S$2:$S$3001,Combined_Data!$D$2:$D$3001,"Full Stack Engineer",Combined_Data!$T$2:$T$3001,TRUE()),0) -> 1387600.2
A11: Backend Engineer | B11: =COUNTIF(Combined_Data!$D$2:$D$3001,"Backend Engineer") -> 143 | C11: =COUNTIFS(Combined_Data!$D$2:$D$3001,"Backend Engineer",Combined_Data!$AG$2:$AG$3001,"Likely Ghost") -> 0 | D11: =C11/B11*100 -> 0 | E11: =AVERAGEIF(Combined_Data!$D$2:$D$3001,"Backend Engineer",Combined_Data!$K$2:$K$3001) -> 71.73986 | F11: =IFERROR(AVERAGEIFS(Combined_Data!$S$2:$S$3001,Combined_Data!$D$2:$D$3001,"Backend Engineer",Combined_Data!$T$2:$T$3001,TRUE()),0) -> 929815.25
A12: Data Scientist | B12: =COUNTIF(Combined_Data!$D$2:$D$3001,"Data Scientist") -> 45 | C12: =COUNTIFS(Combined_Data!$D$2:$D$3001,"Data Scientist",Combined_Data!$AG$2:$AG$3001,"Likely Ghost") -> 1 | D12: =C12/B12*100 -> 2.2222222 | E12: =AVERAGEIF(Combined_Data!$D$2:$D$3001,"Data Scientist",Combined_Data!$K$2:$K$3001) -> 52.62 | F12: =IFERROR(AVERAGEIFS(Combined_Data!$S$2:$S$3001,Combined_Data!$D$2:$D$3001,"Data Scientist",Combined_Data!$T$2:$T$3001,TRUE()),0) -> 596326.92
A13: Data Engineer | B13: =COUNTIF(Combined_Data!$D$2:$D$3001,"Data Engineer") -> 36 | C13: =COUNTIFS(Combined_Data!$D$2:$D$3001,"Data Engineer",Combined_Data!$AG$2:$AG$3001,"Likely Ghost") -> 0 | D13: =C13/B13*100 -> 0 | E13: =AVERAGEIF(Combined_Data!$D$2:$D$3001,"Data Engineer",Combined_Data!$K$2:$K$3001) -> 26.308333 | F13: =IFERROR(AVERAGEIFS(Combined_Data!$S$2:$S$3001,Combined_Data!$D$2:$D$3001,"Data Engineer",Combined_Data!$T$2:$T$3001,TRUE()),0) -> 906050
A14: DevOps Engineer | B14: =COUNTIF(Combined_Data!$D$2:$D$3001,"DevOps Engineer") -> 24 | C14: =COUNTIFS(Combined_Data!$D$2:$D$3001,"DevOps Engineer",Combined_Data!$AG$2:$AG$3001,"Likely Ghost") -> 0 | D14: =C14/B14*100 -> 0 | E14: =AVERAGEIF(Combined_Data!$D$2:$D$3001,"DevOps Engineer",Combined_Data!$K$2:$K$3001) -> 0.22083333 | F14: =IFERROR(AVERAGEIFS(Combined_Data!$S$2:$S$3001,Combined_Data!$D$2:$D$3001,"DevOps Engineer",Combined_Data!$T$2:$T$3001,TRUE()),0) -> 787010.67
A15: QA/Test Engineer | B15: =COUNTIF(Combined_Data!$D$2:$D$3001,"QA/Test Engineer") -> 14 | C15: =COUNTIFS(Combined_Data!$D$2:$D$3001,"QA/Test Engineer",Combined_Data!$AG$2:$AG$3001,"Likely Ghost") -> 0 | D15: =C15/B15*100 -> 0 | E15: =AVERAGEIF(Combined_Data!$D$2:$D$3001,"QA/Test Engineer",Combined_Data!$K$2:$K$3001) -> 16.135714 | F15: =IFERROR(AVERAGEIFS(Combined_Data!$S$2:$S$3001,Combined_Data!$D$2:$D$3001,"QA/Test Engineer",Combined_Data!$T$2:$T$3001,TRUE()),0) -> 919910
A16: Product Manager | B16: =COUNTIF(Combined_Data!$D$2:$D$3001,"Product Manager") -> 6 | C16: =COUNTIFS(Combined_Data!$D$2:$D$3001,"Product Manager",Combined_Data!$AG$2:$AG$3001,"Likely Ghost") -> 0 | D16: =C16/B16*100 -> 0 | E16: =AVERAGEIF(Combined_Data!$D$2:$D$3001,"Product Manager",Combined_Data!$K$2:$K$3001) -> 0.93333333 | F16: =IFERROR(AVERAGEIFS(Combined_Data!$S$2:$S$3001,Combined_Data!$D$2:$D$3001,"Product Manager",Combined_Data!$T$2:$T$3001,TRUE()),0) -> 0

Sheet City_Analysis
A1: City / Location Analysis
A2: Ghost rate & posting volume by city (top 15 cities by listing count, "Not Specified" = location omitted by scraper/employer)
A4: City | B4: Total Postings | C4: Likely Ghost | D4: Ghost Rate % | E4: Avg Days Live | F4: Avg Ghost Score %
A5: Not Specified | B5: =COUNTIF(Combined_Data!$G$2:$G$3001,"Not Specified") -> 1550 | C5: =COUNTIFS(Combined_Data!$G$2:$G$3001,"Not Specified",Combined_Data!$AG$2:$AG$3001,"Likely Ghost") -> 55 | D5: =IFERROR(C5/B5*100,0) -> 3.5483871 | E5: =IFERROR(AVERAGEIF(Combined_Data!$G$2:$G$3001,"Not Specified",Combined_Data!$K$2:$K$3001),0) -> 22.924774 | F5: =IFERROR(AVERAGEIF(Combined_Data!$G$2:$G$3001,"Not Specified",Combined_Data!$AF$2:$AF$3001),0) -> 24.343355
A6: Bengaluru | B6: =COUNTIF(Combined_Data!$G$2:$G$3001,"Bengaluru") -> 359 | C6: =COUNTIFS(Combined_Data!$G$2:$G$3001,"Bengaluru",Combined_Data!$AG$2:$AG$3001,"Likely Ghost") -> 16 | D6: =IFERROR(C6/B6*100,0) -> 4.4568245 | E6: =IFERROR(AVERAGEIF(Combined_Data!$G$2:$G$3001,"Bengaluru",Combined_Data!$K$2:$K$3001),0) -> 40.203343 | F6: =IFERROR(AVERAGEIF(Combined_Data!$G$2:$G$3001,"Bengaluru",Combined_Data!$AF$2:$AF$3001),0) -> 24.612256
A7: Chennai | B7: =COUNTIF(Combined_Data!$G$2:$G$3001,"Chennai") -> 165 | C7: =COUNTIFS(Combined_Data!$G$2:$G$3001,"Chennai",Combined_Data!$AG$2:$AG$3001,"Likely Ghost") -> 8 | D7: =IFERROR(C7/B7*100,0) -> 4.8484848 | E7: =IFERROR(AVERAGEIF(Combined_Data!$G$2:$G$3001,"Chennai",Combined_Data!$K$2:$K$3001),0) -> 44.478788 | F7: =IFERROR(AVERAGEIF(Combined_Data!$G$2:$G$3001,"Chennai",Combined_Data!$AF$2:$AF$3001),0) -> 27.728485
A8: Pune Division | B8: =COUNTIF(Combined_Data!$G$2:$G$3001,"Pune Division") -> 78 | C8: =COUNTIFS(Combined_Data!$G$2:$G$3001,"Pune Division",Combined_Data!$AG$2:$AG$3001,"Likely Ghost") -> 5 | D8: =IFERROR(C8/B8*100,0) -> 6.4102564 | E8: =IFERROR(AVERAGEIF(Combined_Data!$G$2:$G$3001,"Pune Division",Combined_Data!$K$2:$K$3001),0) -> 30.910256 | F8: =IFERROR(AVERAGEIF(Combined_Data!$G$2:$G$3001,"Pune Division",Combined_Data!$AF$2:$AF$3001),0) -> 32.44359
A9: Hyderabad | B9: =COUNTIF(Combined_Data!$G$2:$G$3001,"Hyderabad") -> 75 | C9: =COUNTIFS(Combined_Data!$G$2:$G$3001,"Hyderabad",Combined_Data!$AG$2:$AG$3001,"Likely Ghost") -> 4 | D9: =IFERROR(C9/B9*100,0) -> 5.3333333 | E9: =IFERROR(AVERAGEIF(Combined_Data!$G$2:$G$3001,"Hyderabad",Combined_Data!$K$2:$K$3001),0) -> 30.306667 | F9: =IFERROR(AVERAGEIF(Combined_Data!$G$2:$G$3001,"Hyderabad",Combined_Data!$AF$2:$AF$3001),0) -> 34.696
A10: Mumbai Metropolitan Region | B10: =COUNTIF(Combined_Data!$G$2:$G$3001,"Mumbai Metropolitan Region") -> 54 | C10: =COUNTIFS(Combined_Data!$G$2:$G$3001,"Mumbai Metropolitan Region",Combined_Data!$AG$2:$AG$3001,"Likely Ghost") -> 6 | D10: =IFERROR(C10/B10*100,0) -> 11.111111 | E10: =IFERROR(AVERAGEIF(Combined_Data!$G$2:$G$3001,"Mumbai Metropolitan Region",Combined_Data!$K$2:$K$3001),0) -> 68.518519 | F10: =IFERROR(AVERAGEIF(Combined_Data!$G$2:$G$3001,"Mumbai Metropolitan Region",Combined_Data!$AF$2:$AF$3001),0) -> 37.592593
A11: Mumbai | B11: =COUNTIF(Combined_Data!$G$2:$G$3001,"Mumbai") -> 51 | C11: =COUNTIFS(Combined_Data!$G$2:$G$3001,"Mumbai",Combined_Data!$AG$2:$AG$3001,"Likely Ghost") -> 10 | D11: =IFERROR(C11/B11*100,0) -> 19.607843 | E11: =IFERROR(AVERAGEIF(Combined_Data!$G$2:$G$3001,"Mumbai",Combined_Data!$K$2:$K$3001),0) -> 50.882353 | F11: =IFERROR(AVERAGEIF(Combined_Data!$G$2:$G$3001,"Mumbai",Combined_Data!$AF$2:$AF$3001),0) -> 30.823529
A12: Coimbatore | B12: =COUNTIF(Combined_Data!$G$2:$G$3001,"Coimbatore") -> 50 | C12: =COUNTIFS(Combined_Data!$G$2:$G$3001,"Coimbatore",Combined_Data!$AG$2:$AG$3001,"Likely Ghost") -> 7 | D12: =IFERROR(C12/B12*100,0) -> 14 | E12: =IFERROR(AVERAGEIF(Combined_Data!$G$2:$G$3001,"Coimbatore",Combined_Data!$K$2:$K$3001),0) -> 29.02 | F12: =IFERROR(AVERAGEIF(Combined_Data!$G$2:$G$3001,"Coimbatore",Combined_Data!$AF$2:$AF$3001),0) -> 37.166
A13: Jaipur | B13: =COUNTIF(Combined_Data!$G$2:$G$3001,"Jaipur") -> 47 | C13: =COUNTIFS(Combined_Data!$G$2:$G$3001,"Jaipur",Combined_Data!$AG$2:$AG$3001,"Likely Ghost") -> 4 | D13: =IFERROR(C13/B13*100,0) -> 8.5106383 | E13: =IFERROR(AVERAGEIF(Combined_Data!$G$2:$G$3001,"Jaipur",Combined_Data!$K$2:$K$3001),0) -> 28.148936 | F13: =IFERROR(AVERAGEIF(Combined_Data!$G$2:$G$3001,"Jaipur",Combined_Data!$AF$2:$AF$3001),0) -> 41.674468
A14: Gurugram | B14: =COUNTIF(Combined_Data!$G$2:$G$3001,"Gurugram") -> 46 | C14: =COUNTIFS(Combined_Data!$G$2:$G$3001,"Gurugram",Combined_Data!$AG$2:$AG$3001,"Likely Ghost") -> 3 | D14: =IFERROR(C14/B14*100,0) -> 6.5217391 | E14: =IFERROR(AVERAGEIF(Combined_Data!$G$2:$G$3001,"Gurugram",Combined_Data!$K$2:$K$3001),0) -> 25.652174 | F14: =IFERROR(AVERAGEIF(Combined_Data!$G$2:$G$3001,"Gurugram",Combined_Data!$AF$2:$AF$3001),0) -> 33.878261
A15: Pune | B15: =COUNTIF(Combined_Data!$G$2:$G$3001,"Pune") -> 46 | C15: =COUNTIFS(Combined_Data!$G$2:$G$3001,"Pune",Combined_Data!$AG$2:$AG$3001,"Likely Ghost") -> 0 | D15: =IFERROR(C15/B15*100,0) -> 0 | E15: =IFERROR(AVERAGEIF(Combined_Data!$G$2:$G$3001,"Pune",Combined_Data!$K$2:$K$3001),0) -> 62.673913 | F15: =IFERROR(AVERAGEIF(Combined_Data!$G$2:$G$3001,"Pune",Combined_Data!$AF$2:$AF$3001),0) -> 15.232609
A16: Gurgaon | B16: =COUNTIF(Combined_Data!$G$2:$G$3001,"Gurgaon") -> 33 | C16: =COUNTIFS(Combined_Data!$G$2:$G$3001,"Gurgaon",Combined_Data!$AG$2:$AG$3001,"Likely Ghost") -> 0 | D16: =IFERROR(C16/B16*100,0) -> 0 | E16: =IFERROR(AVERAGEIF(Combined_Data!$G$2:$G$3001,"Gurgaon",Combined_Data!$K$2:$K$3001),0) -> 58.909091 | F16: =IFERROR(AVERAGEIF(Combined_Data!$G$2:$G$3001,"Gurgaon",Combined_Data!$AF$2:$AF$3001),0) -> 21.233333
A17: Remote | B17: =COUNTIF(Combined_Data!$G$2:$G$3001,"Remote") -> 32 | C17: =COUNTIFS(Combined_Data!$G$2:$G$3001,"Remote",Combined_Data!$AG$2:$AG$3001,"Likely Ghost") -> 3 | D17: =IFERROR(C17/B17*100,0) -> 9.375 | E17: =IFERROR(AVERAGEIF(Combined_Data!$G$2:$G$3001,"Remote",Combined_Data!$K$2:$K$3001),0) -> 0.646875 | F17: =IFERROR(AVERAGEIF(Combined_Data!$G$2:$G$3001,"Remote",Combined_Data!$AF$2:$AF$3001),0) -> 23.228125
A18: India | B18: =COUNTIF(Combined_Data!$G$2:$G$3001,"India") -> 30 | C18: =COUNTIFS(Combined_Data!$G$2:$G$3001,"India",Combined_Data!$AG$2:$AG$3001,"Likely Ghost") -> 0 | D18: =IFERROR(C18/B18*100,0) -> 0 | E18: =IFERROR(AVERAGEIF(Combined_Data!$G$2:$G$3001,"India",Combined_Data!$K$2:$K$3001),0) -> 32.1 | F18: =IFERROR(AVERAGEIF(Combined_Data!$G$2:$G$3001,"India",Combined_Data!$AF$2:$AF$3001),0) -> 21.926667
A19: Navi Mumbai | B19: =COUNTIF(Combined_Data!$G$2:$G$3001,"Navi Mumbai") -> 28 | C19: =COUNTIFS(Combined_Data!$G$2:$G$3001,"Navi Mumbai",Combined_Data!$AG$2:$AG$3001,"Likely Ghost") -> 5 | D19: =IFERROR(C19/B19*100,0) -> 17.857143 | E19: =IFERROR(AVERAGEIF(Combined_Data!$G$2:$G$3001,"Navi Mumbai",Combined_Data!$K$2:$K$3001),0) -> 34.178571 | F19: =IFERROR(AVERAGEIF(Combined_Data!$G$2:$G$3001,"Navi Mumbai",Combined_Data!$AF$2:$AF$3001),0) -> 42.371429
A21: Note: "Not Specified" dominates because many scraped listings omit an explicit city field at source — this is a data-availability artifact, not evidence of ghosting.

Sheet Experience_Contract
A1: Experience Level & Contract Type Analysis
A2: Ghost rate by seniority level and by employment contract type
A4: Experience Level | B4: Total Postings | C4: Likely Ghost | D4: Ghost Rate % | E4: Avg Ghost Score %
A5: Not Captured by Scraper | B5: =COUNTIF(Combined_Data!$M$2:$M$3001,"Not Captured by Scraper") -> 2000 | C5: =COUNTIFS(Combined_Data!$M$2:$M$3001,"Not Captured by Scraper",Combined_Data!$AG$2:$AG$3001,"Likely Ghost") -> 69 | D5: =IFERROR(C5/B5*100,0) -> 3.45 | E5: =IFERROR(AVERAGEIF(Combined_Data!$M$2:$M$3001,"Not Captured by Scraper",Combined_Data!$AF$2:$AF$3001),0) -> 22.9552
A6: Mid-Senior level | B6: =COUNTIF(Combined_Data!$M$2:$M$3001,"Mid-Senior level") -> 579 | C6: =COUNTIFS(Combined_Data!$M$2:$M$3001,"Mid-Senior level",Combined_Data!$AG$2:$AG$3001,"Likely Ghost") -> 77 | D6: =IFERROR(C6/B6*100,0) -> 13.298791 | E6: =IFERROR(AVERAGEIF(Combined_Data!$M$2:$M$3001,"Mid-Senior level",Combined_Data!$AF$2:$AF$3001),0) -> 39.651295
A7: Not Applicable | B7: =COUNTIF(Combined_Data!$M$2:$M$3001,"Not Applicable") -> 295 | C7: =COUNTIFS(Combined_Data!$M$2:$M$3001,"Not Applicable",Combined_Data!$AG$2:$AG$3001,"Likely Ghost") -> 0 | D7: =IFERROR(C7/B7*100,0) -> 0 | E7: =IFERROR(AVERAGEIF(Combined_Data!$M$2:$M$3001,"Not Applicable",Combined_Data!$AF$2:$AF$3001),0) -> 23.170847
A8: Associate | B8: =COUNTIF(Combined_Data!$M$2:$M$3001,"Associate") -> 69 | C8: =COUNTIFS(Combined_Data!$M$2:$M$3001,"Associate",Combined_Data!$AG$2:$AG$3001,"Likely Ghost") -> 0 | D8: =IFERROR(C8/B8*100,0) -> 0 | E8: =IFERROR(AVERAGEIF(Combined_Data!$M$2:$M$3001,"Associate",Combined_Data!$AF$2:$AF$3001),0) -> 24.662319
A9: Entry level | B9: =COUNTIF(Combined_Data!$M$2:$M$3001,"Entry level") -> 44 | C9: =COUNTIFS(Combined_Data!$M$2:$M$3001,"Entry level",Combined_Data!$AG$2:$AG$3001,"Likely Ghost") -> 0 | D9: =IFERROR(C9/B9*100,0) -> 0 | E9: =IFERROR(AVERAGEIF(Combined_Data!$M$2:$M$3001,"Entry level",Combined_Data!$AF$2:$AF$3001),0) -> 30.225
A10: Internship | B10: =COUNTIF(Combined_Data!$M$2:$M$3001,"Internship") -> 8 | C10: =COUNTIFS(Combined_Data!$M$2:$M$3001,"Internship",Combined_Data!$AG$2:$AG$3001,"Likely Ghost") -> 0 | D10: =IFERROR(C10/B10*100,0) -> 0 | E10: =IFERROR(AVERAGEIF(Combined_Data!$M$2:$M$3001,"Internship",Combined_Data!$AF$2:$AF$3001),0) -> 23.2375
A11: Director | B11: =COUNTIF(Combined_Data!$M$2:$M$3001,"Director") -> 4 | C11: =COUNTIFS(Combined_Data!$M$2:$M$3001,"Director",Combined_Data!$AG$2:$AG$3001,"Likely Ghost") -> 0 | D11: =IFERROR(C11/B11*100,0) -> 0 | E11: =IFERROR(AVERAGEIF(Combined_Data!$M$2:$M$3001,"Director",Combined_Data!$AF$2:$AF$3001),0) -> 21.45
A12: Executive | B12: =COUNTIF(Combined_Data!$M$2:$M$3001,"Executive") -> 1 | C12: =COUNTIFS(Combined_Data!$M$2:$M$3001,"Executive",Combined_Data!$AG$2:$AG$3001,"Likely Ghost") -> 0 | D12: =IFERROR(C12/B12*100,0) -> 0 | E12: =IFERROR(AVERAGEIF(Combined_Data!$M$2:$M$3001,"Executive",Combined_Data!$AF$2:$AF$3001),0) -> 42.9
A15: Contract Type | B15: Total Postings | C15: Likely Ghost | D15: Ghost Rate % | E15: Avg Ghost Score %
A16: Full-time | B16: =COUNTIF(Combined_Data!$L$2:$L$3001,"Full-time") -> 1609 | C16: =COUNTIFS(Combined_Data!$L$2:$L$3001,"Full-time",Combined_Data!$AG$2:$AG$3001,"Likely Ghost") -> 88 | D16: =IFERROR(C16/B16*100,0) -> 5.4692356 | E16: =IFERROR(AVERAGEIF(Combined_Data!$L$2:$L$3001,"Full-time",Combined_Data!$AF$2:$AF$3001),0) -> 28.603418
A17: Not Captured by Scraper | B17: =COUNTIF(Combined_Data!$L$2:$L$3001,"Not Captured by Scraper") -> 1335 | C17: =COUNTIFS(Combined_Data!$L$2:$L$3001,"Not Captured by Scraper",Combined_Data!$AG$2:$AG$3001,"Likely Ghost") -> 55 | D17: =IFERROR(C17/B17*100,0) -> 4.1198502 | E17: =IFERROR(AVERAGEIF(Combined_Data!$L$2:$L$3001,"Not Captured by Scraper",Combined_Data!$AF$2:$AF$3001),0) -> 23.80779
A18: Temporary | B18: =COUNTIF(Combined_Data!$L$2:$L$3001,"Temporary") -> 15 | C18: =COUNTIFS(Combined_Data!$L$2:$L$3001,"Temporary",Combined_Data!$AG$2:$AG$3001,"Likely Ghost") -> 1 | D18: =IFERROR(C18/B18*100,0) -> 6.6666667 | E18: =IFERROR(AVERAGEIF(Combined_Data!$L$2:$L$3001,"Temporary",Combined_Data!$AF$2:$AF$3001),0) -> 23.826667
A19: Contract | B19: =COUNTIF(Combined_Data!$L$2:$L$3001,"Contract") -> 14 | C19: =COUNTIFS(Combined_Data!$L$2:$L$3001,"Contract",Combined_Data!$AG$2:$AG$3001,"Likely Ghost") -> 0 | D19: =IFERROR(C19/B19*100,0) -> 0 | E19: =IFERROR(AVERAGEIF(Combined_Data!$L$2:$L$3001,"Contract",Combined_Data!$AF$2:$AF$3001),0) -> 20.428571
A20: Internship | B20: =COUNTIF(Combined_Data!$L$2:$L$3001,"Internship") -> 10 | C20: =COUNTIFS(Combined_Data!$L$2:$L$3001,"Internship",Combined_Data!$AG$2:$AG$3001,"Likely Ghost") -> 0 | D20: =IFERROR(C20/B20*100,0) -> 0 | E20: =IFERROR(AVERAGEIF(Combined_Data!$L$2:$L$3001,"Internship",Combined_Data!$AF$2:$AF$3001),0) -> 21.45
A21: Entry Level | B21: =COUNTIF(Combined_Data!$L$2:$L$3001,"Entry Level") -> 9 | C21: =COUNTIFS(Combined_Data!$L$2:$L$3001,"Entry Level",Combined_Data!$AG$2:$AG$3001,"Likely Ghost") -> 2 | D21: =IFERROR(C21/B21*100,0) -> 22.222222 | E21: =IFERROR(AVERAGEIF(Combined_Data!$L$2:$L$3001,"Entry Level",Combined_Data!$AF$2:$AF$3001),0) -> 28.577778
A22: Part-time | B22: =COUNTIF(Combined_Data!$L$2:$L$3001,"Part-time") -> 7 | C22: =COUNTIFS(Combined_Data!$L$2:$L$3001,"Part-time",Combined_Data!$AG$2:$AG$3001,"Likely Ghost") -> 0 | D22: =IFERROR(C22/B22*100,0) -> 0 | E22: =IFERROR(AVERAGEIF(Combined_Data!$L$2:$L$3001,"Part-time",Combined_Data!$AF$2:$AF$3001),0) -> 14.3
A23: Volunteer | B23: =COUNTIF(Combined_Data!$L$2:$L$3001,"Volunteer") -> 1 | C23: =COUNTIFS(Combined_Data!$L$2:$L$3001,"Volunteer",Combined_Data!$AG$2:$AG$3001,"Likely Ghost") -> 0 | D23: =IFERROR(C23/B23*100,0) -> 0 | E23: =IFERROR(AVERAGEIF(Combined_Data!$L$2:$L$3001,"Volunteer",Combined_Data!$AF$2:$AF$3001),0) -> 28.6

Sheet Salary_Analysis
A1: Salary Disclosure & Distribution Analysis
A2: Only 599 of 3,000 listings (~20%) had a comparable annual salary figure — most Indian job posts do not disclose pay. Figures below are based on that disclosed subset only.
A4: Portal | B4: Total Postings | C4: Salary Disclosed | D4: Disclosure Rate % | E4: Avg Est. Annual Salary (disclosed)
A5: LinkedIn | B5: =COUNTIF(Combined_Data!$B$2:$B$3001,"LinkedIn") -> 1000 | C5: =COUNTIFS(Combined_Data!$B$2:$B$3001,"LinkedIn",Combined_Data!$T$2:$T$3001,TRUE()) -> 0 | D5: =IFERROR(C5/B5*100,0) -> 0 | E5: =IFERROR(AVERAGEIFS(Combined_Data!$S$2:$S$3001,Combined_Data!$B$2:$B$3001,"LinkedIn",Combined_Data!$T$2:$T$3001,TRUE()),0) -> 0
A6: Indeed | B6: =COUNTIF(Combined_Data!$B$2:$B$3001,"Indeed") -> 1000 | C6: =COUNTIFS(Combined_Data!$B$2:$B$3001,"Indeed",Combined_Data!$T$2:$T$3001,TRUE()) -> 148 | D6: =IFERROR(C6/B6*100,0) -> 14.8 | E6: =IFERROR(AVERAGEIFS(Combined_Data!$S$2:$S$3001,Combined_Data!$B$2:$B$3001,"Indeed",Combined_Data!$T$2:$T$3001,TRUE()),0) -> 712321.28
A7: Glassdoor | B7: =COUNTIF(Combined_Data!$B$2:$B$3001,"Glassdoor") -> 1000 | C7: =COUNTIFS(Combined_Data!$B$2:$B$3001,"Glassdoor",Combined_Data!$T$2:$T$3001,TRUE()) -> 451 | D7: =IFERROR(C7/B7*100,0) -> 45.1 | E7: =IFERROR(AVERAGEIFS(Combined_Data!$S$2:$S$3001,Combined_Data!$B$2:$B$3001,"Glassdoor",Combined_Data!$T$2:$T$3001,TRUE()),0) -> 608706.69
A10: Role Bucket | B10: Total Postings | C10: Salary Disclosed | D10: Disclosure Rate % | E10: Avg Est. Annual Salary (disclosed)
A11: Software Engineer | B11: =COUNTIF(Combined_Data!$D$2:$D$3001,"Software Engineer") -> 1198 | C11: =COUNTIFS(Combined_Data!$D$2:$D$3001,"Software Engineer",Combined_Data!$T$2:$T$3001,TRUE()) -> 128 | D11: =IFERROR(C11/B11*100,0) -> 10.684474 | E11: =IFERROR(AVERAGEIFS(Combined_Data!$S$2:$S$3001,Combined_Data!$D$2:$D$3001,"Software Engineer",Combined_Data!$T$2:$T$3001,TRUE()),0) -> 582718.11
A12: Other | B12: =COUNTIF(Combined_Data!$D$2:$D$3001,"Other") -> 756 | C12: =COUNTIFS(Combined_Data!$D$2:$D$3001,"Other",Combined_Data!$T$2:$T$3001,TRUE()) -> 150 | D12: =IFERROR(C12/B12*100,0) -> 19.84127 | E12: =IFERROR(AVERAGEIFS(Combined_Data!$S$2:$S$3001,Combined_Data!$D$2:$D$3001,"Other",Combined_Data!$T$2:$T$3001,TRUE()),0) -> 613551.15
A13: Data Analyst | B13: =COUNTIF(Combined_Data!$D$2:$D$3001,"Data Analyst") -> 271 | C13: =COUNTIFS(Combined_Data!$D$2:$D$3001,"Data Analyst",Combined_Data!$T$2:$T$3001,TRUE()) -> 125 | D13: =IFERROR(C13/B13*100,0) -> 46.125461 | E13: =IFERROR(AVERAGEIFS(Combined_Data!$S$2:$S$3001,Combined_Data!$D$2:$D$3001,"Data Analyst",Combined_Data!$T$2:$T$3001,TRUE()),0) -> 563160.42
A14: ML Engineer | B14: =COUNTIF(Combined_Data!$D$2:$D$3001,"ML Engineer") -> 204 | C14: =COUNTIFS(Combined_Data!$D$2:$D$3001,"ML Engineer",Combined_Data!$T$2:$T$3001,TRUE()) -> 70 | D14: =IFERROR(C14/B14*100,0) -> 34.313725 | E14: =IFERROR(AVERAGEIFS(Combined_Data!$S$2:$S$3001,Combined_Data!$D$2:$D$3001,"ML Engineer",Combined_Data!$T$2:$T$3001,TRUE()),0) -> 638042.2
A15: Frontend Engineer | B15: =COUNTIF(Combined_Data!$D$2:$D$3001,"Frontend Engineer") -> 154 | C15: =COUNTIFS(Combined_Data!$D$2:$D$3001,"Frontend Engineer",Combined_Data!$T$2:$T$3001,TRUE()) -> 70 | D15: =IFERROR(C15/B15*100,0) -> 45.454545 | E15: =IFERROR(AVERAGEIFS(Combined_Data!$S$2:$S$3001,Combined_Data!$D$2:$D$3001,"Frontend Engineer",Combined_Data!$T$2:$T$3001,TRUE()),0) -> 633805.33
A16: Full Stack Engineer | B16: =COUNTIF(Combined_Data!$D$2:$D$3001,"Full Stack Engineer") -> 149 | C16: =COUNTIFS(Combined_Data!$D$2:$D$3001,"Full Stack Engineer",Combined_Data!$T$2:$T$3001,TRUE()) -> 15 | D16: =IFERROR(C16/B16*100,0) -> 10.067114 | E16: =IFERROR(AVERAGEIFS(Combined_Data!$S$2:$S$3001,Combined_Data!$D$2:$D$3001,"Full Stack Engineer",Combined_Data!$T$2:$T$3001,TRUE()),0) -> 1387600.2
A17: Backend Engineer | B17: =COUNTIF(Combined_Data!$D$2:$D$3001,"Backend Engineer") -> 143 | C17: =COUNTIFS(Combined_Data!$D$2:$D$3001,"Backend Engineer",Combined_Data!$T$2:$T$3001,TRUE()) -> 12 | D17: =IFERROR(C17/B17*100,0) -> 8.3916084 | E17: =IFERROR(AVERAGEIFS(Combined_Data!$S$2:$S$3001,Combined_Data!$D$2:$D$3001,"Backend Engineer",Combined_Data!$T$2:$T$3001,TRUE()),0) -> 929815.25
A18: Data Scientist | B18: =COUNTIF(Combined_Data!$D$2:$D$3001,"Data Scientist") -> 45 | C18: =COUNTIFS(Combined_Data!$D$2:$D$3001,"Data Scientist",Combined_Data!$T$2:$T$3001,TRUE()) -> 13 | D18: =IFERROR(C18/B18*100,0) -> 28.888889 | E18: =IFERROR(AVERAGEIFS(Combined_Data!$S$2:$S$3001,Combined_Data!$D$2:$D$3001,"Data Scientist",Combined_Data!$T$2:$T$3001,TRUE()),0) -> 596326.92
A19: Data Engineer | B19: =COUNTIF(Combined_Data!$D$2:$D$3001,"Data Engineer") -> 36 | C19: =COUNTIFS(Combined_Data!$D$2:$D$3001,"Data Engineer",Combined_Data!$T$2:$T$3001,TRUE()) -> 10 | D19: =IFERROR(C19/B19*100,0) -> 27.777778 | E19: =IFERROR(AVERAGEIFS(Combined_Data!$S$2:$S$3001,Combined_Data!$D$2:$D$3001,"Data Engineer",Combined_Data!$T$2:$T$3001,TRUE()),0) -> 906050
A20: DevOps Engineer | B20: =COUNTIF(Combined_Data!$D$2:$D$3001,"DevOps Engineer") -> 24 | C20: =COUNTIFS(Combined_Data!$D$2:$D$3001,"DevOps Engineer",Combined_Data!$T$2:$T$3001,TRUE()) -> 3 | D20: =IFERROR(C20/B20*100,0) -> 12.5 | E20: =IFERROR(AVERAGEIFS(Combined_Data!$S$2:$S$3001,Combined_Data!$D$2:$D$3001,"DevOps Engineer",Combined_Data!$T$2:$T$3001,TRUE()),0) -> 787010.67
A21: QA/Test Engineer | B21: =COUNTIF(Combined_Data!$D$2:$D$3001,"QA/Test Engineer") -> 14 | C21: =COUNTIFS(Combined_Data!$D$2:$D$3001,"QA/Test Engineer",Combined_Data!$T$2:$T$3001,TRUE()) -> 3 | D21: =IFERROR(C21/B21*100,0) -> 21.428571 | E21: =IFERROR(AVERAGEIFS(Combined_Data!$S$2:$S$3001,Combined_Data!$D$2:$D$3001,"QA/Test Engineer",Combined_Data!$T$2:$T$3001,TRUE()),0) -> 919910
A22: Product Manager | B22: =COUNTIF(Combined_Data!$D$2:$D$3001,"Product Manager") -> 6 | C22: =COUNTIFS(Combined_Data!$D$2:$D$3001,"Product Manager",Combined_Data!$T$2:$T$3001,TRUE()) -> 0 | D22: =IFERROR(C22/B22*100,0) -> 0 | E22: =IFERROR(AVERAGEIFS(Combined_Data!$S$2:$S$3001,Combined_Data!$D$2:$D$3001,"Product Manager",Combined_Data!$T$2:$T$3001,TRUE()),0) -> 0
A25: Salary Bucket (Annual, INR) | B25: Count | C25: % of Disclosed
A26: Under ₹6L | B26: =COUNTIFS(Combined_Data!$T$2:$T$3001,TRUE(),Combined_Data!$S$2:$S$3001,">="&0,Combined_Data!$S$2:$S$3001,"<"&600000) -> 358 | C26: =IFERROR(B26/COUNTIF(Combined_Data!$T$2:$T$3001,TRUE())*100,0) -> 59.766277
A27: ₹6L – 12L | B27: =COUNTIFS(Combined_Data!$T$2:$T$3001,TRUE(),Combined_Data!$S$2:$S$3001,">="&600000,Combined_Data!$S$2:$S$3001,"<"&1200000) -> 205 | C27: =IFERROR(B27/COUNTIF(Combined_Data!$T$2:$T$3001,TRUE())*100,0) -> 34.223706
A28: ₹12L – 20L | B28: =COUNTIFS(Combined_Data!$T$2:$T$3001,TRUE(),Combined_Data!$S$2:$S$3001,">="&1200000,Combined_Data!$S$2:$S$3001,"<"&2000000) -> 23 | C28: =IFERROR(B28/COUNTIF(Combined_Data!$T$2:$T$3001,TRUE())*100,0) -> 3.8397329
A29: ₹20L – 35L | B29: =COUNTIFS(Combined_Data!$T$2:$T$3001,TRUE(),Combined_Data!$S$2:$S$3001,">="&2000000,Combined_Data!$S$2:$S$3001,"<"&3500000) -> 8 | C29: =IFERROR(B29/COUNTIF(Combined_Data!$T$2:$T$3001,TRUE())*100,0) -> 1.3355593
A30: ₹35L+ | B30: =COUNTIFS(Combined_Data!$T$2:$T$3001,TRUE(),Combined_Data!$S$2:$S$3001,">="&3500000,Combined_Data!$S$2:$S$3001,"<"&999999999) -> 5 | C30: =IFERROR(B30/COUNTIF(Combined_Data!$T$2:$T$3001,TRUE())*100,0) -> 0.83472454
A32: Note: salary buckets and averages only include listings flagged Salary Comparable=TRUE (parsed, annualized, currency-normalized figures) — raw/unparseable salary text is excluded rather than guessed at.

Sheet Combined_Data
A1: Job ID | B1: Portal | C1: Job Title | D1: Role Bucket | E1: Company Name | F1: Company Disclosed? | G1: City | H1: State | I1: Posted Date | J1: Scraped Date | K1: Days Live | L1: Contract Type | M1: Experience Level | N1: Salary Disclosed? | O1: Salary Min | P1: Salary Max | Q1: Currency | R1: Salary Period (raw) | S1: Est. Annual Salary | T1: Salary Comparable? | U1: Salary Outlier Flag | V1: Description Word Count | W1: Description Preview | X1: Company Posting Count (this portal) | Y1: Posting Velocity /week | Z1: Flag: No Company | AA1: Flag: No Salary | AB1: Flag: Short Desc | AC1: Flag: Stale Listing | AD1: Flag: High Velocity | AE1: Ghost Score (0-7) | AF1: Ghost Score % | AG1: GHOST LABEL | AH1: Source URL | AI1: Explorer Match Flag
A2: LI_4410905842 | B2: LinkedIn | C2: Software Engineer | D2: Software Engineer | E2: Sphera | F2: =TRUE() -> TRUE | G2: Bengaluru | H2: Karnataka | I2: 46190 | J2: 46210 | K2: 20 | L2: Full-time | M2: Not Applicable | N2: =FALSE() -> FALSE | Q2: N/A | R2: Not provided by LinkedIn scraper | T2: =FALSE() -> FALSE | U2: =FALSE() -> FALSE | V2: 563 | W2: Sphera is a leading global provider of enterprise software and services that enables companies to manage and optimize their environmental, health, safety and sustainability. Our mission is to create a safer, more sustainable and productive world. Sphera is a portfolio company of... | X2: 1 | Y2: 0.01 | Z2: =FALSE() -> FALSE | AA2: =TRUE() -> TRUE | AB2: =FALSE() -> FALSE | AC2: =TRUE() -> TRUE | AD2: =FALSE() -> FALSE | AE2: 2 | AF2: 28.6 | AG2: Uncertain | AH2: https://in.linkedin.com/jobs/view/software-engineer-at-sphera-4410905842?trk=public_jobs_topcard-title | AI2: =IF(AND(OR(Company_Explorer!$B$5="All Companies",$E2=Company_Explorer!$B$5),OR(Company_Explorer!$B$6="All Platforms",$B2=Company_Explorer!$B$6),OR(Company_Explorer!$B$7="All Roles",$D2=Company_Explorer!$B$7),OR(Company_Explorer!$B$8="All Ghost Labels",$AG2=Company_Explorer!$B$8)),1,0) -> 0
A3: LI_4416642506 | B3: LinkedIn | C3: Software Engineer I | D3: Software Engineer | E3: CME Group | F3: =TRUE() -> TRUE | G3: Bengaluru | H3: Karnataka | I3: 46204 | J3: 46210 | K3: 6 | L3: Full-time | M3: Not Applicable | N3: =FALSE() -> FALSE | Q3: N/A | R3: Not provided by LinkedIn scraper | T3: =FALSE() -> FALSE | U3: =FALSE() -> FALSE | V3: 541 | W3: Responsibilities Application Development: Design, develop, and maintain custom applications, add-ons, scripts, and extensions that integrate with Google Workspace tools to address specific business needs. AppSheet and Cloud Development: Lead the design, development, and deployme... | X3: 1 | Y3: 0.01 | Z3: =FALSE() -> FALSE | AA3: =TRUE() -> TRUE | AB3: =FALSE() -> FALSE | AC3: =FALSE() -> FALSE | AD3: =FALSE() -> FALSE | AE3: 1 | AF3: 14.3 | AG3: Likely Genuine | AH3: https://in.linkedin.com/jobs/view/software-engineer-i-at-cme-group-4416642506?trk=public_jobs_topcard-title | AI3: =IF(AND(OR(Company_Explorer!$B$5="All Companies",$E3=Company_Explorer!$B$5),OR(Company_Explorer!$B$6="All Platforms",$B3=Company_Explorer!$B$6),OR(Company_Explorer!$B$7="All Roles",$D3=Company_Explorer!$B$7),OR(Company_Explorer!$B$8="All Ghost Labels",$AG3=Company_Explorer!$B$8)),1,0) -> 0
A4: LI_4401614127 | B4: LinkedIn | C4: Software Engineer III - Java | D4: Software Engineer | E4: Walmart Global Tech India | F4: =TRUE() -> TRUE | G4: Bengaluru | H4: Karnataka | I4: 46197 | J4: 46210 | K4: 13 | L4: Full-time | M4: Not Applicable | N4: =FALSE() -> FALSE | Q4: N/A | R4: Not provided by LinkedIn scraper | T4: =FALSE() -> FALSE | U4: =FALSE() -> FALSE | V4: 642 | W4: About Team: Our team collaborates with Massmart Product team to understand existing issues in Business and develops scalable tech solutions for them. Massmart is a Walmart market existing in South Africa (SA) with multiples banners like Makro, Game, Builders, with around 300 st... | X4: 9 | Y4: 0.06 | Z4: =FALSE() -> FALSE | AA4: =TRUE() -> TRUE | AB4: =FALSE() -> FALSE | AC4: =FALSE() -> FALSE | AD4: =FALSE() -> FALSE | AE4: 1 | AF4: 14.3 | AG4: Likely Genuine | AH4: https://in.linkedin.com/jobs/view/software-engineer-iii-java-at-walmart-global-tech-india-4401614127?trk=public_jobs_topcard-title | AI4: =IF(AND(OR(Company_Explorer!$B$5="All Companies",$E4=Company_Explorer!$B$5),OR(Company_Explorer!$B$6="All Platforms",$B4=Company_Explorer!$B$6),OR(Company_Explorer!$B$7="All Roles",$D4=Company_Explorer!$B$7),OR(Company_Explorer!$B$8="All Ghost Labels",$AG4=Company_Explorer!$B$8)),1,0) -> 0
A5: LI_4404671522 | B5: LinkedIn | C5: Software Engineer (Wifi/ Kernel/ Embedded) | D5: Software Engineer | E5: Arista Networks | F5: =TRUE() -> TRUE | G5: Pune District | H5: Maharashtra | I5: 46196 | J5: 46210 | K5: 14 | L5: Full-time | M5: Mid-Senior level | N5: =FALSE() -> FALSE | Q5: N/A | R5: Not provided by LinkedIn scraper | T5: =FALSE() -> FALSE | U5: =FALSE() -> FALSE | V5: 665 | W5: Arista Networks is an industry leader in data-driven, client-to-cloud networking for large data center, campus and routing environments. Arista is a well-established and profitable company with over $5 billion in revenue. Arista’s award-winning platforms, ranging in Ethernet spee... | X5: 2 | Y5: 0.01 | Z5: =FALSE() -> FALSE | AA5: =TRUE() -> TRUE | AB5: =FALSE() -> FALSE | AC5: =FALSE() -> FALSE | AD5: =FALSE() -> FALSE | AE5: 1 | AF5: 14.3 | AG5: Likely Genuine | AH5: https://in.linkedin.com/jobs/view/software-engineer-wifi-kernel-embedded-at-arista-networks-4404671522?trk=public_jobs_topcard-title | AI5: =IF(AND(OR(Company_Explorer!$B$5="All Companies",$E5=Company_Explorer!$B$5),OR(Company_Explorer!$B$6="All Platforms",$B5=Company_Explorer!$B$6),OR(Company_Explorer!$B$7="All Roles",$D5=Company_Explorer!$B$7),OR(Company_Explorer!$B$8="All Ghost Labels",$AG5=Company_Explorer!$B$8)),1,0) -> 0
A6: LI_4430996476 | B6: LinkedIn | C6: Custom Software Engineer | D6: Software Engineer | E6: Accenture in India | F6: =TRUE() -> TRUE | G6: Bengaluru | H6: Karnataka | I6: 46198 | J6: 46210 | K6: 12 | L6: Full-time | M6: Mid-Senior level | N6: =FALSE() -> FALSE | Q6: N/A | R6: Not provided by LinkedIn scraper | T6: =FALSE() -> FALSE | U6: =FALSE() -> FALSE | V6: 320 | W6: Project Role : Custom Software Engineer Project Role Description : Develop custom software solutions to design, code, and enhance components across systems or applications. Use modern frameworks and agile practices to deliver scalable, high-performing solutions tailored to speci... | X6: 429 | Y6: 2.66 | Z6: =FALSE() -> FALSE | AA6: =TRUE() -> TRUE | AB6: =FALSE() -> FALSE | AC6: =FALSE() -> FALSE | AD6: =TRUE() -> TRUE | AE6: 3 | AF6: 42.9 | AG6: Uncertain | AH6: https://in.linkedin.com/jobs/view/custom-software-engineer-at-accenture-in-india-4430996476?trk=public_jobs_topcard-title | AI6: =IF(AND(OR(Company_Explorer!$B$5="All Companies",$E6=Company_Explorer!$B$5),OR(Company_Explorer!$B$6="All Platforms",$B6=Company_Explorer!$B$6),OR(Company_Explorer!$B$7="All Roles",$D6=Company_Explorer!$B$7),OR(Company_Explorer!$B$8="All Ghost Labels",$AG6=Company_Explorer!$B$8)),1,0) -> 0
A7: LI_4436441724 | B7: LinkedIn | C7: Custom Software Engineer | D7: Software Engineer | E7: Accenture in India | F7: =TRUE() -> TRUE | G7: Kolkata | H7: West Bengal | I7: 46206 | J7: 46210 | K7: 4 | L7: Full-time | M7: Entry level | N7: =FALSE() -> FALSE | Q7: N/A | R7: Not provided by LinkedIn scraper | T7: =FALSE() -> FALSE | U7: =FALSE() -> FALSE | V7: 326 | W7: Project Role : Custom Software Engineer Project Role Description : Design, build and configure applications to meet business process and application requirements. Must have skills : Workday Core Integrations Good to have skills : NA Minimum 2 Year(s) Of Experience Is Required... | X7: 429 | Y7: 2.66 | Z7: =FALSE() -> FALSE | AA7: =TRUE() -> TRUE | AB7: =FALSE() -> FALSE | AC7: =FALSE() -> FALSE | AD7: =TRUE() -> TRUE | AE7: 3 | AF7: 42.9 | AG7: Uncertain | AH7: https://in.linkedin.com/jobs/view/custom-software-engineer-at-accenture-in-india-4436441724?trk=public_jobs_topcard-title | AI7: =IF(AND(OR(Company_Explorer!$B$5="All Companies",$E7=Company_Explorer!$B$5),OR(Company_Explorer!$B$6="All Platforms",$B7=Company_Explorer!$B$6),OR(Company_Explorer!$B$7="All Roles",$D7=Company_Explorer!$B$7),OR(Company_Explorer!$B$8="All Ghost Labels",$AG7=Company_Explorer!$B$8)),1,0) -> 0
A8: LI_4425848073 | B8: LinkedIn | C8: Software Engineer - Front End | D8: Frontend Engineer | E8: SmartBear | F8: =TRUE() -> TRUE | G8: Ahmedabad | H8: Gujarat | I8: 46204 | J8: 46210 | K8: 6 | L8: Full-time | M8: Not Applicable | N8: =FALSE() -> FALSE | Q8: N/A | R8: Not provided by LinkedIn scraper | T8: =FALSE() -> FALSE | U8: =FALSE() -> FALSE | V8: 1034 | W8: SmartBear delivers application integrity for modern tech stacks, ensuring continuous, measurable assurance that software just works as intended with governance to operate at AI speed and scale. SmartBear offers deep test automation, API lifecycle management, and observability cap... | X8: 2 | Y8: 0.01 | Z8: =FALSE() -> FALSE | AA8: =TRUE() -> TRUE | AB8: =FALSE() -> FALSE | AC8: =FALSE() -> FALSE | AD8: =FALSE() -> FALSE | AE8: 1 | AF8: 14.3 | AG8: Likely Genuine | AH8: https://in.linkedin.com/jobs/view/software-engineer-front-end-at-smartbear-4425848073?trk=public_jobs_topcard-title | AI8: =IF(AND(OR(Company_Explorer!$B$5="All Companies",$E8=Company_Explorer!$B$5),OR(Company_Explorer!$B$6="All Platforms",$B8=Company_Explorer!$B$6),OR(Company_Explorer!$B$7="All Roles",$D8=Company_Explorer!$B$7),OR(Company_Explorer!$B$8="All Ghost Labels",$AG8=Company_Explorer!$B$8)),1,0) -> 0
A9: LI_4425825970 | B9: LinkedIn | C9: Software Engineer - Front End | D9: Frontend Engineer | E9: SmartBear | F9: =TRUE() -> TRUE | G9: Ahmedabad | H9: Gujarat | I9: 46204 | J9: 46210 | K9: 6 | L9: Full-time | M9: Not Applicable | N9: =FALSE() -> FALSE | Q9: N/A | R9: Not provided by LinkedIn scraper | T9: =FALSE() -> FALSE | U9: =FALSE() -> FALSE | V9: 1034 | W9: SmartBear delivers application integrity for modern tech stacks, ensuring continuous, measurable assurance that software just works as intended with governance to operate at AI speed and scale. SmartBear offers deep test automation, API lifecycle management, and observability cap... | X9: 2 | Y9: 0.01 | Z9: =FALSE() -> FALSE | AA9: =TRUE() -> TRUE | AB9: =FALSE() -> FALSE | AC9: =FALSE() -> FALSE | AD9: =FALSE() -> FALSE | AE9: 1 | AF9: 14.3 | AG9: Likely Genuine | AH9: https://in.linkedin.com/jobs/view/software-engineer-front-end-at-smartbear-4425825970?trk=public_jobs_topcard-title | AI9: =IF(AND(OR(Company_Explorer!$B$5="All Companies",$E9=Company_Explorer!$B$5),OR(Company_Explorer!$B$6="All Platforms",$B9=Company_Explorer!$B$6),OR(Company_Explorer!$B$7="All Roles",$D9=Company_Explorer!$B$7),OR(Company_Explorer!$B$8="All Ghost Labels",$AG9=Company_Explorer!$B$8)),1,0) -> 0
A10: LI_4430763577 | B10: LinkedIn | C10: Custom Software Engineer | D10: Software Engineer | E10: Accenture in India | F10: =TRUE() -> TRUE | G10: Chennai | H10: Tamil Nadu | I10: 46198 | J10: 46210 | K10: 12 | L10: Full-time | M10: Mid-Senior level | N10: =FALSE() -> FALSE | Q10: N/A | R10: Not provided by LinkedIn scraper | T10: =FALSE() -> FALSE | U10: =FALSE() -> FALSE | V10: 306 | W10: Project Role : Custom Software Engineer Project Role Description : Develop custom software solutions to design, code, and enhance components across systems or applications. Use modern frameworks and agile practices to deliver scalable, high-performing solutions tailored to speci... | X10: 429 | Y10: 2.66 | Z10: =FALSE() -> FALSE | AA10: =TRUE() -> TRUE | AB10: =FALSE() -> FALSE | AC10: =FALSE() -> FALSE | AD10: =TRUE() -> TRUE | AE10: 3 | AF10: 42.9 | AG10: Uncertain | AH10: https://in.linkedin.com/jobs/view/custom-software-engineer-at-accenture-in-india-4430763577?trk=public_jobs_topcard-title | AI10: =IF(AND(OR(Company_Explorer!$B$5="All Companies",$E10=Company_Explorer!$B$5),OR(Company_Explorer!$B$6="All Platforms",$B10=Company_Explorer!$B$6),OR(Company_Explorer!$B$7="All Roles",$D10=Company_Explorer!$B$7),OR(Company_Explorer!$B$8="All Ghost Labels",$AG10=Company_Explorer!$B$8)),1,0) -> 0
A11: LI_4390860957 | B11: LinkedIn | C11: Custom Software Engineer | D11: Software Engineer | E11: Accenture in India | F11: =TRUE() -> TRUE | G11: Bengaluru | H11: Karnataka | I11: 46198 | J11: 46210 | K11: 12 | L11: Full-time | M11: Mid-Senior level | N11: =FALSE() -> FALSE | Q11: N/A | R11: Not provided by LinkedIn scraper | T11: =FALSE() -> FALSE | U11: =FALSE() -> FALSE | V11: 319 | W11: Project Role : Custom Software Engineer Project Role Description : Develop custom software solutions to design, code, and enhance components across systems or applications. Use modern frameworks and agile practices to deliver scalable, high-performing solutions tailored to speci... | X11: 429 | Y11: 2.66 | Z11: =FALSE() -> FALSE | AA11: =TRUE() -> TRUE | AB11: =FALSE() -> FALSE | AC11: =FALSE() -> FALSE | AD11: =TRUE() -> TRUE | AE11: 3 | AF11: 42.9 | AG11: Uncertain | AH11: https://in.linkedin.com/jobs/view/custom-software-engineer-at-accenture-in-india-4390860957?trk=public_jobs_topcard-title | AI11: =IF(AND(OR(Company_Explorer!$B$5="All Companies",$E11=Company_Explorer!$B$5),OR(Company_Explorer!$B$6="All Platforms",$B11=Company_Explorer!$B$6),OR(Company_Explorer!$B$7="All Roles",$D11=Company_Explorer!$B$7),OR(Company_Explorer!$B$8="All Ghost Labels",$AG11=Company_Explorer!$B$8)),1,0) -> 0
A12: LI_4434047893 | B12: LinkedIn | C12: Custom Software Engineer | D12: Software Engineer | E12: Accenture in India | F12: =TRUE() -> TRUE | G12: Chennai | H12: Tamil Nadu | I12: 46200 | J12: 46210 | K12: 10 | L12: Full-time | M12: Mid-Senior level | N12: =FALSE() -> FALSE | Q12: N/A | R12: Not provided by LinkedIn scraper | T12: =FALSE() -> FALSE | U12: =FALSE() -> FALSE | V12: 309 | W12: Project Role : Custom Software Engineer Project Role Description : Develop custom software solutions to design, code, and enhance components across systems or applications. Use modern frameworks and agile practices to deliver scalable, high-performing solutions tailored to speci... | X12: 429 | Y12: 2.66 | Z12: =FALSE() -> FALSE | AA12: =TRUE() -> TRUE | AB12: =FALSE() -> FALSE | AC12: =FALSE() -> FALSE | AD12: =TRUE() -> TRUE | AE12: 3 | AF12: 42.9 | AG12: Uncertain | AH12: https://in.linkedin.com/jobs/view/custom-software-engineer-at-accenture-in-india-4434047893?trk=public_jobs_topcard-title | AI12: =IF(AND(OR(Company_Explorer!$B$5="All Companies",$E12=Company_Explorer!$B$5),OR(Company_Explorer!$B$6="All Platforms",$B12=Company_Explorer!$B$6),OR(Company_Explorer!$B$7="All Roles",$D12=Company_Explorer!$B$7),OR(Company_Explorer!$B$8="All Ghost Labels",$AG12=Company_Explorer!$B$8)),1,0) -> 0
A13: LI_4390866505 | B13: LinkedIn | C13: Custom Software Engineer | D13: Software Engineer | E13: Accenture in India | F13: =TRUE() -> TRUE | G13: Bengaluru | H13: Karnataka | I13: 46198 | J13: 46210 | K13: 12 | L13: Full-time | M13: Mid-Senior level | N13: =FALSE() -> FALSE | Q13: N/A | R13: Not provided by LinkedIn scraper | T13: =FALSE() -> FALSE | U13: =FALSE() -> FALSE | V13: 319 | W13: Project Role : Custom Software Engineer Project Role Description : Develop custom software solutions to design, code, and enhance components across systems or applications. Use modern frameworks and agile practices to deliver scalable, high-performing solutions tailored to speci... | X13: 429 | Y13: 2.66 | Z13: =FALSE() -> FALSE | AA13: =TRUE() -> TRUE | AB13: =FALSE() -> FALSE | AC13: =FALSE() -> FALSE | AD13: =TRUE() -> TRUE | AE13: 3 | AF13: 42.9 | AG13: Uncertain | AH13: https://in.linkedin.com/jobs/view/custom-software-engineer-at-accenture-in-india-4390866505?trk=public_jobs_topcard-title | AI13: =IF(AND(OR(Company_Explorer!$B$5="All Companies",$E13=Company_Explorer!$B$5),OR(Company_Explorer!$B$6="All Platforms",$B13=Company_Explorer!$B$6),OR(Company_Explorer!$B$7="All Roles",$D13=Company_Explorer!$B$7),OR(Company_Explorer!$B$8="All Ghost Labels",$AG13=Company_Explorer!$B$8)),1,0) -> 0
A14: LI_4370558206 | B14: LinkedIn | C14: Custom Software Engineer | D14: Software Engineer | E14: Accenture in India | F14: =TRUE() -> TRUE | G14: Bengaluru | H14: Karnataka | I14: 46198 | J14: 46210 | K14: 12 | L14: Full-time | M14: Mid-Senior level | N14: =FALSE() -> FALSE | Q14: N/A | R14: Not provided by LinkedIn scraper | T14: =FALSE() -> FALSE | U14: =FALSE() -> FALSE | V14: 271 | W14: Project Role : Custom Software Engineer Project Role Description : Design, build and configure applications to meet business process and application requirements. Must have skills : Python (Programming Language) Good to have skills : AI, ML, Langchain, Langraph, J Minimum 3 Y... | X14: 429 | Y14: 2.66 | Z14: =FALSE() -> FALSE | AA14: =TRUE() -> TRUE | AB14: =TRUE() -> TRUE | AC14: =FALSE() -> FALSE | AD14: =TRUE() -> TRUE | AE14: 4 | AF14: 57.1 | AG14: Likely Ghost | AH14: https://in.linkedin.com/jobs/view/custom-software-engineer-at-accenture-in-india-4370558206?trk=public_jobs_topcard-title | AI14: =IF(AND(OR(Company_Explorer!$B$5="All Companies",$E14=Company_Explorer!$B$5),OR(Company_Explorer!$B$6="All Platforms",$B14=Company_Explorer!$B$6),OR(Company_Explorer!$B$7="All Roles",$D14=Company_Explorer!$B$7),OR(Company_Explorer!$B$8="All Ghost Labels",$AG14=Company_Explorer!$B$8)),1,0) -> 0
A15: LI_4425982957 | B15: LinkedIn | C15: Software Engineer | D15: Software Engineer | E15: Silicon Patterns | F15: =TRUE() -> TRUE | G15: Bengaluru | H15: Karnataka | I15: 46182 | J15: 46210 | K15: 28 | L15: Full-time | M15: Associate | N15: =FALSE() -> FALSE | Q15: N/A | R15: Not provided by LinkedIn scraper | T15: =FALSE() -> FALSE | U15: =FALSE() -> FALSE | V15: 108 | W15: Job Description: EXP; 3 to 5 years Location:- Bangalore 1)BMC & RM Firmware Development Engineer Design, develop, and validate BMC (Open BMC-based) and RM (Remote Management) firmware 2)Specialist in C, strong in C++ or Python 3)Highly Proficient in developing firmware based on... | X15: 1 | Y15: 0.01 | Z15: =FALSE() -> FALSE | AA15: =TRUE() -> TRUE | AB15: =TRUE() -> TRUE | AC15: =TRUE() -> TRUE | AD15: =FALSE() -> FALSE | AE15: 3 | AF15: 42.9 | AG15: Uncertain | AH15: https://in.linkedin.com/jobs/view/software-engineer-at-silicon-patterns-4425982957?trk=public_jobs_topcard-title | AI15: =IF(AND(OR(Company_Explorer!$B$5="All Companies",$E15=Company_Explorer!$B$5),OR(Company_Explorer!$B$6="All Platforms",$B15=Company_Explorer!$B$6),OR(Company_Explorer!$B$7="All Roles",$D15=Company_Explorer!$B$7),OR(Company_Explorer!$B$8="All Ghost Labels",$AG15=Company_Explorer!$B$8)),1,0) -> 0
A16: LI_4423678095 | B16: LinkedIn | C16: Software Engineer - Java | D16: Software Engineer | E16: EPAM Systems | F16: =TRUE() -> TRUE | G16: Hyderabad | H16: Telangana | I16: 46184 | J16: 46210 | K16: 26 | L16: Full-time | M16: Associate | N16: =FALSE() -> FALSE | Q16: N/A | R16: Not provided by LinkedIn scraper | T16: =FALSE() -> FALSE | U16: =FALSE() -> FALSE | V16: 178 | W16: We are seeking a Software Engineer – Java with GCP to join our team and contribute to building robust, scalable applications. In this role, you will leverage your strong Java expertise and cloud knowledge to design and develop high-quality solutions within an Agile environment. R... | X16: 1 | Y16: 0.01 | Z16: =FALSE() -> FALSE | AA16: =TRUE() -> TRUE | AB16: =TRUE() -> TRUE | AC16: =TRUE() -> TRUE | AD16: =FALSE() -> FALSE | AE16: 3 | AF16: 42.9 | AG16: Uncertain | AH16: https://in.linkedin.com/jobs/view/software-engineer-java-at-epam-systems-4423678095?trk=public_jobs_topcard-title | AI16: =IF(AND(OR(Company_Explorer!$B$5="All Companies",$E16=Company_Explorer!$B$5),OR(Company_Explorer!$B$6="All Platforms",$B16=Company_Explorer!$B$6),OR(Company_Explorer!$B$7="All Roles",$D16=Company_Explorer!$B$7),OR(Company_Explorer!$B$8="All Ghost Labels",$AG16=Company_Explorer!$B$8)),1,0) -> 0
A17: LI_4366363763 | B17: LinkedIn | C17: Custom Software Engineer | D17: Software Engineer | E17: Accenture in India | F17: =TRUE() -> TRUE | G17: Coimbatore | H17: Tamil Nadu | I17: 46198 | J17: 46210 | K17: 12 | L17: Full-time | M17: Mid-Senior level | N17: =FALSE() -> FALSE | Q17: N/A | R17: Not provided by LinkedIn scraper | T17: =FALSE() -> FALSE | U17: =FALSE() -> FALSE | V17: 279 | W17: Project Role : Custom Software Engineer Project Role Description : Develop custom software solutions to design, code, and enhance components across systems or applications. Use modern frameworks and agile practices to deliver scalable, high-performing solutions tailored to speci... | X17: 429 | Y17: 2.66 | Z17: =FALSE() -> FALSE | AA17: =TRUE() -> TRUE | AB17: =FALSE() -> FALSE | AC17: =FALSE() -> FALSE | AD17: =TRUE() -> TRUE | AE17: 3 | AF17: 42.9 | AG17: Uncertain | AH17: https://in.linkedin.com/jobs/view/custom-software-engineer-at-accenture-in-india-4366363763?trk=public_jobs_topcard-title | AI17: =IF(AND(OR(Company_Explorer!$B$5="All Companies",$E17=Company_Explorer!$B$5),OR(Company_Explorer!$B$6="All Platforms",$B17=Company_Explorer!$B$6),OR(Company_Explorer!$B$7="All Roles",$D17=Company_Explorer!$B$7),OR(Company_Explorer!$B$8="All Ghost Labels",$AG17=Company_Explorer!$B$8)),1,0) -> 0
A18: LI_4432350778 | B18: LinkedIn | C18: Fresher &#8211; Software Engineer | Gurugram | D18: Software Engineer | E18: DigitalXNode | F18: =TRUE() -> TRUE | G18: Gurugram | H18: Haryana | I18: 46204 | J18: 46210 | K18: 6 | L18: Full-time | M18: Not Applicable | N18: =FALSE() -> FALSE | Q18: N/A | R18: Not provided by LinkedIn scraper | T18: =FALSE() -> FALSE | U18: =FALSE() -> FALSE | V18: 490 | W18: We are looking for enthusiastic and highly motivated Fresher Software Engineers who are eager to build a successful career in software development. This opportunity is ideal for recent graduates with a strong understanding of programming fundamentals, object-oriented concepts, an... | X18: 1 | Y18: 0.01 | Z18: =FALSE() -> FALSE | AA18: =TRUE() -> TRUE | AB18: =FALSE() -> FALSE | AC18: =FALSE() -> FALSE | AD18: =FALSE() -> FALSE | AE18: 1 | AF18: 14.3 | AG18: Likely Genuine | AH18: https://in.linkedin.com/jobs/view/fresher-%238211-software-engineer-gurugram-at-digitalxnode-4432350778?trk=public_jobs_topcard-title | AI18: =IF(AND(OR(Company_Explorer!$B$5="All Companies",$E18=Company_Explorer!$B$5),OR(Company_Explorer!$B$6="All Platforms",$B18=Company_Explorer!$B$6),OR(Company_Explorer!$B$7="All Roles",$D18=Company_Explorer!$B$7),OR(Company_Explorer!$B$8="All Ghost Labels",$AG18=Company_Explorer!$B$8)),1,0) -> 0
A19: LI_4391709172 | B19: LinkedIn | C19: Web Developer | D19: Software Engineer | E19: Accenture in India | F19: =TRUE() -> TRUE | G19: Hyderabad | H19: Telangana | I19: 46194 | J19: 46210 | K19: 16 | L19: Full-time | M19: Mid-Senior level | N19: =FALSE() -> FALSE | Q19: N/A | R19: Not provided by LinkedIn scraper | T19: =FALSE() -> FALSE | U19: =FALSE() -> FALSE | V19: 268 | W19: Project Role : Web Developer Project Role Description : Design, build and test web-based applications for various site components and edit site content. Document technical designs and specifications. Research and incorporate updated content for websites. Must have skills : Pyth... | X19: 429 | Y19: 2.66 | Z19: =FALSE() -> FALSE | AA19: =TRUE() -> TRUE | AB19: =TRUE() -> TRUE | AC19: =FALSE() -> FALSE | AD19: =TRUE() -> TRUE | AE19: 4 | AF19: 57.1 | AG19: Likely Ghost | AH19: https://in.linkedin.com/jobs/view/web-developer-at-accenture-in-india-4391709172?trk=public_jobs_topcard-title | AI19: =IF(AND(OR(Company_Explorer!$B$5="All Companies",$E19=Company_Explorer!$B$5),OR(Company_Explorer!$B$6="All Platforms",$B19=Company_Explorer!$B$6),OR(Company_Explorer!$B$7="All Roles",$D19=Company_Explorer!$B$7),OR(Company_Explorer!$B$8="All Ghost Labels",$AG19=Company_Explorer!$B$8)),1,0) -> 0
A20: LI_4437100474 | B20: LinkedIn | C20: Software Engineer | D20: Software Engineer | E20: Infineon Technologies | F20: =TRUE() -> TRUE | G20: Bengaluru East | H20: Karnataka | I20: 46208 | J20: 46210 | K20: 2 | L20: Full-time | M20: Mid-Senior level | N20: =FALSE() -> FALSE | Q20: N/A | R20: Not provided by LinkedIn scraper | T20: =FALSE() -> FALSE | U20: =FALSE() -> FALSE | V20: 323 | W20: Your Role Key responsibilities in your new role Team up with the departments within BC to understand business demand for automation Consult in both technical feasibility and process optimization looking at processes end-to-end as well as workflow optimization Perform the techni... | X20: 1 | Y20: 0.01 | Z20: =FALSE() -> FALSE | AA20: =TRUE() -> TRUE | AB20: =FALSE() -> FALSE | AC20: =FALSE() -> FALSE | AD20: =FALSE() -> FALSE | AE20: 1 | AF20: 14.3 | AG20: Likely Genuine | AH20: https://in.linkedin.com/jobs/view/software-engineer-at-infineon-technologies-4437100474?trk=public_jobs_topcard-title | AI20: =IF(AND(OR(Company_Explorer!$B$5="All Companies",$E20=Company_Explorer!$B$5),OR(Company_Explorer!$B$6="All Platforms",$B20=Company_Explorer!$B$6),OR(Company_Explorer!$B$7="All Roles",$D20=Company_Explorer!$B$7),OR(Company_Explorer!$B$8="All Ghost Labels",$AG20=Company_Explorer!$B$8)),1,0) -> 0
A21: LI_4288926117 | B21: LinkedIn | C21: Software Development Engineer | D21: Other | E21: Accenture in India | F21: =TRUE() -> TRUE | G21: Hyderabad | H21: Telangana | I21: 46198 | J21: 46210 | K21: 12 | L21: Full-time | M21: Mid-Senior level | N21: =FALSE() -> FALSE | Q21: N/A | R21: Not provided by LinkedIn scraper | T21: =FALSE() -> FALSE | U21: =FALSE() -> FALSE | V21: 286 | W21: Project Role : Software Development Engineer Project Role Description : Analyze, design, code and test multiple components of application code across one or more clients. Perform maintenance, enhancements and/or development work. Must have skills : SAP BTP Integration Suite Go... | X21: 429 | Y21: 2.66 | Z21: =FALSE() -> FALSE | AA21: =TRUE() -> TRUE | AB21: =FALSE() -> FALSE | AC21: =FALSE() -> FALSE | AD21: =TRUE() -> TRUE | AE21: 3 | AF21: 42.9 | AG21: Uncertain | AH21: https://in.linkedin.com/jobs/view/software-development-engineer-at-accenture-in-india-4288926117?trk=public_jobs_topcard-title | AI21: =IF(AND(OR(Company_Explorer!$B$5="All Companies",$E21=Company_Explorer!$B$5),OR(Company_Explorer!$B$6="All Platforms",$B21=Company_Explorer!$B$6),OR(Company_Explorer!$B$7="All Roles",$D21=Company_Explorer!$B$7),OR(Company_Explorer!$B$8="All Ghost Labels",$AG21=Company_Explorer!$B$8)),1,0) -> 0
A22: LI_4430286548 | B22: LinkedIn | C22: Web Developer Associate | D22: Software Engineer | E22: Accenture in India | F22: =TRUE() -> TRUE | G22: Mumbai | H22: Maharashtra | I22: 46198 | J22: 46210 | K22: 12 | L22: Full-time | M22: Entry level | N22: =FALSE() -> FALSE | Q22: N/A | R22: Not provided by LinkedIn scraper | T22: =FALSE() -> FALSE | U22: =FALSE() -> FALSE | V22: 409 | W22: Skill required: Marketing Operations - Web Application Development Designation: Web Developer Associate Qualifications:Any Graduation Years of Experience:1 to 3 years About Accenture Accenture is a global professional services company with leading capabilities in digital, cl... | X22: 429 | Y22: 2.66 | Z22: =FALSE() -> FALSE | AA22: =TRUE() -> TRUE | AB22: =FALSE() -> FALSE | AC22: =FALSE() -> FALSE | AD22: =TRUE() -> TRUE | AE22: 3 | AF22: 42.9 | AG22: Uncertain | AH22: https://in.linkedin.com/jobs/view/web-developer-associate-at-accenture-in-india-4430286548?trk=public_jobs_topcard-title | AI22: =IF(AND(OR(Company_Explorer!$B$5="All Companies",$E22=Company_Explorer!$B$5),OR(Company_Explorer!$B$6="All Platforms",$B22=Company_Explorer!$B$6),OR(Company_Explorer!$B$7="All Roles",$D22=Company_Explorer!$B$7),OR(Company_Explorer!$B$8="All Ghost Labels",$AG22=Company_Explorer!$B$8)),1,0) -> 0
A23: LI_4389222803 | B23: LinkedIn | C23: Software Engineer Fullstack Developer | D23: Full Stack Engineer | E23: DHL | F23: =TRUE() -> TRUE | G23: Indore | H23: Madhya Pradesh | I23: 46105 | J23: 46210 | K23: 105 | L23: Full-time | M23: Mid-Senior level | N23: =FALSE() -> FALSE | Q23: N/A | R23: Not provided by LinkedIn scraper | T23: =FALSE() -> FALSE | U23: =FALSE() -> FALSE | V23: 483 | W23: Your IT Future, Delivered. Software Engineer Full stack Developer (Python + JavaScript) With a global team of 5600+ IT professionals, DHL IT Services connects people and keeps the global economy running by continuously innovating and creating sustainable digital solutions. We w... | X23: 3 | Y23: 0.02 | Z23: =FALSE() -> FALSE | AA23: =TRUE() -> TRUE | AB23: =FALSE() -> FALSE | AC23: =TRUE() -> TRUE | AD23: =FALSE() -> FALSE | AE23: 2 | AF23: 28.6 | AG23: Uncertain | AH23: https://in.linkedin.com/jobs/view/software-engineer-fullstack-developer-at-dhl-4389222803?trk=public_jobs_topcard-title | AI23: =IF(AND(OR(Company_Explorer!$B$5="All Companies",$E23=Company_Explorer!$B$5),OR(Company_Explorer!$B$6="All Platforms",$B23=Company_Explorer!$B$6),OR(Company_Explorer!$B$7="All Roles",$D23=Company_Explorer!$B$7),OR(Company_Explorer!$B$8="All Ghost Labels",$AG23=Company_Explorer!$B$8)),1,0) -> 0
A24: LI_4424366187 | B24: LinkedIn | C24: Software Engineer (Typescript) | $55/hr Remote | D24: Software Engineer | E24: Crossing Hurdles | F24: =TRUE() -> TRUE | G24: India | H24: Not Specified | I24: 46199 | J24: 46210 | K24: 11 | L24: Contract | M24: Associate | N24: =TRUE() -> TRUE | O24: 20 | P24: 55 | Q24: Symbol-only ($), scale ambiguous | R24: Not provided by LinkedIn scraper | T24: =FALSE() -> FALSE | U24: =FALSE() -> FALSE | V24: 174 | W24: Position: Typescript Developer Type: Contract Compensation: $20 - $55/hour Location: Remote Commitment: 10-40 hrs/week Role Responsibilities Design, implement, and maintain high-quality Typescript codebases tailored for AI model training. Collaborate closely with cross-functiona... | X24: 7 | Y24: 0.04 | Z24: =FALSE() -> FALSE | AA24: =FALSE() -> FALSE | AB24: =TRUE() -> TRUE | AC24: =FALSE() -> FALSE | AD24: =FALSE() -> FALSE | AE24: 1 | AF24: 14.3 | AG24: Likely Genuine | AH24: https://in.linkedin.com/jobs/view/software-engineer-typescript-%2455-hr-remote-at-crossing-hurdles-4424366187?trk=public_jobs_topcard-title | AI24: =IF(AND(OR(Company_Explorer!$B$5="All Companies",$E24=Company_Explorer!$B$5),OR(Company_Explorer!$B$6="All Platforms",$B24=Company_Explorer!$B$6),OR(Company_Explorer!$B$7="All Roles",$D24=Company_Explorer!$B$7),OR(Company_Explorer!$B$8="All Ghost Labels",$AG24=Company_Explorer!$B$8)),1,0) -> 0
A25: LI_4436300981 | B25: LinkedIn | C25: Test Automation Engineer | D25: Other | E25: Capgemini | F25: =TRUE() -> TRUE | G25: Pune Division | H25: Maharashtra | I25: 46205 | J25: 46210 | K25: 5 | L25: Full-time | M25: Mid-Senior level | N25: =FALSE() -> FALSE | Q25: N/A | R25: Not provided by LinkedIn scraper | T25: =FALSE() -> FALSE | U25: =FALSE() -> FALSE | V25: 139 | W25: Job Description As Test Automation Engineer, you are involved in the automated verification and validation of products made by engineers in a development process. Your technical and professional knowledge of Test Automation, programming, test environments and methodologies is so... | X25: 9 | Y25: 0.06 | Z25: =FALSE() -> FALSE | AA25: =TRUE() -> TRUE | AB25: =TRUE() -> TRUE | AC25: =FALSE() -> FALSE | AD25: =FALSE() -> FALSE | AE25: 2 | AF25: 28.6 | AG25: Uncertain | AH25: https://in.linkedin.com/jobs/view/test-automation-engineer-at-capgemini-4436300981?trk=public_jobs_topcard-title | AI25: =IF(AND(OR(Company_Explorer!$B$5="All Companies",$E25=Company_Explorer!$B$5),OR(Company_Explorer!$B$6="All Platforms",$B25=Company_Explorer!$B$6),OR(Company_Explorer!$B$7="All Roles",$D25=Company_Explorer!$B$7),OR(Company_Explorer!$B$8="All Ghost Labels",$AG25=Company_Explorer!$B$8)),1,0) -> 0
A26: LI_4436398751 | B26: LinkedIn | C26: Software/Platform Engineer I | D26: Other | E26: MetLife | F26: =TRUE() -> TRUE | G26: Pune Division | H26: Maharashtra | I26: 46205 | J26: 46210 | K26: 5 | L26: Full-time | M26: Not Applicable | N26: =FALSE() -> FALSE | Q26: N/A | R26: Not provided by LinkedIn scraper | T26: =FALSE() -> FALSE | U26: =FALSE() -> FALSE | V26: 122 | W26: Job Responsibilities Modernize CI/CD using GitHub Actions, reusable workflows, templates, and standardized automation aligned to COE standards. Administer and govern GitHub Enterprise, including repo onboarding, access models, branch protections, runners, and security controls. ... | X26: 3 | Y26: 0.02 | Z26: =FALSE() -> FALSE | AA26: =TRUE() -> TRUE | AB26: =TRUE() -> TRUE | AC26: =FALSE() -> FALSE | AD26: =FALSE() -> FALSE | AE26: 2 | AF26: 28.6 | AG26: Uncertain | AH26: https://in.linkedin.com/jobs/view/software-platform-engineer-i-at-metlife-4436398751?trk=public_jobs_topcard-title | AI26: =IF(AND(OR(Company_Explorer!$B$5="All Companies",$E26=Company_Explorer!$B$5),OR(Company_Explorer!$B$6="All Platforms",$B26=Company_Explorer!$B$6),OR(Company_Explorer!$B$7="All Roles",$D26=Company_Explorer!$B$7),OR(Company_Explorer!$B$8="All Ghost Labels",$AG26=Company_Explorer!$B$8)),1,0) -> 0
A27: LI_4428033013 | B27: LinkedIn | C27: Java Software Engineer | D27: Software Engineer | E27: Tata Consultancy Services | F27: =TRUE() -> TRUE | G27: Bangalore Urban | H27: Karnataka | I27: 46189 | J27: 46210 | K27: 21 | L27: Full-time | M27: Mid-Senior level | N27: =FALSE() -> FALSE | Q27: N/A | R27: Not provided by LinkedIn scraper | T27: =FALSE() -> FALSE | U27: =FALSE() -> FALSE | V27: 115 | W27: Dear Candidate, Walk In Invitation :: TCS :: Java Full Stack Developer + AWS :: Bangalore :: 20-Jun-26 (Saturday) Roles and Responsibilities Role - Java Full Stack Developer + AWS Location – Bangalore (Face to Face Interview) Exp - 5+ Interested and available candidates on... | X27: 4 | Y27: 0.02 | Z27: =FALSE() -> FALSE | AA27: =TRUE() -> TRUE | AB27: =TRUE() -> TRUE | AC27: =TRUE() -> TRUE | AD27: =FALSE() -> FALSE | AE27: 3 | AF27: 42.9 | AG27: Uncertain | AH27: https://in.linkedin.com/jobs/view/java-software-engineer-at-tata-consultancy-services-4428033013?trk=public_jobs_topcard-title | AI27: =IF(AND(OR(Company_Explorer!$B$5="All Companies",$E27=Company_Explorer!$B$5),OR(Company_Explorer!$B$6="All Platforms",$B27=Company_Explorer!$B$6),OR(Company_Explorer!$B$7="All Roles",$D27=Company_Explorer!$B$7),OR(Company_Explorer!$B$8="All Ghost Labels",$AG27=Company_Explorer!$B$8)),1,0) -> 0
A28: LI_4412340196 | B28: LinkedIn | C28: Software Engineer | D28: Software Engineer | E28: Bajaj Finserv | F28: =TRUE() -> TRUE | G28: Pune Division | H28: Maharashtra | I28: 46152 | J28: 46210 | K28: 58 | L28: Full-time | M28: Associate | N28: =FALSE() -> FALSE | Q28: N/A | R28: Not provided by LinkedIn scraper | T28: =FALSE() -> FALSE | U28: =FALSE() -> FALSE | V28: 576 | W28: Location Name: Pune Corporate Office - Mantri Job Purpose JOB PURPOSE (Summarize in one statement why the job exists; and how it contributes to the overall objective of the company) Join Bajaj Finserv Ltd., where our omnipresence strategy drives 10% month-on-month growth in ... | X28: 10 | Y28: 0.06 | Z28: =FALSE() -> FALSE | AA28: =TRUE() -> TRUE | AB28: =FALSE() -> FALSE | AC28: =TRUE() -> TRUE | AD28: =FALSE() -> FALSE | AE28: 2 | AF28: 28.6 | AG28: Uncertain | AH28: https://in.linkedin.com/jobs/view/software-engineer-at-bajaj-finserv-4412340196?trk=public_jobs_topcard-title | AI28: =IF(AND(OR(Company_Explorer!$B$5="All Companies",$E28=Company_Explorer!$B$5),OR(Company_Explorer!$B$6="All Platforms",$B28=Company_Explorer!$B$6),OR(Company_Explorer!$B$7="All Roles",$D28=Company_Explorer!$B$7),OR(Company_Explorer!$B$8="All Ghost Labels",$AG28=Company_Explorer!$B$8)),1,0) -> 0
A29: LI_4426806382 | B29: LinkedIn | C29: Software Engineer | D29: Software Engineer | E29: Infor | F29: =TRUE() -> TRUE | G29: Hyderabad | H29: Telangana | I29: 46189 | J29: 46210 | K29: 21 | L29: Full-time | M29: Not Applicable | N29: =FALSE() -> FALSE | Q29: N/A | R29: Not provided by LinkedIn scraper | T29: =FALSE() -> FALSE | U29: =FALSE() -> FALSE | V29: 558 | W29: Department: Development Location: Hyderabad Description Infor are seeking a Software Engineer who is passionate about developing high-quality, scalable software solutions. You will work closely with senior engineers, product managers, and designers to deliver products that dri... | X29: 1 | Y29: 0.01 | Z29: =FALSE() -> FALSE | AA29: =TRUE() -> TRUE | AB29: =FALSE() -> FALSE | AC29: =TRUE() -> TRUE | AD29: =FALSE() -> FALSE | AE29: 2 | AF29: 28.6 | AG29: Uncertain | AH29: https://in.linkedin.com/jobs/view/software-engineer-at-infor-4426806382?trk=public_jobs_topcard-title | AI29: =IF(AND(OR(Company_Explorer!$B$5="All Companies",$E29=Company_Explorer!$B$5),OR(Company_Explorer!$B$6="All Platforms",$B29=Company_Explorer!$B$6),OR(Company_Explorer!$B$7="All Roles",$D29=Company_Explorer!$B$7),OR(Company_Explorer!$B$8="All Ghost Labels",$AG29=Company_Explorer!$B$8)),1,0) -> 0
A30: LI_4430613601 | B30: LinkedIn | C30: Web Developer Associate | D30: Software Engineer | E30: Accenture in India | F30: =TRUE() -> TRUE | G30: Mumbai | H30: Maharashtra | I30: 46199 | J30: 46210 | K30: 11 | L30: Full-time | M30: Entry level | N30: =FALSE() -> FALSE | Q30: N/A | R30: Not provided by LinkedIn scraper | T30: =FALSE() -> FALSE | U30: =FALSE() -> FALSE | V30: 404 | W30: Skill required: Marketing Operations - Web Application Development Designation: Web Developer Associate Qualifications:Any Graduation Years of Experience:1 to 3 years About Accenture Accenture is a global professional services company with leading capabilities in digital, cl... | X30: 429 | Y30: 2.66 | Z30: =FALSE() -> FALSE | AA30: =TRUE() -> TRUE | AB30: =FALSE() -> FALSE | AC30: =FALSE() -> FALSE | AD30: =TRUE() -> TRUE | AE30: 3 | AF30: 42.9 | AG30: Uncertain | AH30: https://in.linkedin.com/jobs/view/web-developer-associate-at-accenture-in-india-4430613601?trk=public_jobs_topcard-title | AI30: =IF(AND(OR(Company_Explorer!$B$5="All Companies",$E30=Company_Explorer!$B$5),OR(Company_Explorer!$B$6="All Platforms",$B30=Company_Explorer!$B$6),OR(Company_Explorer!$B$7="All Roles",$D30=Company_Explorer!$B$7),OR(Company_Explorer!$B$8="All Ghost Labels",$AG30=Company_Explorer!$B$8)),1,0) -> 0
A31: LI_4401639906 | B31: LinkedIn | C31: Web Developer | D31: Software Engineer | E31: Accenture in India | F31: =TRUE() -> TRUE | G31: Bengaluru | H31: Karnataka | I31: 46198 | J31: 46210 | K31: 12 | L31: Full-time | M31: Mid-Senior level | N31: =FALSE() -> FALSE | Q31: N/A | R31: Not provided by LinkedIn scraper | T31: =FALSE() -> FALSE | U31: =FALSE() -> FALSE | V31: 262 | W31: Project Role : Web Developer Project Role Description : Design, build and test web-based applications for various site components and edit site content. Document technical designs and specifications. Research and incorporate updated content for websites. Must have skills : Java... | X31: 429 | Y31: 2.66 | Z31: =FALSE() -> FALSE | AA31: =TRUE() -> TRUE | AB31: =TRUE() -> TRUE | AC31: =FALSE() -> FALSE | AD31: =TRUE() -> TRUE | AE31: 4 | AF31: 57.1 | AG31: Likely Ghost | AH31: https://in.linkedin.com/jobs/view/web-developer-at-accenture-in-india-4401639906?trk=public_jobs_topcard-title | AI31: =IF(AND(OR(Company_Explorer!$B$5="All Companies",$E31=Company_Explorer!$B$5),OR(Company_Explorer!$B$6="All Platforms",$B31=Company_Explorer!$B$6),OR(Company_Explorer!$B$7="All Roles",$D31=Company_Explorer!$B$7),OR(Company_Explorer!$B$8="All Ghost Labels",$AG31=Company_Explorer!$B$8)),1,0) -> 0
A32: LI_4421929814 | B32: LinkedIn | C32: Software Engineer - Python Automation | D32: Software Engineer | E32: HARMAN India | F32: =TRUE() -> TRUE | G32: Bengaluru | H32: Karnataka | I32: 46202 | J32: 46210 | K32: 8 | L32: Full-time | M32: Not Applicable | N32: =FALSE() -> FALSE | Q32: N/A | R32: Not provided by LinkedIn scraper | T32: =FALSE() -> FALSE | U32: =FALSE() -> FALSE | V32: 960 | W32: Introduction: A Career at HARMAN Automotive We’re a global, multi-disciplinary team that’s putting the innovative power of technology to work and transforming tomorrow. At HARMAN Automotive, we give you the keys to fast-track your career. Engineer audio systems and integrated t... | X32: 3 | Y32: 0.02 | Z32: =FALSE() -> FALSE | AA32: =TRUE() -> TRUE | AB32: =FALSE() -> FALSE | AC32: =FALSE() -> FALSE | AD32: =FALSE() -> FALSE | AE32: 1 | AF32: 14.3 | AG32: Likely Genuine | AH32: https://in.linkedin.com/jobs/view/software-engineer-python-automation-at-harman-india-4421929814?trk=public_jobs_topcard-title | AI32: =IF(AND(OR(Company_Explorer!$B$5="All Companies",$E32=Company_Explorer!$B$5),OR(Company_Explorer!$B$6="All Platforms",$B32=Company_Explorer!$B$6),OR(Company_Explorer!$B$7="All Roles",$D32=Company_Explorer!$B$7),OR(Company_Explorer!$B$8="All Ghost Labels",$AG32=Company_Explorer!$B$8)),1,0) -> 0
A33: LI_4300708794 | B33: LinkedIn | C33: Software Engineer | D33: Software Engineer | E33: Encardio Rite | F33: =TRUE() -> TRUE | G33: Greater Lucknow Area | H33: Not Specified | I33: 45915 | J33: 46210 | K33: 295 | L33: Full-time | M33: Entry level | N33: =FALSE() -> FALSE | Q33: N/A | R33: Not provided by LinkedIn scraper | T33: =FALSE() -> FALSE | U33: =FALSE() -> FALSE | V33: 358 | W33: Key Responsibilities Design, develop, and maintain web applications using HTML, CSS, JavaScript, PHP, Laravel, and React JS. Build and optimize database structures using MySQL or other alternative databases like PostgreSQL and SQLite. Develop robust desktop applications usin... | X33: 1 | Y33: 0.01 | Z33: =FALSE() -> FALSE | AA33: =TRUE() -> TRUE | AB33: =FALSE() -> FALSE | AC33: =TRUE() -> TRUE | AD33: =FALSE() -> FALSE | AE33: 2 | AF33: 28.6 | AG33: Uncertain | AH33: https://in.linkedin.com/jobs/view/software-engineer-at-encardio-rite-4300708794?trk=public_jobs_topcard-title | AI33: =IF(AND(OR(Company_Explorer!$B$5="All Companies",$E33=Company_Explorer!$B$5),OR(Company_Explorer!$B$6="All Platforms",$B33=Company_Explorer!$B$6),OR(Company_Explorer!$B$7="All Roles",$D33=Company_Explorer!$B$7),OR(Company_Explorer!$B$8="All Ghost Labels",$AG33=Company_Explorer!$B$8)),1,0) -> 0
A34: LI_4401673965 | B34: LinkedIn | C34: Web Developer | D34: Software Engineer | E34: Accenture in India | F34: =TRUE() -> TRUE | G34: Bengaluru | H34: Karnataka | I34: 46199 | J34: 46210 | K34: 11 | L34: Full-time | M34: Mid-Senior level | N34: =FALSE() -> FALSE | Q34: N/A | R34: Not provided by LinkedIn scraper | T34: =FALSE() -> FALSE | U34: =FALSE() -> FALSE | V34: 262 | W34: Project Role : Web Developer Project Role Description : Design, build and test web-based applications for various site components and edit site content. Document technical designs and specifications. Research and incorporate updated content for websites. Must have skills : Java... | X34: 429 | Y34: 2.66 | Z34: =FALSE() -> FALSE | AA34: =TRUE() -> TRUE | AB34: =TRUE() -> TRUE | AC34: =FALSE() -> FALSE | AD34: =TRUE() -> TRUE | AE34: 4 | AF34: 57.1 | AG34: Likely Ghost | AH34: https://in.linkedin.com/jobs/view/web-developer-at-accenture-in-india-4401673965?trk=public_jobs_topcard-title | AI34: =IF(AND(OR(Company_Explorer!$B$5="All Companies",$E34=Company_Explorer!$B$5),OR(Company_Explorer!$B$6="All Platforms",$B34=Company_Explorer!$B$6),OR(Company_Explorer!$B$7="All Roles",$D34=Company_Explorer!$B$7),OR(Company_Explorer!$B$8="All Ghost Labels",$AG34=Company_Explorer!$B$8)),1,0) -> 0
A35: LI_4424354198 | B35: LinkedIn | C35: Full-Stack Software Engineer | D35: Software Engineer | E35: Rempact | F35: =TRUE() -> TRUE | G35: Mumbai | H35: Maharashtra | I35: 46177 | J35: 46210 | K35: 33 | L35: Full-time | M35: Not Applicable | N35: =FALSE() -> FALSE | Q35: N/A | R35: Not provided by LinkedIn scraper | T35: =FALSE() -> FALSE | U35: =FALSE() -> FALSE | V35: 531 | W35: Location: Mumbai. 5 days a week, in-office. Type: Full-time Compensation: ₹50,000 - ₹1,50,000 per month, based on experience and demonstrated work Experience: 1 - 4 years About Our Client Our Client is a B2B SaaS company building AI-powered document intelligence and analytic... | X35: 1 | Y35: 0.01 | Z35: =FALSE() -> FALSE | AA35: =TRUE() -> TRUE | AB35: =FALSE() -> FALSE | AC35: =TRUE() -> TRUE | AD35: =FALSE() -> FALSE | AE35: 2 | AF35: 28.6 | AG35: Uncertain | AH35: https://in.linkedin.com/jobs/view/full-stack-software-engineer-at-rempact-4424354198?trk=public_jobs_topcard-title | AI35: =IF(AND(OR(Company_Explorer!$B$5="All Companies",$E35=Company_Explorer!$B$5),OR(Company_Explorer!$B$6="All Platforms",$B35=Company_Explorer!$B$6),OR(Company_Explorer!$B$7="All Roles",$D35=Company_Explorer!$B$7),OR(Company_Explorer!$B$8="All Ghost Labels",$AG35=Company_Explorer!$B$8)),1,0) -> 0
A36: LI_4432254380 | B36: LinkedIn | C36: Software Engineer | D36: Software Engineer | E36: Quest Global | F36: =TRUE() -> TRUE | G36: Hyderabad | H36: Telangana | I36: 46196 | J36: 46210 | K36: 14 | L36: Full-time | M36: Mid-Senior level | N36: =FALSE() -> FALSE | Q36: N/A | R36: Not provided by LinkedIn scraper | T36: =FALSE() -> FALSE | U36: =FALSE() -> FALSE | V36: 272 | W36: Job Description: Job Title: Snr Software Development Engineer Experience: 5+ Years Location: Hyderabad Job Type: Full-Time Job Summary : We are seeking a talented Java Developer with expertise in building robust, scalable backend systems and proficiency in AWS Cloud services. W... | X36: 3 | Y36: 0.02 | Z36: =FALSE() -> FALSE | AA36: =TRUE() -> TRUE | AB36: =TRUE() -> TRUE | AC36: =FALSE() -> FALSE | AD36: =FALSE() -> FALSE | AE36: 2 | AF36: 28.6 | AG36: Uncertain | AH36: https://in.linkedin.com/jobs/view/software-engineer-at-quest-global-4432254380?trk=public_jobs_topcard-title | AI36: =IF(AND(OR(Company_Explorer!$B$5="All Companies",$E36=Company_Explorer!$B$5),OR(Company_Explorer!$B$6="All Platforms",$B36=Company_Explorer!$B$6),OR(Company_Explorer!$B$7="All Roles",$D36=Company_Explorer!$B$7),OR(Company_Explorer!$B$8="All Ghost Labels",$AG36=Company_Explorer!$B$8)),1,0) -> 0
A37: LI_4417067332 | B37: LinkedIn | C37: Software Development Engineer - I | D37: Other | E37: CommerceIQ | F37: =TRUE() -> TRUE | G37: Bengaluru | H37: Karnataka | I37: 46204 | J37: 46210 | K37: 6 | L37: Full-time | M37: Not Applicable | N37: =FALSE() -> FALSE | Q37: N/A | R37: Not provided by LinkedIn scraper | T37: =FALSE() -> FALSE | U37: =FALSE() -> FALSE | V37: 343 | W37: The Company CommerceIQ is building the AI platform that runs commerce for the world's largest brands. We are not selling AI demos. We are shipping AI agents for content, media, and sales into the workflows of the Fortune 100 every week. 2,200+ Customers 10 of Top 12 CPG Comp... | X37: 2 | Y37: 0.01 | Z37: =FALSE() -> FALSE | AA37: =TRUE() -> TRUE | AB37: =FALSE() -> FALSE | AC37: =FALSE() -> FALSE | AD37: =FALSE() -> FALSE | AE37: 1 | AF37: 14.3 | AG37: Likely Genuine | AH37: https://in.linkedin.com/jobs/view/software-development-engineer-i-at-commerceiq-4417067332?trk=public_jobs_topcard-title | AI37: =IF(AND(OR(Company_Explorer!$B$5="All Companies",$E37=Company_Explorer!$B$5),OR(Company_Explorer!$B$6="All Platforms",$B37=Company_Explorer!$B$6),OR(Company_Explorer!$B$7="All Roles",$D37=Company_Explorer!$B$7),OR(Company_Explorer!$B$8="All Ghost Labels",$AG37=Company_Explorer!$B$8)),1,0) -> 0
A38: LI_4432327967 | B38: LinkedIn | C38: Associate Software Engineer | D38: Software Engineer | E38: ZENNER India | F38: =TRUE() -> TRUE | G38: Faridabad | H38: Haryana | I38: 46204 | J38: 46210 | K38: 6 | L38: Full-time | M38: Entry level | N38: =FALSE() -> FALSE | Q38: N/A | R38: Not provided by LinkedIn scraper | T38: =FALSE() -> FALSE | U38: =FALSE() -> FALSE | V38: 541 | W38: About ZENNER Aquamet At ZENNER Aquamet, we develop modern software solutions that power connected IoT ecosystems and enable secure, data-driven decision-making. Our engineering teams build scalable web applications, APIs, and cloud-based services that support customers across uti... | X38: 1 | Y38: 0.01 | Z38: =FALSE() -> FALSE | AA38: =TRUE() -> TRUE | AB38: =FALSE() -> FALSE | AC38: =FALSE() -> FALSE | AD38: =FALSE() -> FALSE | AE38: 1 | AF38: 14.3 | AG38: Likely Genuine | AH38: https://in.linkedin.com/jobs/view/associate-software-engineer-at-zenner-india-4432327967?trk=public_jobs_topcard-title | AI38: =IF(AND(OR(Company_Explorer!$B$5="All Companies",$E38=Company_Explorer!$B$5),OR(Company_Explorer!$B$6="All Platforms",$B38=Company_Explorer!$B$6),OR(Company_Explorer!$B$7="All Roles",$D38=Company_Explorer!$B$7),OR(Company_Explorer!$B$8="All Ghost Labels",$AG38=Company_Explorer!$B$8)),1,0) -> 0
A39: LI_4428441551 | B39: LinkedIn | C39: Software Engineer | D39: Software Engineer | E39: Tata Consultancy Services | F39: =TRUE() -> TRUE | G39: Ahmedabad | H39: Gujarat | I39: 46190 | J39: 46210 | K39: 20 | L39: Full-time | M39: Mid-Senior level | N39: =FALSE() -> FALSE | Q39: N/A | R39: Not provided by LinkedIn scraper | T39: =FALSE() -> FALSE | U39: =FALSE() -> FALSE | V39: 171 | W39: Hi Folks Tata Consultancy Services is hosting a BFSI Walk-in Drive in Gandhinagar (Ahmedabad). Join the innovative world of Tata Consultancy Services and explore exciting opportunities. We are looking for tech enthusiasts for the following skills: Open Roles Hiring Location Prima... | X39: 4 | Y39: 0.02 | Z39: =FALSE() -> FALSE | AA39: =TRUE() -> TRUE | AB39: =TRUE() -> TRUE | AC39: =TRUE() -> TRUE | AD39: =FALSE() -> FALSE | AE39: 3 | AF39: 42.9 | AG39: Uncertain | AH39: https://in.linkedin.com/jobs/view/software-engineer-at-tata-consultancy-services-4428441551?trk=public_jobs_topcard-title | AI39: =IF(AND(OR(Company_Explorer!$B$5="All Companies",$E39=Company_Explorer!$B$5),OR(Company_Explorer!$B$6="All Platforms",$B39=Company_Explorer!$B$6),OR(Company_Explorer!$B$7="All Roles",$D39=Company_Explorer!$B$7),OR(Company_Explorer!$B$8="All Ghost Labels",$AG39=Company_Explorer!$B$8)),1,0) -> 0
A40: LI_4371894374 | B40: LinkedIn | C40: Custom Software Engineer | D40: Software Engineer | E40: Accenture in India | F40: =TRUE() -> TRUE | G40: Chennai | H40: Tamil Nadu | I40: 46198 | J40: 46210 | K40: 12 | L40: Full-time | M40: Mid-Senior level | N40: =FALSE() -> FALSE | Q40: N/A | R40: Not provided by LinkedIn scraper | T40: =FALSE() -> FALSE | U40: =FALSE() -> FALSE | V40: 275 | W40: Project Role : Custom Software Engineer Project Role Description : Develop custom software solutions to design, code, and enhance components across systems or applications. Use modern frameworks and agile practices to deliver scalable, high-performing solutions tailored to speci... | X40: 429 | Y40: 2.66 | Z40: =FALSE() -> FALSE | AA40: =TRUE() -> TRUE | AB40: =FALSE() -> FALSE | AC40: =FALSE() -> FALSE | AD40: =TRUE() -> TRUE | AE40: 3 | AF40: 42.9 | AG40: Uncertain | AH40: https://in.linkedin.com/jobs/view/custom-software-engineer-at-accenture-in-india-4371894374?trk=public_jobs_topcard-title | AI40: =IF(AND(OR(Company_Explorer!$B$5="All Companies",$E40=Company_Explorer!$B$5),OR(Company_Explorer!$B$6="All Platforms",$B40=Company_Explorer!$B$6),OR(Company_Explorer!$B$7="All Roles",$D40=Company_Explorer!$B$7),OR(Company_Explorer!$B$8="All Ghost Labels",$AG40=Company_Explorer!$B$8)),1,0) -> 0
A41: LI_4433895436 | B41: LinkedIn | C41: Custom Software Engineer | D41: Software Engineer | E41: Accenture in India | F41: =TRUE() -> TRUE | G41: Bengaluru | H41: Karnataka | I41: 46199 | J41: 46210 | K41: 11 | L41: Full-time | M41: Mid-Senior level | N41: =FALSE() -> FALSE | Q41: N/A | R41: Not provided by LinkedIn scraper | T41: =FALSE() -> FALSE | U41: =FALSE() -> FALSE | V41: 314 | W41: Project Role : Custom Software Engineer Project Role Description : Develop custom software solutions to design, code, and enhance components across systems or applications. Use modern frameworks and agile practices to deliver scalable, high-performing solutions tailored to speci... | X41: 429 | Y41: 2.66 | Z41: =FALSE() -> FALSE | AA41: =TRUE() -> TRUE | AB41: =FALSE() -> FALSE | AC41: =FALSE() -> FALSE | AD41: =TRUE() -> TRUE | AE41: 3 | AF41: 42.9 | AG41: Uncertain | AH41: https://in.linkedin.com/jobs/view/custom-software-engineer-at-accenture-in-india-4433895436?trk=public_jobs_topcard-title | AI41: =IF(AND(OR(Company_Explorer!$B$5="All Companies",$E41=Company_Explorer!$B$5),OR(Company_Explorer!$B$6="All Platforms",$B41=Company_Explorer!$B$6),OR(Company_Explorer!$B$7="All Roles",$D41=Company_Explorer!$B$7),OR(Company_Explorer!$B$8="All Ghost Labels",$AG41=Company_Explorer!$B$8)),1,0) -> 0
A42: LI_4372102046 | B42: LinkedIn | C42: Custom Software Engineer | D42: Software Engineer | E42: Accenture in India | F42: =TRUE() -> TRUE | G42: Chennai | H42: Tamil Nadu | I42: 46198 | J42: 46210 | K42: 12 | L42: Full-time | M42: Mid-Senior level | N42: =FALSE() -> FALSE | Q42: N/A | R42: Not provided by LinkedIn scraper | T42: =FALSE() -> FALSE | U42: =FALSE() -> FALSE | V42: 277 | W42: Project Role : Custom Software Engineer Project Role Description : Develop custom software solutions to design, code, and enhance components across systems or applications. Use modern frameworks and agile practices to deliver scalable, high-performing solutions tailored to speci... | X42: 429 | Y42: 2.66 | Z42: =FALSE() -> FALSE | AA42: =TRUE() -> TRUE | AB42: =FALSE() -> FALSE | AC42: =FALSE() -> FALSE | AD42: =TRUE() -> TRUE | AE42: 3 | AF42: 42.9 | AG42: Uncertain | AH42: https://in.linkedin.com/jobs/view/custom-software-engineer-at-accenture-in-india-4372102046?trk=public_jobs_topcard-title | AI42: =IF(AND(OR(Company_Explorer!$B$5="All Companies",$E42=Company_Explorer!$B$5),OR(Company_Explorer!$B$6="All Platforms",$B42=Company_Explorer!$B$6),OR(Company_Explorer!$B$7="All Roles",$D42=Company_Explorer!$B$7),OR(Company_Explorer!$B$8="All Ghost Labels",$AG42=Company_Explorer!$B$8)),1,0) -> 0
A43: LI_4341764606 | B43: LinkedIn | C43: Custom Software Engineer | D43: Software Engineer | E43: Accenture in India | F43: =TRUE() -> TRUE | G43: Bengaluru | H43: Karnataka | I43: 46198 | J43: 46210 | K43: 12 | L43: Full-time | M43: Mid-Senior level | N43: =FALSE() -> FALSE | Q43: N/A | R43: Not provided by LinkedIn scraper | T43: =FALSE() -> FALSE | U43: =FALSE() -> FALSE | V43: 302 | W43: Project Role : Custom Software Engineer Project Role Description : Develop custom software solutions to design, code, and enhance components across systems or applications. Use modern frameworks and agile practices to deliver scalable, high-performing solutions tailored to speci... | X43: 429 | Y43: 2.66 | Z43: =FALSE() -> FALSE | AA43: =TRUE() -> TRUE | AB43: =FALSE() -> FALSE | AC43: =FALSE() -> FALSE | AD43: =TRUE() -> TRUE | AE43: 3 | AF43: 42.9 | AG43: Uncertain | AH43: https://in.linkedin.com/jobs/view/custom-software-engineer-at-accenture-in-india-4341764606?trk=public_jobs_topcard-title | AI43: =IF(AND(OR(Company_Explorer!$B$5="All Companies",$E43=Company_Explorer!$B$5),OR(Company_Explorer!$B$6="All Platforms",$B43=Company_Explorer!$B$6),OR(Company_Explorer!$B$7="All Roles",$D43=Company_Explorer!$B$7),OR(Company_Explorer!$B$8="All Ghost Labels",$AG43=Company_Explorer!$B$8)),1,0) -> 0
A44: LI_4436417065 | B44: LinkedIn | C44: Software/Platform Engineer I | D44: Other | E44: MetLife | F44: =TRUE() -> TRUE | G44: Pune Division | H44: Maharashtra | I44: 46205 | J44: 46210 | K44: 5 | L44: Full-time | M44: Not Applicable | N44: =FALSE() -> FALSE | Q44: N/A | R44: Not provided by LinkedIn scraper | T44: =FALSE() -> FALSE | U44: =FALSE() -> FALSE | V44: 121 | W44: Job Responsibilities Modernize CI/CD using GitHub Actions, reusable workflows, templates, and standardized automation aligned to COE standards. Administer and govern GitHub Enterprise, including repo onboarding, access models, branch protections, runners, and security controls. ... | X44: 3 | Y44: 0.02 | Z44: =FALSE() -> FALSE | AA44: =TRUE() -> TRUE | AB44: =TRUE() -> TRUE | AC44: =FALSE() -> FALSE | AD44: =FALSE() -> FALSE | AE44: 2 | AF44: 28.6 | AG44: Uncertain | AH44: https://in.linkedin.com/jobs/view/software-platform-engineer-i-at-metlife-4436417065?trk=public_jobs_topcard-title | AI44: =IF(AND(OR(Company_Explorer!$B$5="All Companies",$E44=Company_Explorer!$B$5),OR(Company_Explorer!$B$6="All Platforms",$B44=Company_Explorer!$B$6),OR(Company_Explorer!$B$7="All Roles",$D44=Company_Explorer!$B$7),OR(Company_Explorer!$B$8="All Ghost Labels",$AG44=Company_Explorer!$B$8)),1,0) -> 0
A45: LI_4409278208 | B45: LinkedIn | C45: Custom Software Engineer | D45: Software Engineer | E45: Accenture in India | F45: =TRUE() -> TRUE | G45: Chennai | H45: Tamil Nadu | I45: 46198 | J45: 46210 | K45: 12 | L45: Full-time | M45: Mid-Senior level | N45: =FALSE() -> FALSE | Q45: N/A | R45: Not provided by LinkedIn scraper | T45: =FALSE() -> FALSE | U45: =FALSE() -> FALSE | V45: 281 | W45: Project Role : Custom Software Engineer Project Role Description : Analyze, design, code and test multiple components of application code across one or more clients. Perform maintenance, enhancements and/or development work. Must have skills : Java Enterprise Edition Good to h... | X45: 429 | Y45: 2.66 | Z45: =FALSE() -> FALSE | AA45: =TRUE() -> TRUE | AB45: =FALSE() -> FALSE | AC45: =FALSE() -> FALSE | AD45: =TRUE() -> TRUE | AE45: 3 | AF45: 42.9 | AG45: Uncertain | AH45: https://in.linkedin.com/jobs/view/custom-software-engineer-at-accenture-in-india-4409278208?trk=public_jobs_topcard-title | AI45: =IF(AND(OR(Company_Explorer!$B$5="All Companies",$E45=Company_Explorer!$B$5),OR(Company_Explorer!$B$6="All Platforms",$B45=Company_Explorer!$B$6),OR(Company_Explorer!$B$7="All Roles",$D45=Company_Explorer!$B$7),OR(Company_Explorer!$B$8="All Ghost Labels",$AG45=Company_Explorer!$B$8)),1,0) -> 0
A46: LI_4436090639 | B46: LinkedIn | C46: Software Engineer | D46: Software Engineer | E46: Scoutit | F46: =TRUE() -> TRUE | G46: Bengaluru Rural District | H46: Karnataka | I46: 46209 | J46: 46210 | K46: 1 | L46: Full-time | M46: Entry level | N46: =FALSE() -> FALSE | Q46: N/A | R46: Not provided by LinkedIn scraper | T46: =FALSE() -> FALSE | U46: =FALSE() -> FALSE | V46: 158 | W46: We're looking for Software Engineers! Qualifications Proficiency in software development or a related field Familiarity working on project(s) involving the implementation of solutions applying development life cycles (SDLC) through iterative agile development Familiarity worki... | X46: 3 | Y46: 0.02 | Z46: =FALSE() -> FALSE | AA46: =TRUE() -> TRUE | AB46: =TRUE() -> TRUE | AC46: =FALSE() -> FALSE | AD46: =FALSE() -> FALSE | AE46: 2 | AF46: 28.6 | AG46: Uncertain | AH46: https://in.linkedin.com/jobs/view/software-engineer-at-scoutit-4436090639?trk=public_jobs_topcard-title | AI46: =IF(AND(OR(Company_Explorer!$B$5="All Companies",$E46=Company_Explorer!$B$5),OR(Company_Explorer!$B$6="All Platforms",$B46=Company_Explorer!$B$6),OR(Company_Explorer!$B$7="All Roles",$D46=Company_Explorer!$B$7),OR(Company_Explorer!$B$8="All Ghost Labels",$AG46=Company_Explorer!$B$8)),1,0) -> 0
A47: LI_4367949006 | B47: LinkedIn | C47: System Engineer (m/f/d) | D47: Other | E47: Deutsche Telekom | F47: =TRUE() -> TRUE | G47: Bengaluru | H47: Karnataka | I47: 46053 | J47: 46210 | K47: 157 | L47: Part-time | M47: Not Applicable | N47: =FALSE() -> FALSE | Q47: N/A | R47: Not provided by LinkedIn scraper | T47: =FALSE() -> FALSE | U47: =FALSE() -> FALSE | V47: 685 | W47: Deine Aufgabe Diese Rolle ist für einen Unix/Linux Engineer/Administrator mit Verantwortlichkeiten im Bereich Systemadministration, Virtualisierung und Infrastrukturmanagement. Die Position erfordert exzellente Administrationskenntnisse und praktische Erfahrung mit Unix-Betriebs... | X47: 1 | Y47: 0.01 | Z47: =FALSE() -> FALSE | AA47: =TRUE() -> TRUE | AB47: =FALSE() -> FALSE | AC47: =TRUE() -> TRUE | AD47: =FALSE() -> FALSE | AE47: 2 | AF47: 28.6 | AG47: Uncertain | AH47: https://in.linkedin.com/jobs/view/system-engineer-m-f-d-at-deutsche-telekom-4367949006?trk=public_jobs_topcard-title | AI47: =IF(AND(OR(Company_Explorer!$B$5="All Companies",$E47=Company_Explorer!$B$5),OR(Company_Explorer!$B$6="All Platforms",$B47=Company_Explorer!$B$6),OR(Company_Explorer!$B$7="All Roles",$D47=Company_Explorer!$B$7),OR(Company_Explorer!$B$8="All Ghost Labels",$AG47=Company_Explorer!$B$8)),1,0) -> 0
A48: LI_4314588566 | B48: LinkedIn | C48: Software Engineer 2 | D48: Software Engineer | E48: Visteon Corporation | F48: =TRUE() -> TRUE | G48: Pune Division | H48: Maharashtra | I48: 46205 | J48: 46210 | K48: 5 | L48: Full-time | M48: Not Applicable | N48: =FALSE() -> FALSE | Q48: N/A | R48: Not provided by LinkedIn scraper | T48: =FALSE() -> FALSE | U48: =FALSE() -> FALSE | V48: 980 | W48: Autosar appln Engineer At Visteon, the work we do is both relevant and recognized—not just by our organization, but by our peers, by industry-leading brands, and by millions of drivers around the world. That’s YOUR work. And, as a truly global technology leader in the mobility ... | X48: 1 | Y48: 0.01 | Z48: =FALSE() -> FALSE | AA48: =TRUE() -> TRUE | AB48: =FALSE() -> FALSE | AC48: =FALSE() -> FALSE | AD48: =FALSE() -> FALSE | AE48: 1 | AF48: 14.3 | AG48: Likely Genuine | AH48: https://in.linkedin.com/jobs/view/software-engineer-2-at-visteon-corporation-4314588566?trk=public_jobs_topcard-title | AI48: =IF(AND(OR(Company_Explorer!$B$5="All Companies",$E48=Company_Explorer!$B$5),OR(Company_Explorer!$B$6="All Platforms",$B48=Company_Explorer!$B$6),OR(Company_Explorer!$B$7="All Roles",$D48=Company_Explorer!$B$7),OR(Company_Explorer!$B$8="All Ghost Labels",$AG48=Company_Explorer!$B$8)),1,0) -> 0
A49: LI_4418955962 | B49: LinkedIn | C49: Software Engineer-I | D49: Software Engineer | E49: PENNEP | F49: =TRUE() -> TRUE | G49: Jalandhar I | H49: Punjab | I49: 46167 | J49: 46210 | K49: 43 | L49: Full-time | M49: Not Applicable | N49: =FALSE() -> FALSE | Q49: N/A | R49: Not provided by LinkedIn scraper | T49: =FALSE() -> FALSE | U49: =FALSE() -> FALSE | V49: 316 | W49: Description PENNEP is seeking a skilled Software Engineer-I to join our team. The ideal candidate will have experience in NodeJS, JavaScript or TypeScript, ReactJS, NextJS, API design and development, NoSQL database design and development. The successful candidate will be respon... | X49: 1 | Y49: 0.01 | Z49: =FALSE() -> FALSE | AA49: =TRUE() -> TRUE | AB49: =FALSE() -> FALSE | AC49: =TRUE() -> TRUE | AD49: =FALSE() -> FALSE | AE49: 2 | AF49: 28.6 | AG49: Uncertain | AH49: https://in.linkedin.com/jobs/view/software-engineer-i-at-pennep-4418955962?trk=public_jobs_topcard-title | AI49: =IF(AND(OR(Company_Explorer!$B$5="All Companies",$E49=Company_Explorer!$B$5),OR(Company_Explorer!$B$6="All Platforms",$B49=Company_Explorer!$B$6),OR(Company_Explorer!$B$7="All Roles",$D49=Company_Explorer!$B$7),OR(Company_Explorer!$B$8="All Ghost Labels",$AG49=Company_Explorer!$B$8)),1,0) -> 0
A50: LI_4421080436 | B50: LinkedIn | C50: Software Engineer - (C#/.NET & React) Job | D50: Software Engineer | E50: YASH Technologies | F50: =TRUE() -> TRUE | G50: Bengaluru | H50: Karnataka | I50: 46192 | J50: 46210 | K50: 18 | L50: Full-time | M50: Not Applicable | N50: =FALSE() -> FALSE | Q50: N/A | R50: Not provided by LinkedIn scraper | T50: =FALSE() -> FALSE | U50: =FALSE() -> FALSE | V50: 336 | W50: YASH Technologies is a leading technology integrator specializing in helping clients reimagine operating models, enhance competitiveness, optimize costs, foster exceptional stakeholder experiences, and drive business transformation. At YASH, we’re a cluster of the brightest star... | X50: 1 | Y50: 0.01 | Z50: =FALSE() -> FALSE | AA50: =TRUE() -> TRUE | AB50: =FALSE() -> FALSE | AC50: =FALSE() -> FALSE | AD50: =FALSE() -> FALSE | AE50: 1 | AF50: 14.3 | AG50: Likely Genuine | AH50: https://in.linkedin.com/jobs/view/software-engineer-c%23-net-react-job-at-yash-technologies-4421080436?trk=public_jobs_topcard-title | AI50: =IF(AND(OR(Company_Explorer!$B$5="All Companies",$E50=Company_Explorer!$B$5),OR(Company_Explorer!$B$6="All Platforms",$B50=Company_Explorer!$B$6),OR(Company_Explorer!$B$7="All Roles",$D50=Company_Explorer!$B$7),OR(Company_Explorer!$B$8="All Ghost Labels",$AG50=Company_Explorer!$B$8)),1,0) -> 0
A51: LI_4420140045 | B51: LinkedIn | C51: Full Stack Software Engineer (C#, JavaScript) | D51: Full Stack Engineer | E51: Vonage | F51: =TRUE() -> TRUE | G51: Bengaluru East | H51: Karnataka | I51: 46197 | J51: 46210 | K51: 13 | L51: Full-time | M51: Mid-Senior level | N51: =FALSE() -> FALSE | Q51: N/A | R51: Not provided by LinkedIn scraper | T51: =FALSE() -> FALSE | U51: =FALSE() -> FALSE | V51: 429 | W51: Join Vonage and help us innovate cloud communications for businesses worldwide! Why This Role Matters We are looking for Software Engineers to work in the Call Center as a Service (CCaaS) Technology Team where you will be working on a global, multi-tenant, real-time service, wi... | X51: 1 | Y51: 0.01 | Z51: =FALSE() -> FALSE | AA51: =TRUE() -> TRUE | AB51: =FALSE() -> FALSE | AC51: =FALSE() -> FALSE | AD51: =FALSE() -> FALSE | AE51: 1 | AF51: 14.3 | AG51: Likely Genuine | AH51: https://in.linkedin.com/jobs/view/full-stack-software-engineer-c%23-javascript-at-vonage-4420140045?trk=public_jobs_topcard-title | AI51: =IF(AND(OR(Company_Explorer!$B$5="All Companies",$E51=Company_Explorer!$B$5),OR(Company_Explorer!$B$6="All Platforms",$B51=Company_Explorer!$B$6),OR(Company_Explorer!$B$7="All Roles",$D51=Company_Explorer!$B$7),OR(Company_Explorer!$B$8="All Ghost Labels",$AG51=Company_Explorer!$B$8)),1,0) -> 0
A52: LI_4428239567 | B52: LinkedIn | C52: Software Engineer-Full Stack | D52: Full Stack Engineer | E52: Okta | F52: =TRUE() -> TRUE | G52: Bengaluru | H52: Karnataka | I52: 46192 | J52: 46210 | K52: 18 | L52: Full-time | M52: Not Applicable | N52: =FALSE() -> FALSE | Q52: N/A | R52: Not provided by LinkedIn scraper | T52: =FALSE() -> FALSE | U52: =FALSE() -> FALSE | V52: 724 | W52: Secure Every Identity, from AI to Human Identity is the key to unlocking the potential of AI. Okta secures AI by building the trusted, neutral infrastructure that enables organizations to safely embrace this new era. This work requires a relentless drive to solve complex challen... | X52: 1 | Y52: 0.01 | Z52: =FALSE() -> FALSE | AA52: =TRUE() -> TRUE | AB52: =FALSE() -> FALSE | AC52: =FALSE() -> FALSE | AD52: =FALSE() -> FALSE | AE52: 1 | AF52: 14.3 | AG52: Likely Genuine | AH52: https://in.linkedin.com/jobs/view/software-engineer-full-stack-at-okta-4428239567?trk=public_jobs_topcard-title | AI52: =IF(AND(OR(Company_Explorer!$B$5="All Companies",$E52=Company_Explorer!$B$5),OR(Company_Explorer!$B$6="All Platforms",$B52=Company_Explorer!$B$6),OR(Company_Explorer!$B$7="All Roles",$D52=Company_Explorer!$B$7),OR(Company_Explorer!$B$8="All Ghost Labels",$AG52=Company_Explorer!$B$8)),1,0) -> 0
A53: LI_4429130181 | B53: LinkedIn | C53: Software Engineer | D53: Software Engineer | E53: DHL | F53: =TRUE() -> TRUE | G53: Indore | H53: Madhya Pradesh | I53: 46206 | J53: 46210 | K53: 4 | L53: Full-time | M53: Mid-Senior level | N53: =FALSE() -> FALSE | Q53: N/A | R53: Not provided by LinkedIn scraper | T53: =FALSE() -> FALSE | U53: =FALSE() -> FALSE | V53: 559 | W53: Your Future, Delivered. Software Engineer – AI Platform (MCP & AI Integrations) With a global team of around 5600+ IT professionals, DHL IT Services connects people and keeps the global economy running by continuously innovating and creating sustainable digital solutions. We wo... | X53: 3 | Y53: 0.02 | Z53: =FALSE() -> FALSE | AA53: =TRUE() -> TRUE | AB53: =FALSE() -> FALSE | AC53: =FALSE() -> FALSE | AD53: =FALSE() -> FALSE | AE53: 1 | AF53: 14.3 | AG53: Likely Genuine | AH53: https://in.linkedin.com/jobs/view/software-engineer-at-dhl-4429130181?trk=public_jobs_topcard-title | AI53: =IF(AND(OR(Company_Explorer!$B$5="All Companies",$E53=Company_Explorer!$B$5),OR(Company_Explorer!$B$6="All Platforms",$B53=Company_Explorer!$B$6),OR(Company_Explorer!$B$7="All Roles",$D53=Company_Explorer!$B$7),OR(Company_Explorer!$B$8="All Ghost Labels",$AG53=Company_Explorer!$B$8)),1,0) -> 0
A54: LI_4433195196 | B54: LinkedIn | C54: Software Developer/Engineer - Frontend (ReactJs) | D54: Frontend Engineer | E54: Siemens | F54: =TRUE() -> TRUE | G54: Bangalore Urban | H54: Karnataka | I54: 46206 | J54: 46210 | K54: 4 | L54: Full-time | M54: Not Applicable | N54: =FALSE() -> FALSE | Q54: N/A | R54: Not provided by LinkedIn scraper | T54: =FALSE() -> FALSE | U54: =FALSE() -> FALSE | V54: 528 | W54: Hello Visionary! We empower our people to stay resilient and relevant in a constantly evolving world. We’re looking for people who are always searching for creative ways to grow and learn. People who want to make a real impact, now and in the future. Does that sound like you? T... | X54: 2 | Y54: 0.01 | Z54: =FALSE() -> FALSE | AA54: =TRUE() -> TRUE | AB54: =FALSE() -> FALSE | AC54: =FALSE() -> FALSE | AD54: =FALSE() -> FALSE | AE54: 1 | AF54: 14.3 | AG54: Likely Genuine | AH54: https://in.linkedin.com/jobs/view/software-developer-engineer-frontend-reactjs-at-siemens-4433195196?trk=public_jobs_topcard-title | AI54: =IF(AND(OR(Company_Explorer!$B$5="All Companies",$E54=Company_Explorer!$B$5),OR(Company_Explorer!$B$6="All Platforms",$B54=Company_Explorer!$B$6),OR(Company_Explorer!$B$7="All Roles",$D54=Company_Explorer!$B$7),OR(Company_Explorer!$B$8="All Ghost Labels",$AG54=Company_Explorer!$B$8)),1,0) -> 0
A55: LI_4408816727 | B55: LinkedIn | C55: Software Development Engineer Testing | D55: Other | E55: apna | F55: =TRUE() -> TRUE | G55: Bengaluru | H55: Karnataka | I55: 46123 | J55: 46210 | K55: 87 | L55: Full-time | M55: Mid-Senior level | N55: =FALSE() -> FALSE | Q55: N/A | R55: Not provided by LinkedIn scraper | T55: =FALSE() -> FALSE | U55: =FALSE() -> FALSE | V55: 187 | W55: Qualifications: Key Responsibilities: Execute manual test cases and report defects accurately to the development team Assist in developing, maintaining, and running automated test scripts for functional and regression testing Participate in requirements analysis to understand an... | X55: 1 | Y55: 0.01 | Z55: =FALSE() -> FALSE | AA55: =TRUE() -> TRUE | AB55: =TRUE() -> TRUE | AC55: =TRUE() -> TRUE | AD55: =FALSE() -> FALSE | AE55: 3 | AF55: 42.9 | AG55: Uncertain | AH55: https://in.linkedin.com/jobs/view/software-development-engineer-testing-at-apna-4408816727?trk=public_jobs_topcard-title | AI55: =IF(AND(OR(Company_Explorer!$B$5="All Companies",$E55=Company_Explorer!$B$5),OR(Company_Explorer!$B$6="All Platforms",$B55=Company_Explorer!$B$6),OR(Company_Explorer!$B$7="All Roles",$D55=Company_Explorer!$B$7),OR(Company_Explorer!$B$8="All Ghost Labels",$AG55=Company_Explorer!$B$8)),1,0) -> 0
A56: LI_4347741969 | B56: LinkedIn | C56: Software Development Engineer | D56: Other | E56: Accenture in India | F56: =TRUE() -> TRUE | G56: Pune City | H56: Maharashtra | I56: 46198 | J56: 46210 | K56: 12 | L56: Full-time | M56: Mid-Senior level | N56: =FALSE() -> FALSE | Q56: N/A | R56: Not provided by LinkedIn scraper | T56: =FALSE() -> FALSE | U56: =FALSE() -> FALSE | V56: 286 | W56: Project Role : Software Development Engineer Project Role Description : Analyze, design, code and test multiple components of application code across one or more clients. Perform maintenance, enhancements and/or development work. Must have skills : SAP Governance Risk and Compl... | X56: 429 | Y56: 2.66 | Z56: =FALSE() -> FALSE | AA56: =TRUE() -> TRUE | AB56: =FALSE() -> FALSE | AC56: =FALSE() -> FALSE | AD56: =TRUE() -> TRUE | AE56: 3 | AF56: 42.9 | AG56: Uncertain | AH56: https://in.linkedin.com/jobs/view/software-development-engineer-at-accenture-in-india-4347741969?trk=public_jobs_topcard-title | AI56: =IF(AND(OR(Company_Explorer!$B$5="All Companies",$E56=Company_Explorer!$B$5),OR(Company_Explorer!$B$6="All Platforms",$B56=Company_Explorer!$B$6),OR(Company_Explorer!$B$7="All Roles",$D56=Company_Explorer!$B$7),OR(Company_Explorer!$B$8="All Ghost Labels",$AG56=Company_Explorer!$B$8)),1,0) -> 0
A57: LI_4431855036 | B57: LinkedIn | C57: Full-Stack Software Engineer | D57: Software Engineer | E57: Chargebee | F57: =TRUE() -> TRUE | G57: Bengaluru | H57: Karnataka | I57: 46197 | J57: 46210 | K57: 13 | L57: Full-time | M57: Associate | N57: =FALSE() -> FALSE | Q57: N/A | R57: Not provided by LinkedIn scraper | T57: =FALSE() -> FALSE | U57: =FALSE() -> FALSE | V57: 573 | W57: About Chargebee Chargebee is the subscription billing and monetization platform built for the AI economy, powering some of the world's fastest-growing subscription and SaaS businesses. Companies of all sizes — from fast-scaling startups to global enterprises — rely on Chargebee t... | X57: 1 | Y57: 0.01 | Z57: =FALSE() -> FALSE | AA57: =TRUE() -> TRUE | AB57: =FALSE() -> FALSE | AC57: =FALSE() -> FALSE | AD57: =FALSE() -> FALSE | AE57: 1 | AF57: 14.3 | AG57: Likely Genuine | AH57: https://in.linkedin.com/jobs/view/full-stack-software-engineer-at-chargebee-4431855036?trk=public_jobs_topcard-title | AI57: =IF(AND(OR(Company_Explorer!$B$5="All Companies",$E57=Company_Explorer!$B$5),OR(Company_Explorer!$B$6="All Platforms",$B57=Company_Explorer!$B$6),OR(Company_Explorer!$B$7="All Roles",$D57=Company_Explorer!$B$7),OR(Company_Explorer!$B$8="All Ghost Labels",$AG57=Company_Explorer!$B$8)),1,0) -> 0
A58: LI_4371897313 | B58: LinkedIn | C58: Custom Software Engineer | D58: Software Engineer | E58: Accenture in India | F58: =TRUE() -> TRUE | G58: Chennai | H58: Tamil Nadu | I58: 46198 | J58: 46210 | K58: 12 | L58: Full-time | M58: Mid-Senior level | N58: =FALSE() -> FALSE | Q58: N/A | R58: Not provided by LinkedIn scraper | T58: =FALSE() -> FALSE | U58: =FALSE() -> FALSE | V58: 277 | W58: Project Role : Custom Software Engineer Project Role Description : Develop custom software solutions to design, code, and enhance components across systems or applications. Use modern frameworks and agile practices to deliver scalable, high-performing solutions tailored to speci... | X58: 429 | Y58: 2.66 | Z58: =FALSE() -> FALSE | AA58: =TRUE() -> TRUE | AB58: =FALSE() -> FALSE | AC58: =FALSE() -> FALSE | AD58: =TRUE() -> TRUE | AE58: 3 | AF58: 42.9 | AG58: Uncertain | AH58: https://in.linkedin.com/jobs/view/custom-software-engineer-at-accenture-in-india-4371897313?trk=public_jobs_topcard-title | AI58: =IF(AND(OR(Company_Explorer!$B$5="All Companies",$E58=Company_Explorer!$B$5),OR(Company_Explorer!$B$6="All Platforms",$B58=Company_Explorer!$B$6),OR(Company_Explorer!$B$7="All Roles",$D58=Company_Explorer!$B$7),OR(Company_Explorer!$B$8="All Ghost Labels",$AG58=Company_Explorer!$B$8)),1,0) -> 0
A59: LI_4371881980 | B59: LinkedIn | C59: Custom Software Engineer | D59: Software Engineer | E59: Accenture in India | F59: =TRUE() -> TRUE | G59: Chennai | H59: Tamil Nadu | I59: 46198 | J59: 46210 | K59: 12 | L59: Full-time | M59: Mid-Senior level | N59: =FALSE() -> FALSE | Q59: N/A | R59: Not provided by LinkedIn scraper | T59: =FALSE() -> FALSE | U59: =FALSE() -> FALSE | V59: 277 | W59: Project Role : Custom Software Engineer Project Role Description : Develop custom software solutions to design, code, and enhance components across systems or applications. Use modern frameworks and agile practices to deliver scalable, high-performing solutions tailored to speci... | X59: 429 | Y59: 2.66 | Z59: =FALSE() -> FALSE | AA59: =TRUE() -> TRUE | AB59: =FALSE() -> FALSE | AC59: =FALSE() -> FALSE | AD59: =TRUE() -> TRUE | AE59: 3 | AF59: 42.9 | AG59: Uncertain | AH59: https://in.linkedin.com/jobs/view/custom-software-engineer-at-accenture-in-india-4371881980?trk=public_jobs_topcard-title | AI59: =IF(AND(OR(Company_Explorer!$B$5="All Companies",$E59=Company_Explorer!$B$5),OR(Company_Explorer!$B$6="All Platforms",$B59=Company_Explorer!$B$6),OR(Company_Explorer!$B$7="All Roles",$D59=Company_Explorer!$B$7),OR(Company_Explorer!$B$8="All Ghost Labels",$AG59=Company_Explorer!$B$8)),1,0) -> 0
A60: LI_4436441593 | B60: LinkedIn | C60: Custom Software Engineer | D60: Software Engineer | E60: Accenture in India | F60: =TRUE() -> TRUE | G60: Indore | H60: Madhya Pradesh | I60: 46206 | J60: 46210 | K60: 4 | L60: Full-time | M60: Mid-Senior level | N60: =FALSE() -> FALSE | Q60: N/A | R60: Not provided by LinkedIn scraper | T60: =FALSE() -> FALSE | U60: =FALSE() -> FALSE | V60: 310 | W60: Project Role : Custom Software Engineer Project Role Description : Develop custom software solutions to design, code, and enhance components across systems or applications. Use modern frameworks and agile practices to deliver scalable, high-performing solutions tailored to speci... | X60: 429 | Y60: 2.66 | Z60: =FALSE() -> FALSE | AA60: =TRUE() -> TRUE | AB60: =FALSE() -> FALSE | AC60: =FALSE() -> FALSE | AD60: =TRUE() -> TRUE | AE60: 3 | AF60: 42.9 | AG60: Uncertain | AH60: https://in.linkedin.com/jobs/view/custom-software-engineer-at-accenture-in-india-4436441593?trk=public_jobs_topcard-title | AI60: =IF(AND(OR(Company_Explorer!$B$5="All Companies",$E60=Company_Explorer!$B$5),OR(Company_Explorer!$B$6="All Platforms",$B60=Company_Explorer!$B$6),OR(Company_Explorer!$B$7="All Roles",$D60=Company_Explorer!$B$7),OR(Company_Explorer!$B$8="All Ghost Labels",$AG60=Company_Explorer!$B$8)),1,0) -> 0
A61: LI_4426035904 | B61: LinkedIn | C61: Strategic Software Engineer | D61: Software Engineer | E61: Motorola Mobility (a Lenovo Company) | F61: =TRUE() -> TRUE | G61: Bengaluru | H61: Karnataka | I61: 46183 | J61: 46210 | K61: 27 | L61: Full-time | M61: Mid-Senior level | N61: =FALSE() -> FALSE | Q61: N/A | R61: Not provided by LinkedIn scraper | T61: =FALSE() -> FALSE | U61: =FALSE() -> FALSE | V61: 742 | W61: Hello Moto Motorola Mobility, A Lenovo Company, is one of the world’s fastest growing smartphone providers, creating groundbreaking, affordable, high-quality products designed and built with the global customer in mind. And it’s our people who make this all happen. We are thinke... | X61: 1 | Y61: 0.01 | Z61: =FALSE() -> FALSE | AA61: =TRUE() -> TRUE | AB61: =FALSE() -> FALSE | AC61: =TRUE() -> TRUE | AD61: =FALSE() -> FALSE | AE61: 2 | AF61: 28.6 | AG61: Uncertain | AH61: https://in.linkedin.com/jobs/view/strategic-software-engineer-at-motorola-mobility-a-lenovo-company-4426035904?trk=public_jobs_topcard-title | AI61: =IF(AND(OR(Company_Explorer!$B$5="All Companies",$E61=Company_Explorer!$B$5),OR(Company_Explorer!$B$6="All Platforms",$B61=Company_Explorer!$B$6),OR(Company_Explorer!$B$7="All Roles",$D61=Company_Explorer!$B$7),OR(Company_Explorer!$B$8="All Ghost Labels",$AG61=Company_Explorer!$B$8)),1,0) -> 0
A62: LI_4372101041 | B62: LinkedIn | C62: Custom Software Engineer | D62: Software Engineer | E62: Accenture in India | F62: =TRUE() -> TRUE | G62: Chennai | H62: Tamil Nadu | I62: 46198 | J62: 46210 | K62: 12 | L62: Full-time | M62: Mid-Senior level | N62: =FALSE() -> FALSE | Q62: N/A | R62: Not provided by LinkedIn scraper | T62: =FALSE() -> FALSE | U62: =FALSE() -> FALSE | V62: 277 | W62: Project Role : Custom Software Engineer Project Role Description : Develop custom software solutions to design, code, and enhance components across systems or applications. Use modern frameworks and agile practices to deliver scalable, high-performing solutions tailored to speci... | X62: 429 | Y62: 2.66 | Z62: =FALSE() -> FALSE | AA62: =TRUE() -> TRUE | AB62: =FALSE() -> FALSE | AC62: =FALSE() -> FALSE | AD62: =TRUE() -> TRUE | AE62: 3 | AF62: 42.9 | AG62: Uncertain | AH62: https://in.linkedin.com/jobs/view/custom-software-engineer-at-accenture-in-india-4372101041?trk=public_jobs_topcard-title | AI62: =IF(AND(OR(Company_Explorer!$B$5="All Companies",$E62=Company_Explorer!$B$5),OR(Company_Explorer!$B$6="All Platforms",$B62=Company_Explorer!$B$6),OR(Company_Explorer!$B$7="All Roles",$D62=Company_Explorer!$B$7),OR(Company_Explorer!$B$8="All Ghost Labels",$AG62=Company_Explorer!$B$8)),1,0) -> 0
